Workbook
Name Climate: Settings!$C$10
Name Country: Settings!$C$7
Name Development_status: Settings!$C$9
Name Region: Settings!$C$8
Name Year: Settings!$C$6
Name Year1: Settings!$C$13
Name Year2: Settings!$C$14
Name Year3: Settings!$C$15

Sheet Intro
B1: ="This workbook contains the baseline of the "&B17&" sectors energy flow" -> This workbook contains the baseline of the Afolu sectors energy flow
B4: Color coding:
C5: TIMES input files, imports data from blue sheets only
C6: Calculation sheets, used for calculating values, such as stocks, full load hours, etc. based on raw input data and default values.
C7: Default values either country specific values or international average values.
C8: Input of raw data from the statistics
C10: Cells containing parameter values
B13: Model specific information
B16: 2022 | C16: insert base modelling year
B17: Afolu | C17: Insert main sector name
B18: AFO | C18: insert short sector name
B20: Total overview of regions within the model
B21: Region number | C21: 1 | D21: 2 | E21: 3 | F21: 4 | G21: 5 | H21: 6 | I21: 7 | J21: 8 | K21: 9 | L21: 10 | M21: 11 | N21: 12 | O21: 13 | P21: 14 | Q21: 15 | R21: 16 | S21: 17 | T21: 18 | U21: 19 | V21: 20 | W21: 21 | X21: 22 | Y21: 23 | Z21: 24 | AA21: 25 | AB21: 26 | AC21: 27 | AD21: 28 | AE21: 29 | AF21: 30
B22: Region name | C22: REG1
B25: Calibration to match existing national Emission Inventory
B27: Total AFOLU sectors emissions | G27: Emission inventory values | L27: Calibration factor
E28: 2019 | J28: =$B$16 -> 2022 | O28: =$B$16 -> 2022
B29: CH4 | G29: CH4 | L29: CH4 | O29: 1
B30: N2O | G30: N2O | L30: N2O | O30: 1
B31: CO2 | G31: CO2 | L31: CO2 | O31: 1
B32: CO2sinks (negative from e.g. Forest) | G32: CO2sinks (negative from e.g. Forrest) | L32: CO2sinks (negative from e.g. Forrest) | O32: 1
B53: Illustration of residential sectors energy flow
B72: Trademark/Legal stuff

Sheet Settings
B1: Settings
Q4: Conversion factors
C5: Select: | G5: Country list | I5: Region types | K5: Development status | M5: Climate type
B6: Year | C6: 2022 | G6: Afghanistan | I6: North America | K6: Developing country | M6: Temperate | Q6: 1000000000 | R6: liters/Mm3
B7: Country | C7: Sweden | G7: Albania | I7: Western Europe | K7: Developed country | M7: Warm | Q7: 0.0001 | R7: ton/hg
B8: Region | C8: Europe | G8: Algeria | I8: Eastern Europe | M8: Cool | Q8: =10^(-3) -> 0.001 | R8: TJ/GJ
B9: Development | C9: Developed country | G9: American Samoa | I9: Oceania
B10: Climate | C10: Cool | G10: Andorra | I10: Latin America
G11: Angola | I11: Africa
G12: Anguilla | I12: Middle East
G13: Antigua and Barbuda | I13: Asia
G14: Argentina
G15: Armenia
G16: Aruba
G17: Australia
G18: Austria
G19: Azerbaijan
G20: Bahamas
G21: Bahrain
G22: Bangladesh
G23: Barbados
G24: Belarus
G25: Belgium
... G244: Zimbabwe

Sheet Lookup tables
A1: Lookup tables
A3: Crop name (FAO database) | B3: IPCC Category | D3: Crop name (FAO crop calendar) | E3: IPCC Category | G3: Animal names (FAO) | H3: Animal names (FAOSTAT) | I3: Animal names (CH4 table EFDB IPCC) | J3: Animal names (N2O table EFDB IPCC) | L3: Cerial names | M3: Biomass names
A4: Barley | B4: Cereals | D4: Bananas | E4: Woody crops | G4: Asses | H4: Asses | I4: Mules and Asses | J4: Other animals | L4: Barley | M4: Barley straw
A5: Olives | B5: Woody crops | D5: Bananas | E5: Woody crops | G5: Camels | H5: Camels | I5: Camels | J5: Other animals | L5: Wheat | M5: Wheat straw
A6: Wheat | B6: Cereals | D6: Bananas and plantains | E6: Woody crops | G6: Cattle, dairy | H6: Cattle, dairy | I6: Dairy cows | J6: Dairy cattle | L6: Oats | M6: Oat straw
A7: Grapes | B7: Woody crops | D7: Bananas˚ | E7: Woody crops | G7: Cattle, non-dairy | H7: Cattle, non-dairy | I7: Other cattle | J7: Non-dairy cattle | L7: Maize (corn) | M7: Maize cob
A8: Almonds, in shell | B8: Woody crops | D8: Barley | E8: Cereals | G8: Goats | H8: Goats | I8: Goats | J8: Other animals | L8: Triticale | M8: Average
A9: Sunflower seed | B9: Seeds | D9: Barley | E9: Cereals | G9: Horses | H9: Horses | I9: Horses | J9: Other animals | L9: Rye | M9: Rye straw
A10: Oats | B10: Cereals | D10: Barley and other cereals | E10: Cereals | G10: Mules and hinnies | H10: Mules and hinnies | I10: Mules and Asses | J10: Other animals | L10: Mixed grain | M10: Average
A11: Maize (corn) | B11: Cereals | D11: Barley and other cereals | E11: Cereals | G11: Sheep | H11: Sheep | I11: Sheep | J11: Sheep | L11: Cereals n.e.c. | M11: Average
A12: Triticale | B12: Cereals | D12: Barley and wheat | E12: Cereals | G12: Buffalo | H12: Buffalo | I12: Buffalo | J12: Other animals | L12: Sorghum | M12: Sorghum straw/stalk
A13: Other pulses n.e.c. | B13: Legumes | D13: Barley spring | E13: Cereals | G13: Swine, breeding | H13: Swine, breeding | I13: Swine | J13: Swine | L13: Buckwheat | M13: Average
A14: Oranges | B14: Woody crops | D14: Barley winter | E14: Cereals | G14: Swine, market | H14: Swine, market | I14: Swine | J14: Swine | L14: Fonio | M14: Average
... A18: Rice | B18: Rice | D18: Cereals 1 | E18: Cereals | G18: Poultry | H18: Poultries | I18: Ducks | J18: Ducks | L18: Rice | M18: Rice straw
A19: Peaches and nectarines | B19: Woody crops | D19: Cereals 2 | E19: Cereals | G19: Poultry | H19: Ducks | I19: Turkeys | J19: Turkeys
A20: Rape or colza seed | B20: Seeds | D20: Citrus | E20: Woody crops | G20: Poultry | H20: Turkeys
A21: Potatoes | B21: Roots | D21: Citrus | E21: Woody crops
A22: Tomatoes | B22: Vegetables | D22: Citrus ˚ | E22: Woody crops
A23: Other nuts (excluding wild edible nuts and groundnuts), in shell, n.e.c. | B23: Woody crops | D23: Citrus˚ | E23: Woody crops
A24: Lemons and limes | B24: Woody crops | D24: Cocoa | E24: Woody crops
A25: Mixed grain | B25: Cereals | D25: Coconut | E25: Woody crops
A26: Cauliflowers and broccoli | B26: Vegetables | D26: Coffee | E26: Woody crops
A27: Chestnuts, in shell | B27: Woody crops | D27: Coffee | E27: Woody crops
A28: Lettuce and chicory | B28: Herbs and greens | D28: Coffee˚ | E28: Woody crops
A29: Other tropical fruits, n.e.c. | B29: Woody crops | D29: Cotton | E29: Fiber crops
A30: Apples | B30: Woody crops | D30: Cotton | E30: Fiber crops
A31: Green garlic | B31: Vegetables | D31: Cotton˚ | E31: Fiber crops
A32: Cherries | B32: Woody crops | D32: Date palm | E32: Woody crops
... A161: Yautia | B161: Roots | D161: Sugar beets | E161: Roots
D162: Sugar beets˚ | E162: Roots
D163: Sugarcane | E163: Vegetables
D164: Sugarcane | E164: Vegetables
D165: Sugarcane˚ | E165: Vegetables
D166: Summer cereals | E166: Cereals
D167: Sunflower | E167: Seeds
D168: Sunflower | E168: Seeds
D169: Sunflower˚ | E169: Seeds
D170: Sunflowers | E170: Seeds
D171: Sweet potatoes | E171: Roots
D172: Sweet potatoes | E172: Roots
D173: Sweet potatoes one | E173: Roots
... D204: Yuca | E204: Roots
D209: Total irrigated area (1000 ha)
D211: Data year
D212: Country Name

Sheet Fuel-Technology
A1: This sheet contains the commodities definitions for the AFOLU sector
B3: ~FI_Comm | H3: ~FI_Process | T3: ~FI_T
B4: CSet | C4: CommName | D4: CommDesc | E4: Unit | F4: LimType | H4: Sets | I4: TechName | J4: TechDesc | K4: Tact | L4: Tcap | M4: Tslvl | N4: Vintage | P4: TechName | Q4: *TechDesc | R4: Comm-IN | S4: Comm-OUT | T4: CAP2ACT | U4: EFF | V4: AFA | W4: LIFE
B5: \I: | C5: Name | D5: Description | E5: Activity | H5: \I: | I5: Name | J5: Description | K5: Activity | L5: Capacity | M5: Timeslice levels | N5: Tracking of investment year | P5: \I: Unit | S5: Kha | T5: KhaA/kha | U5: TJ/kha | V5: Annual aviability | W5: Years
B6: ENV | C6: AFOBGACH4 | D6: Biogas - CH4 reduction | E6: ktCH4 | H6: PRE | I6: MINWTR | J6: Mining Of Water | K6: Mm3 | L6: Mm3 | M6: Annual | N6: NO | P6: MINWTR | Q6: =J6 -> Mining Of Water | S6: WTRAFO | T6: 1 | U6: 1 | V6: 1 | W6: 100
B7: ENV | C7: AFOBGAN2O | D7: Biogas - N2O reduction | E7: ktN2O
B8: ENV | C8: AFOCRPCH4 | D8: Crop CH4 | E8: ktCH4
B9: ENV | C9: AFOCRPCO2 | D9: Crop CO2 | E9: ktCO2
B10: ENV | C10: AFOCRPN2O | D10: Crop N2O | E10: ktN2O
B11: ENV | C11: AFOFRSCO2 | D11: Forest CO2 | E11: ktCO2
B12: ENV | C12: AFOLIVCH4 | D12: Livestock - enteric fermentation | E12: ktCH4
B13: ENV | C13: AFOMNRCH4 | D13: Livestock - manure management CH4 | E13: ktCH4
B14: ENV | C14: AFOMNRN2O | D14: Livestock - manure management N2O | E14: ktN2O
B15: ENV | C15: AFOPASN2O | D15: Pasture N2O | E15: ktN2O
B16: ENV | C16: GHGAFO | D16: Total AFOLU GHG Emission | E16: kt CO2e
B17: ENV | C17: GHGAFOCH4 | D17: GHG Emissions Agriculture AFOLU CH4 Emissions kt CO2e | E17: kt CO2e
B18: ENV | C18: GHGAFOCO2 | D18: GHG Emissions Agriculture AFOLU CO2 Emissions kt CO2e | E18: kt CO2e
... B30: MAT | C30: AFOPASGEP | D30: Pasture land | E30: kha
B31: MAT | C31: CADMNR | D31: Cattle Dairy Manure | E31: ktCH4 | F31: FX
B32: MAT | C32: CADMNRNNN | D32: Cattle Dairy Manure No Treatment | E32: ktCH4 | F32: FX
B33: MAT | C33: CADMNRANN | D33: Cattle Dairy Manure Acidification | E33: ktCH4 | F33: FX
B34: MAT | C34: CADMNRNDN | D34: Cattle Dairy Manure Daily_Weekly_Manure_Removal | E34: ktCH4 | F34: FX
B35: MAT | C35: CADMNRNNM | D35: Cattle Dairy Manure Manure_Storage_Covers | E35: ktCH4 | F35: FX
B36: MAT | C36: CADMNRADN | D36: Cattle Dairy Manure Acidification + Daily_Weekly_Manure_Removal | E36: ktCH4 | F36: FX
B37: MAT | C37: CADMNRNDM | D37: Cattle Dairy Manure Acidification + Manure_Storage_Covers | E37: ktCH4 | F37: FX
B38: MAT | C38: CADMNRANM | D38: Cattle Dairy Manure Daily_Weekly_Manure_Removal + Manure_Storage_Covers | E38: ktCH4 | F38: FX
B39: MAT | C39: CADMNRADM | D39: Cattle Dairy Manure Acidification + Daily_Weekly_Manure_Removal + Manure_Storage_Covers | E39: ktCH4 | F39: FX
B40: MAT | C40: CANMNR | D40: Cattle Non Dairy Manure | E40: ktCH4 | F40: FX
B41: MAT | C41: CANMNRNNN | D41: Cattle Non Dairy Manure No Treatment | E41: ktCH4 | F41: FX
B42: MAT | C42: CANMNRANN | D42: Cattle Non Dairy Manure Acidification | E42: ktCH4 | F42: FX
... B48: MAT | C48: CANMNRADM | D48: Cattle Non Dairy Manure Acidification + Daily_Weekly_Manure_Removal + Manure_Storage_Covers | E48: ktCH4 | F48: FX
B49: MAT | C49: CERSTR | D49: Cereal straw | E49: Mton
B50: MAT | C50: FCRWSB | D50: Fiber crops straw | E50: Mton
B51: MAT | C51: FRSFIW | D51: Forest area with FIW | E51: kha
B52: MAT | C52: FRSNATGEF | D52: Naturally regenerating | E52: kha
B53: MAT | C53: FRSPLAGEF | D53: Planted | E53: kha
B54: MAT | C54: FRSWOC | D54: Forest area with WOC | E54: kha
B55: MAT | C55: FRSWOP | D55: Forest area with WOP | E55: kha
B56: MAT | C56: HAGWSB | D56: Herbs and greens straw | E56: Mton
B57: MAT | C57: LEGWSB | D57: Legumes straw | E57: Mton
B58: MAT | C58: RICSTR | D58: Rice straw | E58: Mton
B59: MAT | C59: ROOWSB | D59: Roots straw | E59: Mton
B60: MAT | C60: SEEWSB | D60: Seed straw | E60: Mton
B61: MAT | C61: SWBMNR | D61: Swine Breeding Manure | E61: ktCH4 | F61: FX
B62: MAT | C62: SWBMNRNNN | D62: Swine Breeding Manure No Treatment | E62: ktCH4 | F62: FX
B63: MAT | C63: SWBMNRANN | D63: Swine Breeding Manure Acidification | E63: ktCH4 | F63: FX
B64: MAT | C64: SWBMNRNDN | D64: Swine Breeding Manure Daily_Weekly_Manure_Removal | E64: ktCH4 | F64: FX
B65: MAT | C65: SWBMNRNNM | D65: Swine Breeding Manure Manure_Storage_Covers | E65: ktCH4 | F65: FX
B66: MAT | C66: SWBMNRADN | D66: Swine Breeding Manure Acidification + Daily_Weekly_Manure_Removal | E66: ktCH4 | F66: FX
B67: MAT | C67: SWBMNRNDM | D67: Swine Breeding Manure Acidification + Manure_Storage_Covers | E67: ktCH4 | F67: FX
B68: MAT | C68: SWBMNRANM | D68: Swine Breeding Manure Daily_Weekly_Manure_Removal + Manure_Storage_Covers | E68: ktCH4 | F68: FX
B69: MAT | C69: SWBMNRADM | D69: Swine Breeding Manure Acidification + Daily_Weekly_Manure_Removal + Manure_Storage_Covers | E69: ktCH4 | F69: FX
B70: MAT | C70: SWMMNR | D70: Swine Market Manure | E70: ktCH4 | F70: FX
B71: MAT | C71: SWMMNRNNN | D71: Swine Market Manure No Treatment | E71: ktCH4 | F71: FX
B72: MAT | C72: SWMMNRANN | D72: Swine Market Manure Acidification | E72: ktCH4 | F72: FX
... B78: MAT | C78: SWMMNRADM | D78: Swine Market Manure Acidification + Daily_Weekly_Manure_Removal + Manure_Storage_Covers | E78: ktCH4 | F78: FX
B79: MAT | C79: VEGWSB | D79: Vegetables straw | E79: Mton
B80: MAT | C80: WCRWOC | D80: Woody crops straw | E80: Mton
B81: MAT | C81: WTRAFO | D81: Water | E81: Mm3
B82: NRG | C82: MNR | D82: Manure for energy use | E82: TJ
B83: NRG | C83: WOC | D83: Wood chips | E83: TJ
B84: NRG | C84: WOP | D84: Wood pellets | E84: TJ
B85: NRG | C85: FIW | D85: Fire wood | E85: TJ
B86: NRG | C86: STR | D86: Straw | E86: TJ
B87: NRG | C87: WSA | D87: Agricultural waste | E87: TJ

Sheet Crops
A1: This sheet contains the Crop technologies
B5: ~FI_Process | K5: ~FI_T
B6: Sets | C6: TechName | D6: TechDesc | E6: Techtype long | F6: Option long | G6: Tact | H6: Tcap | I6: Tslvl | K6: TechName | L6: *TechDesc | M6: Comm-IN | N6: Comm-OUT | O6: Comm-OUT-A | P6: CAP2ACT | Q6: EFF | R6: AFA~FX | S6: LIFE | T6: START | U6: OUTPUT | V6: EMISSIONS~AFOCRPCO2 | W6: EMISSIONS~AFOCRPCH4 | X6: EMISSIONS~AFOCRPN2O | Y6: NCAP_PASTI | Z6: FIXOM | AA6: NCAP_COST
B7: * | C7: Name | D7: Description | G7: Activity | H7: Capacity | I7: Timeslice levels | K7: \I: Unit | M7: Mm3 | N7: Mton | O7: TJ | P7: Mton/kha | Q7: Mton/Mm3 | R7: Annual aviability | S7: Years | T7: Year | U7: Mton/Mton | V7: ktCO2/Mton | W7: ktCH4/Mton | X7: ktN2O/Mton | Y7: *kha | Z7: MEUR/kha | AA7: MEUR/kha
B8: =IF(Y8=0,"\I:","DMD") -> DMD | C8: AFOCRPOFICERWTRE0 | D8: Afolu Crops Open Field Cereals Existing 0 | E8: Open Field | F8: Cereals | G8: Mton | H8: kha | I8: Annual | K8: =IF(Y8="","\I:",C8) -> AFOCRPOFICERWTRE0 | L8: Afolu Crops Open Field Cereals Existing 0 | M8: WTRAFO | N8: AFOCRPCERDEM | P8: =IF(IFERROR(VLOOKUP($K8,'Calc - Crops'!$L$24:$Y$47,8,FALSE)," ")=0," ",IFERROR(VLOOKUP($K8,'Calc - Crops'!$L$24:$Y$47,8,FALSE)/1000," ")) -> 0.00061073654 | Q8: =IF(IFERROR(P8/(IFERROR(VLOOKUP(F8,'Calc - water'!$B$39:$G$48,6,FALSE),"")*IFERROR(VLOOKUP(E8,DefaultAFOLU!$C$32:$G$39,5,FALSE),"")),"")=0," ",IFERROR(P8/(IFERROR(VLOOKUP(F8,'Calc - water'!$B$39:$G$48,6,FALSE),"")*IFERROR(VLOOKUP(E8,DefaultAFOLU!$C$32:$G$39,5,FALSE),"")),"")) -> 6.1073654 | R8: 1 | S8: 4 | T8: =IF(Y8=0,Intro!$B$16+1,"") | V8: =IF(IFERROR(VLOOKUP($K8,'Calc - Crops'!$L$24:$Y$47,11,FALSE)," ")=0," ",IFERROR(VLOOKUP($K8,'Calc - Crops'!$L$24:$Y$47,11,FALSE)/$P8," ")) -> 13374.1 | W8: =IF(IFERROR(VLOOKUP($K8,'Calc - Crops'!$L$24:$Y$47,10,FALSE)," ")=0," ",IFERROR(VLOOKUP($K8,'Calc - Crops'!$L$24:$Y$47,10,FALSE)/$P8," ")) -> 0.68463386 | X8: =IF(IFERROR(VLOOKUP($K8,'Calc - Crops'!$L$24:$Y$47,9,FALSE)," ")=0," ",IFERROR(VLOOKUP($K8,'Calc - Crops'!$L$24:$Y$47,9,FALSE)/$P8," ")) -> 18.664672 | Y8: =IFERROR(VLOOKUP($C8,'Calc - Crops'!$L$24:$Y$47,2,FALSE)/1000, " ") -> 953.47 | Z8: =IF(E8<>"",SUMIFS('Input data - Other'!$F:$F,'Input data - Other'!$B:$B,Crops!Z$6,'Input data - Other'!$D:$D,Crops!$E8),"") -> 0.156 | AA8: =IF(F8<>"",SUMIFS('Input data - Other'!$F:$F,'Input data - Other'!$B:$B,Crops!AA$6,'Input data - Other'!$D:$D,Crops!$E8),"") -> 0
B9: \I: | K9: =IF(Y8="","\I:"," ") | O9: CERSTR | P9: =IF(IFERROR(VLOOKUP($K9,'Calc - Crops'!$L$24:$Y$47,8,FALSE)," ")=0," ",IFERROR(VLOOKUP($K9,'Calc - Crops'!$L$24:$Y$47,8,FALSE)/1000," ")) | Q9: =IF(IFERROR(P9/(IFERROR(VLOOKUP(F9,'Calc - water'!$B$39:$G$48,6,FALSE),"")*IFERROR(VLOOKUP(E9,DefaultAFOLU!$C$32:$G$39,5,FALSE),"")),"")=0," ",IFERROR(P9/(IFERROR(VLOOKUP(F9,'Calc - water'!$B$39:$G$48,6,FALSE),"")*IFERROR(VLOOKUP(E9,DefaultAFOLU!$C$32:$G$39,5,FALSE),"")),"")) | T9: =IF(Y9=0,Intro!$B$16+1,"") | U9: =IFERROR(VLOOKUP(O9,DefaultAFOLU!$D$42:$G$50,4,TRUE)," ") -> 0.3 | V9: =IF(IFERROR(VLOOKUP($K9,'Calc - Crops'!$L$24:$Y$47,11,FALSE)," ")=0," ",IFERROR(VLOOKUP($K9,'Calc - Crops'!$L$24:$Y$47,11,FALSE)/$P9," ")) | W9: =IF(IFERROR(VLOOKUP($K9,'Calc - Crops'!$L$24:$Y$47,10,FALSE)," ")=0," ",IFERROR(VLOOKUP($K9,'Calc - Crops'!$L$24:$Y$47,10,FALSE)/$P9," ")) | X9: =IF(IFERROR(VLOOKUP($K9,'Calc - Crops'!$L$24:$Y$47,9,FALSE)," ")=0," ",IFERROR(VLOOKUP($K9,'Calc - Crops'!$L$24:$Y$47,9,FALSE)/$P9," ")) | Y9: =IFERROR(VLOOKUP($C9,'Calc - Crops'!$L$24:$Y$47,2,FALSE)/1000, " ") | Z9: =IF(E9<>"",SUMIFS('Input data - Other'!$F:$F,'Input data - Other'!$B:$B,Crops!Z$6,'Input data - Other'!$D:$D,Crops!$E9),"") | AA9: =IF(F9<>"",SUMIFS('Input data - Other'!$F:$F,'Input data - Other'!$B:$B,Crops!AA$6,'Input data - Other'!$D:$D,Crops!$E9),"")
B10: =IF(Y10=0,"\I:","DMD") -> \I: | C10: AFOCRPOFIRICWTRE0 | D10: Afolu Crops Open Field Rice Existing 0 | E10: Open Field | F10: Rice | G10: Mton | H10: kha | I10: Annual | K10: =IF(Y10=0,"\I:",C10) -> \I: | L10: Afolu Crops Open Field Rice Existing 0 | M10: WTRAFO | N10: AFOCRPRICDEM | P10: =IF(IFERROR(VLOOKUP($K10,'Calc - Crops'!$L$24:$Y$47,8,FALSE)," ")=0," ",IFERROR(VLOOKUP($K10,'Calc - Crops'!$L$24:$Y$47,8,FALSE)/1000," ")) | Q10: =IF(IFERROR(P10/(IFERROR(VLOOKUP(F10,'Calc - water'!$B$39:$G$48,6,FALSE),"")*IFERROR(VLOOKUP(E10,DefaultAFOLU!$C$32:$G$39,5,FALSE),"")),"")=0," ",IFERROR(P10/(IFERROR(VLOOKUP(F10,'Calc - water'!$B$39:$G$48,6,FALSE),"")*IFERROR(VLOOKUP(E10,DefaultAFOLU!$C$32:$G$39,5,FALSE),"")),"")) | R10: 1 | S10: 4 | T10: =IF(Y10=0,Intro!$B$16+1,"") -> 2023 | V10: =IF(IFERROR(VLOOKUP($K10,'Calc - Crops'!$L$24:$Y$47,11,FALSE)," ")=0," ",IFERROR(VLOOKUP($K10,'Calc - Crops'!$L$24:$Y$47,11,FALSE)/$P10," ")) | W10: =IF(IFERROR(VLOOKUP($K10,'Calc - Crops'!$L$24:$Y$47,10,FALSE)," ")=0," ",IFERROR(VLOOKUP($K10,'Calc - Crops'!$L$24:$Y$47,10,FALSE)/$P10," ")) | X10: =IF(IFERROR(VLOOKUP($K10,'Calc - Crops'!$L$24:$Y$47,9,FALSE)," ")=0," ",IFERROR(VLOOKUP($K10,'Calc - Crops'!$L$24:$Y$47,9,FALSE)/$P10," ")) | Y10: =IFERROR(VLOOKUP($C10,'Calc - Crops'!$L$24:$Y$47,2,FALSE)/1000, " ") -> 0 | Z10: =IF(E10<>"",SUMIFS('Input data - Other'!$F:$F,'Input data - Other'!$B:$B,Crops!Z$6,'Input data - Other'!$D:$D,Crops!$E10),"") -> 0.156 | AA10: =IF(F10<>"",SUMIFS('Input data - Other'!$F:$F,'Input data - Other'!$B:$B,Crops!AA$6,'Input data - Other'!$D:$D,Crops!$E10),"") -> 0
B11: \I: | K11: =IF(Y10=0,"\I:"," ") -> \I: | O11: RICSTR | P11: =IF(IFERROR(VLOOKUP($K11,'Calc - Crops'!$L$24:$Y$47,8,FALSE)," ")=0," ",IFERROR(VLOOKUP($K11,'Calc - Crops'!$L$24:$Y$47,8,FALSE)/1000," ")) | Q11: =IF(IFERROR(P11/(IFERROR(VLOOKUP(F11,'Calc - water'!$B$39:$G$48,6,FALSE),"")*IFERROR(VLOOKUP(E11,DefaultAFOLU!$C$32:$G$39,5,FALSE),"")),"")=0," ",IFERROR(P11/(IFERROR(VLOOKUP(F11,'Calc - water'!$B$39:$G$48,6,FALSE),"")*IFERROR(VLOOKUP(E11,DefaultAFOLU!$C$32:$G$39,5,FALSE),"")),"")) | T11: =IF(Y11=0,Intro!$B$16+1,"") | U11: =IFERROR(VLOOKUP(O11,DefaultAFOLU!$D$42:$G$50,4,TRUE)," ") -> 0.3 | V11: =IF(IFERROR(VLOOKUP($K11,'Calc - Crops'!$L$24:$Y$47,11,FALSE)," ")=0," ",IFERROR(VLOOKUP($K11,'Calc - Crops'!$L$24:$Y$47,11,FALSE)/$P11," ")) | W11: =IF(IFERROR(VLOOKUP($K11,'Calc - Crops'!$L$24:$Y$47,10,FALSE)," ")=0," ",IFERROR(VLOOKUP($K11,'Calc - Crops'!$L$24:$Y$47,10,FALSE)/$P11," ")) | X11: =IF(IFERROR(VLOOKUP($K11,'Calc - Crops'!$L$24:$Y$47,9,FALSE)," ")=0," ",IFERROR(VLOOKUP($K11,'Calc - Crops'!$L$24:$Y$47,9,FALSE)/$P11," ")) | Y11: =IFERROR(VLOOKUP($C11,'Calc - Crops'!$L$24:$Y$47,2,FALSE)/1000, " ") | Z11: =IF(E11<>"",SUMIFS('Input data - Other'!$F:$F,'Input data - Other'!$B:$B,Crops!Z$6,'Input data - Other'!$D:$D,Crops!$E11),"") | AA11: =IF(F11<>"",SUMIFS('Input data - Other'!$F:$F,'Input data - Other'!$B:$B,Crops!AA$6,'Input data - Other'!$D:$D,Crops!$E11),"")
B12: =IF(Y12=0,"\I:","DMD") -> DMD | C12: AFOCRPOFILEGWTRE0 | D12: Afolu Crops Open Field Legumes Existing 0 | E12: Open Field | F12: Legumes | G12: Mton | H12: kha | I12: Annual | K12: =IF(Y12=0,"\I:",C12) -> AFOCRPOFILEGWTRE0 | L12: Afolu Crops Open Field Legumes Existing 0 | M12: WTRAFO | N12: AFOCRPLEGDEM | P12: =IF(IFERROR(VLOOKUP($K12,'Calc - Crops'!$L$24:$Y$47,8,FALSE)," ")=0," ",IFERROR(VLOOKUP($K12,'Calc - Crops'!$L$24:$Y$47,8,FALSE)/1000," ")) -> 0.00033219646 | Q12: =IF(IFERROR(P12/(IFERROR(VLOOKUP(F12,'Calc - water'!$B$39:$G$48,6,FALSE),"")*IFERROR(VLOOKUP(E12,DefaultAFOLU!$C$32:$G$39,5,FALSE),"")),"")=0," ",IFERROR(P12/(IFERROR(VLOOKUP(F12,'Calc - water'!$B$39:$G$48,6,FALSE),"")*IFERROR(VLOOKUP(E12,DefaultAFOLU!$C$32:$G$39,5,FALSE),"")),"")) -> 0.0067046943 | R12: 1 | S12: 4 | T12: =IF(Y12=0,Intro!$B$16+1,"") | V12: =IF(IFERROR(VLOOKUP($K12,'Calc - Crops'!$L$24:$Y$47,11,FALSE)," ")=0," ",IFERROR(VLOOKUP($K12,'Calc - Crops'!$L$24:$Y$47,11,FALSE)/$P12," ")) -> 24588.015 | W12: =IF(IFERROR(VLOOKUP($K12,'Calc - Crops'!$L$24:$Y$47,10,FALSE)," ")=0," ",IFERROR(VLOOKUP($K12,'Calc - Crops'!$L$24:$Y$47,10,FALSE)/$P12," ")) -> 1.2586856 | X12: =IF(IFERROR(VLOOKUP($K12,'Calc - Crops'!$L$24:$Y$47,9,FALSE)," ")=0," ",IFERROR(VLOOKUP($K12,'Calc - Crops'!$L$24:$Y$47,9,FALSE)/$P12," ")) -> 34.314626 | Y12: =IFERROR(VLOOKUP($C12,'Calc - Crops'!$L$24:$Y$47,2,FALSE)/1000, " ") -> 58.08 | Z12: =IF(E12<>"",SUMIFS('Input data - Other'!$F:$F,'Input data - Other'!$B:$B,Crops!Z$6,'Input data - Other'!$D:$D,Crops!$E12),"") -> 0.156 | AA12: =IF(F12<>"",SUMIFS('Input data - Other'!$F:$F,'Input data - Other'!$B:$B,Crops!AA$6,'Input data - Other'!$D:$D,Crops!$E12),"") -> 0
B13: \I: | K13: =IF(Y12=0,"\I:"," ") | O13: LEGWSB | P13: =IF(IFERROR(VLOOKUP($K13,'Calc - Crops'!$L$24:$Y$47,8,FALSE)," ")=0," ",IFERROR(VLOOKUP($K13,'Calc - Crops'!$L$24:$Y$47,8,FALSE)/1000," ")) | Q13: =IF(IFERROR(P13/(IFERROR(VLOOKUP(F13,'Calc - water'!$B$39:$G$48,6,FALSE),"")*IFERROR(VLOOKUP(E13,DefaultAFOLU!$C$32:$G$39,5,FALSE),"")),"")=0," ",IFERROR(P13/(IFERROR(VLOOKUP(F13,'Calc - water'!$B$39:$G$48,6,FALSE),"")*IFERROR(VLOOKUP(E13,DefaultAFOLU!$C$32:$G$39,5,FALSE),"")),"")) | T13: =IF(Y13=0,Intro!$B$16+1,"") | U13: =IFERROR(VLOOKUP(O13,DefaultAFOLU!$D$42:$G$50,4,TRUE)," ") -> 0.3 | V13: =IF(IFERROR(VLOOKUP($K13,'Calc - Crops'!$L$24:$Y$47,11,FALSE)," ")=0," ",IFERROR(VLOOKUP($K13,'Calc - Crops'!$L$24:$Y$47,11,FALSE)/$P13," ")) | W13: =IF(IFERROR(VLOOKUP($K13,'Calc - Crops'!$L$24:$Y$47,10,FALSE)," ")=0," ",IFERROR(VLOOKUP($K13,'Calc - Crops'!$L$24:$Y$47,10,FALSE)/$P13," ")) | X13: =IF(IFERROR(VLOOKUP($K13,'Calc - Crops'!$L$24:$Y$47,9,FALSE)," ")=0," ",IFERROR(VLOOKUP($K13,'Calc - Crops'!$L$24:$Y$47,9,FALSE)/$P13," ")) | Y13: =IFERROR(VLOOKUP($C13,'Calc - Crops'!$L$24:$Y$47,2,FALSE)/1000, " ") | Z13: =IF(E13<>"",SUMIFS('Input data - Other'!$F:$F,'Input data - Other'!$B:$B,Crops!Z$6,'Input data - Other'!$D:$D,Crops!$E13),"") | AA13: =IF(F13<>"",SUMIFS('Input data - Other'!$F:$F,'Input data - Other'!$B:$B,Crops!AA$6,'Input data - Other'!$D:$D,Crops!$E13),"")
B14: =IF(Y14=0,"\I:","DMD") -> DMD | C14: AFOCRPOFISEEWTRE0 | D14: Afolu Crops Open Field Seeds Existing 0 | E14: Open Field | F14: Seeds | G14: Mton | H14: kha | I14: Annual | K14: =IF(Y14=0,"\I:",C14) -> AFOCRPOFISEEWTRE0 | L14: Afolu Crops Open Field Seeds Existing 0 | M14: WTRAFO | N14: AFOCRPSEEDEM | P14: =IF(IFERROR(VLOOKUP($K14,'Calc - Crops'!$L$24:$Y$47,8,FALSE)," ")=0," ",IFERROR(VLOOKUP($K14,'Calc - Crops'!$L$24:$Y$47,8,FALSE)/1000," ")) -> 0.00033561 | Q14: =IF(IFERROR(P14/(IFERROR(VLOOKUP(F14,'Calc - water'!$B$39:$G$48,6,FALSE),"")*IFERROR(VLOOKUP(E14,DefaultAFOLU!$C$32:$G$39,5,FALSE),"")),"")=0," ",IFERROR(P14/(IFERROR(VLOOKUP(F14,'Calc - water'!$B$39:$G$48,6,FALSE),"")*IFERROR(VLOOKUP(E14,DefaultAFOLU!$C$32:$G$39,5,FALSE),"")),"")) -> 0.0053286797 | R14: 1 | S14: 4 | T14: =IF(Y14=0,Intro!$B$16+1,"") | V14: =IF(IFERROR(VLOOKUP($K14,'Calc - Crops'!$L$24:$Y$47,11,FALSE)," ")=0," ",IFERROR(VLOOKUP($K14,'Calc - Crops'!$L$24:$Y$47,11,FALSE)/$P14," ")) -> 24337.927 | W14: =IF(IFERROR(VLOOKUP($K14,'Calc - Crops'!$L$24:$Y$47,10,FALSE)," ")=0," ",IFERROR(VLOOKUP($K14,'Calc - Crops'!$L$24:$Y$47,10,FALSE)/$P14," ")) -> 1.2458834 | X14: =IF(IFERROR(VLOOKUP($K14,'Calc - Crops'!$L$24:$Y$47,9,FALSE)," ")=0," ",IFERROR(VLOOKUP($K14,'Calc - Crops'!$L$24:$Y$47,9,FALSE)/$P14," ")) -> 33.965607 | Y14: =IFERROR(VLOOKUP($C14,'Calc - Crops'!$L$24:$Y$47,2,FALSE)/1000, " ") -> 127.38 | Z14: =IF(E14<>"",SUMIFS('Input data - Other'!$F:$F,'Input data - Other'!$B:$B,Crops!Z$6,'Input data - Other'!$D:$D,Crops!$E14),"") -> 0.156 | AA14: =IF(F14<>"",SUMIFS('Input data - Other'!$F:$F,'Input data - Other'!$B:$B,Crops!AA$6,'Input data - Other'!$D:$D,Crops!$E14),"") -> 0
B15: \I: | K15: =IF(Y14=0,"\I:"," ") | O15: SEEWSB | P15: =IF(IFERROR(VLOOKUP($K15,'Calc - Crops'!$L$24:$Y$47,8,FALSE)," ")=0," ",IFERROR(VLOOKUP($K15,'Calc - Crops'!$L$24:$Y$47,8,FALSE)/1000," ")) | Q15: =IF(IFERROR(P15/(IFERROR(VLOOKUP(F15,'Calc - water'!$B$39:$G$48,6,FALSE),"")*IFERROR(VLOOKUP(E15,DefaultAFOLU!$C$32:$G$39,5,FALSE),"")),"")=0," ",IFERROR(P15/(IFERROR(VLOOKUP(F15,'Calc - water'!$B$39:$G$48,6,FALSE),"")*IFERROR(VLOOKUP(E15,DefaultAFOLU!$C$32:$G$39,5,FALSE),"")),"")) | T15: =IF(Y15=0,Intro!$B$16+1,"") | U15: =IFERROR(VLOOKUP(O15,DefaultAFOLU!$D$42:$G$50,4,TRUE)," ") -> 0.3 | V15: =IF(IFERROR(VLOOKUP($K15,'Calc - Crops'!$L$24:$Y$47,11,FALSE)," ")=0," ",IFERROR(VLOOKUP($K15,'Calc - Crops'!$L$24:$Y$47,11,FALSE)/$P15," ")) | W15: =IF(IFERROR(VLOOKUP($K15,'Calc - Crops'!$L$24:$Y$47,10,FALSE)," ")=0," ",IFERROR(VLOOKUP($K15,'Calc - Crops'!$L$24:$Y$47,10,FALSE)/$P15," ")) | X15: =IF(IFERROR(VLOOKUP($K15,'Calc - Crops'!$L$24:$Y$47,9,FALSE)," ")=0," ",IFERROR(VLOOKUP($K15,'Calc - Crops'!$L$24:$Y$47,9,FALSE)/$P15," ")) | Y15: =IFERROR(VLOOKUP($C15,'Calc - Crops'!$L$24:$Y$47,2,FALSE)/1000, " ") | Z15: =IF(E15<>"",SUMIFS('Input data - Other'!$F:$F,'Input data - Other'!$B:$B,Crops!Z$6,'Input data - Other'!$D:$D,Crops!$E15),"") | AA15: =IF(F15<>"",SUMIFS('Input data - Other'!$F:$F,'Input data - Other'!$B:$B,Crops!AA$6,'Input data - Other'!$D:$D,Crops!$E15),"")
B16: =IF(Y16=0,"\I:","DMD") -> \I: | C16: AFOCRPOFIFCRWTRE0 | D16: Afolu Crops Open Field Fiber crops Existing 0 | E16: Open Field | F16: Fiber crops | G16: Mton | H16: kha | I16: Annual | K16: =IF(Y16=0,"\I:",C16) -> \I: | L16: Afolu Crops Open Field Fiber crops Existing 0 | M16: WTRAFO | N16: AFOCRPFCRDEM | P16: =IF(IFERROR(VLOOKUP($K16,'Calc - Crops'!$L$24:$Y$47,8,FALSE)," ")=0," ",IFERROR(VLOOKUP($K16,'Calc - Crops'!$L$24:$Y$47,8,FALSE)/1000," ")) | Q16: =IF(IFERROR(P16/(IFERROR(VLOOKUP(F16,'Calc - water'!$B$39:$G$48,6,FALSE),"")*IFERROR(VLOOKUP(E16,DefaultAFOLU!$C$32:$G$39,5,FALSE),"")),"")=0," ",IFERROR(P16/(IFERROR(VLOOKUP(F16,'Calc - water'!$B$39:$G$48,6,FALSE),"")*IFERROR(VLOOKUP(E16,DefaultAFOLU!$C$32:$G$39,5,FALSE),"")),"")) | R16: 1 | S16: 4 | T16: =IF(Y16=0,Intro!$B$16+1,"") -> 2023 | V16: =IF(IFERROR(VLOOKUP($K16,'Calc - Crops'!$L$24:$Y$47,11,FALSE)," ")=0," ",IFERROR(VLOOKUP($K16,'Calc - Crops'!$L$24:$Y$47,11,FALSE)/$P16," ")) | W16: =IF(IFERROR(VLOOKUP($K16,'Calc - Crops'!$L$24:$Y$47,10,FALSE)," ")=0," ",IFERROR(VLOOKUP($K16,'Calc - Crops'!$L$24:$Y$47,10,FALSE)/$P16," ")) | X16: =IF(IFERROR(VLOOKUP($K16,'Calc - Crops'!$L$24:$Y$47,9,FALSE)," ")=0," ",IFERROR(VLOOKUP($K16,'Calc - Crops'!$L$24:$Y$47,9,FALSE)/$P16," ")) | Y16: =IFERROR(VLOOKUP($C16,'Calc - Crops'!$L$24:$Y$47,2,FALSE)/1000, " ") -> 0 | Z16: =IF(E16<>"",SUMIFS('Input data - Other'!$F:$F,'Input data - Other'!$B:$B,Crops!Z$6,'Input data - Other'!$D:$D,Crops!$E16),"") -> 0.156 | AA16: =IF(F16<>"",SUMIFS('Input data - Other'!$F:$F,'Input data - Other'!$B:$B,Crops!AA$6,'Input data - Other'!$D:$D,Crops!$E16),"") -> 0
B17: \I: | K17: =IF(Y16=0,"\I:"," ") -> \I: | O17: FCRWSB | P17: =IF(IFERROR(VLOOKUP($K17,'Calc - Crops'!$L$24:$Y$47,8,FALSE)," ")=0," ",IFERROR(VLOOKUP($K17,'Calc - Crops'!$L$24:$Y$47,8,FALSE)/1000," ")) | Q17: =IF(IFERROR(P17/(IFERROR(VLOOKUP(F17,'Calc - water'!$B$39:$G$48,6,FALSE),"")*IFERROR(VLOOKUP(E17,DefaultAFOLU!$C$32:$G$39,5,FALSE),"")),"")=0," ",IFERROR(P17/(IFERROR(VLOOKUP(F17,'Calc - water'!$B$39:$G$48,6,FALSE),"")*IFERROR(VLOOKUP(E17,DefaultAFOLU!$C$32:$G$39,5,FALSE),"")),"")) | T17: =IF(Y17=0,Intro!$B$16+1,"") | U17: =IFERROR(VLOOKUP(O17,DefaultAFOLU!$D$42:$G$50,4,TRUE)," ") -> 0.3 | V17: =IF(IFERROR(VLOOKUP($K17,'Calc - Crops'!$L$24:$Y$47,11,FALSE)," ")=0," ",IFERROR(VLOOKUP($K17,'Calc - Crops'!$L$24:$Y$47,11,FALSE)/$P17," ")) | W17: =IF(IFERROR(VLOOKUP($K17,'Calc - Crops'!$L$24:$Y$47,10,FALSE)," ")=0," ",IFERROR(VLOOKUP($K17,'Calc - Crops'!$L$24:$Y$47,10,FALSE)/$P17," ")) | X17: =IF(IFERROR(VLOOKUP($K17,'Calc - Crops'!$L$24:$Y$47,9,FALSE)," ")=0," ",IFERROR(VLOOKUP($K17,'Calc - Crops'!$L$24:$Y$47,9,FALSE)/$P17," ")) | Y17: =IFERROR(VLOOKUP($C17,'Calc - Crops'!$L$24:$Y$47,2,FALSE)/1000, " ") | Z17: =IF(E17<>"",SUMIFS('Input data - Other'!$F:$F,'Input data - Other'!$B:$B,Crops!Z$6,'Input data - Other'!$D:$D,Crops!$E17),"") | AA17: =IF(F17<>"",SUMIFS('Input data - Other'!$F:$F,'Input data - Other'!$B:$B,Crops!AA$6,'Input data - Other'!$D:$D,Crops!$E17),"")
B18: =IF(Y18=0,"\I:","DMD") -> DMD | C18: AFOCRPOFIVEGWTRE0 | D18: Afolu Crops Open Field Vegetables Existing 0 | E18: Open Field | F18: Vegetables | G18: Mton | H18: kha | I18: Annual | K18: =IF(Y18=0,"\I:",C18) -> AFOCRPOFIVEGWTRE0 | L18: Afolu Crops Open Field Vegetables Existing 0 | M18: WTRAFO | N18: AFOCRPVEGDEM | P18: =IF(IFERROR(VLOOKUP($K18,'Calc - Crops'!$L$24:$Y$47,8,FALSE)," ")=0," ",IFERROR(VLOOKUP($K18,'Calc - Crops'!$L$24:$Y$47,8,FALSE)/1000," ")) -> 0.0047459946 | Q18: =IF(IFERROR(P18/(IFERROR(VLOOKUP(F18,'Calc - water'!$B$39:$G$48,6,FALSE),"")*IFERROR(VLOOKUP(E18,DefaultAFOLU!$C$32:$G$39,5,FALSE),"")),"")=0," ",IFERROR(P18/(IFERROR(VLOOKUP(F18,'Calc - water'!$B$39:$G$48,6,FALSE),"")*IFERROR(VLOOKUP(E18,DefaultAFOLU!$C$32:$G$39,5,FALSE),"")),"")) -> 0.0056531788 | R18: 1 | S18: 4 | T18: =IF(Y18=0,Intro!$B$16+1,"") | V18: =IF(IFERROR(VLOOKUP($K18,'Calc - Crops'!$L$24:$Y$47,11,FALSE)," ")=0," ",IFERROR(VLOOKUP($K18,'Calc - Crops'!$L$24:$Y$47,11,FALSE)/$P18," ")) -> 1721.0411 | W18: =IF(IFERROR(VLOOKUP($K18,'Calc - Crops'!$L$24:$Y$47,10,FALSE)," ")=0," ",IFERROR(VLOOKUP($K18,'Calc - Crops'!$L$24:$Y$47,10,FALSE)/$P18," ")) -> 0.088101853 | X18: =IF(IFERROR(VLOOKUP($K18,'Calc - Crops'!$L$24:$Y$47,9,FALSE)," ")=0," ",IFERROR(VLOOKUP($K18,'Calc - Crops'!$L$24:$Y$47,9,FALSE)/$P18," ")) -> 2.4018564 | Y18: =IFERROR(VLOOKUP($C18,'Calc - Crops'!$L$24:$Y$47,2,FALSE)/1000, " ") -> 2.576 | Z18: =IF(E18<>"",SUMIFS('Input data - Other'!$F:$F,'Input data - Other'!$B:$B,Crops!Z$6,'Input data - Other'!$D:$D,Crops!$E18),"") -> 0.156 | AA18: =IF(F18<>"",SUMIFS('Input data - Other'!$F:$F,'Input data - Other'!$B:$B,Crops!AA$6,'Input data - Other'!$D:$D,Crops!$E18),"") -> 0
B19: \I: | K19: =IF(Y18=0,"\I:"," ") | O19: VEGWSB | P19: =IF(IFERROR(VLOOKUP($K19,'Calc - Crops'!$L$24:$Y$47,8,FALSE)," ")=0," ",IFERROR(VLOOKUP($K19,'Calc - Crops'!$L$24:$Y$47,8,FALSE)/1000," ")) | Q19: =IF(IFERROR(P19/(IFERROR(VLOOKUP(F19,'Calc - water'!$B$39:$G$48,6,FALSE),"")*IFERROR(VLOOKUP(E19,DefaultAFOLU!$C$32:$G$39,5,FALSE),"")),"")=0," ",IFERROR(P19/(IFERROR(VLOOKUP(F19,'Calc - water'!$B$39:$G$48,6,FALSE),"")*IFERROR(VLOOKUP(E19,DefaultAFOLU!$C$32:$G$39,5,FALSE),"")),"")) | T19: =IF(Y19=0,Intro!$B$16+1,"") | U19: =IFERROR(VLOOKUP(O19,DefaultAFOLU!$D$42:$G$50,4,TRUE)," ") -> 0.1 | V19: =IF(IFERROR(VLOOKUP($K19,'Calc - Crops'!$L$24:$Y$47,11,FALSE)," ")=0," ",IFERROR(VLOOKUP($K19,'Calc - Crops'!$L$24:$Y$47,11,FALSE)/$P19," ")) | W19: =IF(IFERROR(VLOOKUP($K19,'Calc - Crops'!$L$24:$Y$47,10,FALSE)," ")=0," ",IFERROR(VLOOKUP($K19,'Calc - Crops'!$L$24:$Y$47,10,FALSE)/$P19," ")) | X19: =IF(IFERROR(VLOOKUP($K19,'Calc - Crops'!$L$24:$Y$47,9,FALSE)," ")=0," ",IFERROR(VLOOKUP($K19,'Calc - Crops'!$L$24:$Y$47,9,FALSE)/$P19," ")) | Y19: =IFERROR(VLOOKUP($C19,'Calc - Crops'!$L$24:$Y$47,2,FALSE)/1000, " ") | Z19: =IF(E19<>"",SUMIFS('Input data - Other'!$F:$F,'Input data - Other'!$B:$B,Crops!Z$6,'Input data - Other'!$D:$D,Crops!$E19),"") | AA19: =IF(F19<>"",SUMIFS('Input data - Other'!$F:$F,'Input data - Other'!$B:$B,Crops!AA$6,'Input data - Other'!$D:$D,Crops!$E19),"")
B20: =IF(Y20=0,"\I:","DMD") -> DMD | C20: AFOCRPOFIWCRWTRE0 | D20: Afolu Crops Open Field Woody crops Existing 0 | E20: Open Field | F20: Woody crops | G20: Mton | H20: kha | I20: Annual | K20: =IF(Y20=0,"\I:",C20) -> AFOCRPOFIWCRWTRE0 | L20: Afolu Crops Open Field Woody crops Existing 0 | M20: WTRAFO | N20: AFOCRPWCRDEM | P20: =IF(IFERROR(VLOOKUP($K20,'Calc - Crops'!$L$24:$Y$47,8,FALSE)," ")=0," ",IFERROR(VLOOKUP($K20,'Calc - Crops'!$L$24:$Y$47,8,FALSE)/1000," ")) -> 0.0015218322 | Q20: =IF(IFERROR(P20/(IFERROR(VLOOKUP(F20,'Calc - water'!$B$39:$G$48,6,FALSE),"")*IFERROR(VLOOKUP(E20,DefaultAFOLU!$C$32:$G$39,5,FALSE),"")),"")=0," ",IFERROR(P20/(IFERROR(VLOOKUP(F20,'Calc - water'!$B$39:$G$48,6,FALSE),"")*IFERROR(VLOOKUP(E20,DefaultAFOLU!$C$32:$G$39,5,FALSE),"")),"")) -> 15.218322 | R20: 1 | S20: 4 | T20: =IF(Y20=0,Intro!$B$16+1,"") | V20: =IF(IFERROR(VLOOKUP($K20,'Calc - Crops'!$L$24:$Y$47,11,FALSE)," ")=0," ",IFERROR(VLOOKUP($K20,'Calc - Crops'!$L$24:$Y$47,11,FALSE)/$P20," ")) -> 5367.2486 | W20: =IF(IFERROR(VLOOKUP($K20,'Calc - Crops'!$L$24:$Y$47,10,FALSE)," ")=0," ",IFERROR(VLOOKUP($K20,'Calc - Crops'!$L$24:$Y$47,10,FALSE)/$P20," ")) -> 0.27475494 | X20: =IF(IFERROR(VLOOKUP($K20,'Calc - Crops'!$L$24:$Y$47,9,FALSE)," ")=0," ",IFERROR(VLOOKUP($K20,'Calc - Crops'!$L$24:$Y$47,9,FALSE)/$P20," ")) -> 7.4904432 | Y20: =IFERROR(VLOOKUP($C20,'Calc - Crops'!$L$24:$Y$47,2,FALSE)/1000, " ") -> 2.29 | Z20: =IF(E20<>"",SUMIFS('Input data - Other'!$F:$F,'Input data - Other'!$B:$B,Crops!Z$6,'Input data - Other'!$D:$D,Crops!$E20),"") -> 0.156 | AA20: =IF(F20<>"",SUMIFS('Input data - Other'!$F:$F,'Input data - Other'!$B:$B,Crops!AA$6,'Input data - Other'!$D:$D,Crops!$E20),"") -> 0
B21: \I: | K21: =IF(Y20=0,"\I:"," ") | O21: WCRWOC | P21: =IF(IFERROR(VLOOKUP($K21,'Calc - Crops'!$L$24:$Y$47,8,FALSE)," ")=0," ",IFERROR(VLOOKUP($K21,'Calc - Crops'!$L$24:$Y$47,8,FALSE)/1000," ")) | Q21: =IF(IFERROR(P21/(IFERROR(VLOOKUP(F21,'Calc - water'!$B$39:$G$48,6,FALSE),"")*IFERROR(VLOOKUP(E21,DefaultAFOLU!$C$32:$G$39,5,FALSE),"")),"")=0," ",IFERROR(P21/(IFERROR(VLOOKUP(F21,'Calc - water'!$B$39:$G$48,6,FALSE),"")*IFERROR(VLOOKUP(E21,DefaultAFOLU!$C$32:$G$39,5,FALSE),"")),"")) | T21: =IF(Y21=0,Intro!$B$16+1,"") | U21: =IFERROR(VLOOKUP(O21,DefaultAFOLU!$D$42:$G$50,4,TRUE)," ") -> 0.1 | V21: =IF(IFERROR(VLOOKUP($K21,'Calc - Crops'!$L$24:$Y$47,11,FALSE)," ")=0," ",IFERROR(VLOOKUP($K21,'Calc - Crops'!$L$24:$Y$47,11,FALSE)/$P21," ")) | W21: =IF(IFERROR(VLOOKUP($K21,'Calc - Crops'!$L$24:$Y$47,10,FALSE)," ")=0," ",IFERROR(VLOOKUP($K21,'Calc - Crops'!$L$24:$Y$47,10,FALSE)/$P21," ")) | X21: =IF(IFERROR(VLOOKUP($K21,'Calc - Crops'!$L$24:$Y$47,9,FALSE)," ")=0," ",IFERROR(VLOOKUP($K21,'Calc - Crops'!$L$24:$Y$47,9,FALSE)/$P21," ")) | Y21: =IFERROR(VLOOKUP($C21,'Calc - Crops'!$L$24:$Y$47,2,FALSE)/1000, " ") | Z21: =IF(E21<>"",SUMIFS('Input data - Other'!$F:$F,'Input data - Other'!$B:$B,Crops!Z$6,'Input data - Other'!$D:$D,Crops!$E21),"") | AA21: =IF(F21<>"",SUMIFS('Input data - Other'!$F:$F,'Input data - Other'!$B:$B,Crops!AA$6,'Input data - Other'!$D:$D,Crops!$E21),"")
B22: =IF(Y22=0,"\I:","DMD") -> DMD | C22: AFOCRPOFIROOWTRE0 | D22: Afolu Crops Open Field Roots Existing 0 | E22: Open Field | F22: Roots | G22: Mton | H22: kha | I22: Annual | K22: =IF(Y22=0,"\I:",C22) -> AFOCRPOFIROOWTRE0 | L22: Afolu Crops Open Field Roots Existing 0 | M22: WTRAFO | N22: AFOCRPROODEM | P22: =IF(IFERROR(VLOOKUP($K22,'Calc - Crops'!$L$24:$Y$47,8,FALSE)," ")=0," ",IFERROR(VLOOKUP($K22,'Calc - Crops'!$L$24:$Y$47,8,FALSE)/1000," ")) -> 0.0052539044 | Q22: =IF(IFERROR(P22/(IFERROR(VLOOKUP(F22,'Calc - water'!$B$39:$G$48,6,FALSE),"")*IFERROR(VLOOKUP(E22,DefaultAFOLU!$C$32:$G$39,5,FALSE),"")),"")=0," ",IFERROR(P22/(IFERROR(VLOOKUP(F22,'Calc - water'!$B$39:$G$48,6,FALSE),"")*IFERROR(VLOOKUP(E22,DefaultAFOLU!$C$32:$G$39,5,FALSE),"")),"")) -> 0.015959959 | R22: 1 | S22: 4 | T22: =IF(Y22=0,Intro!$B$16+1,"") | V22: =IF(IFERROR(VLOOKUP($K22,'Calc - Crops'!$L$24:$Y$47,11,FALSE)," ")=0," ",IFERROR(VLOOKUP($K22,'Calc - Crops'!$L$24:$Y$47,11,FALSE)/$P22," ")) -> 1554.6632 | W22: =IF(IFERROR(VLOOKUP($K22,'Calc - Crops'!$L$24:$Y$47,10,FALSE)," ")=0," ",IFERROR(VLOOKUP($K22,'Calc - Crops'!$L$24:$Y$47,10,FALSE)/$P22," ")) -> 0.079584796 | X22: =IF(IFERROR(VLOOKUP($K22,'Calc - Crops'!$L$24:$Y$47,9,FALSE)," ")=0," ",IFERROR(VLOOKUP($K22,'Calc - Crops'!$L$24:$Y$47,9,FALSE)/$P22," ")) -> 2.1696621 | Y22: =IFERROR(VLOOKUP($C22,'Calc - Crops'!$L$24:$Y$47,2,FALSE)/1000, " ") -> 54.41 | Z22: =IF(E22<>"",SUMIFS('Input data - Other'!$F:$F,'Input data - Other'!$B:$B,Crops!Z$6,'Input data - Other'!$D:$D,Crops!$E22),"") -> 0.156 | AA22: =IF(F22<>"",SUMIFS('Input data - Other'!$F:$F,'Input data - Other'!$B:$B,Crops!AA$6,'Input data - Other'!$D:$D,Crops!$E22),"") -> 0
B23: \I: | K23: =IF(Y22=0,"\I:"," ") | O23: ROOWSB | P23: =IF(IFERROR(VLOOKUP($K23,'Calc - Crops'!$L$24:$Y$47,8,FALSE)," ")=0," ",IFERROR(VLOOKUP($K23,'Calc - Crops'!$L$24:$Y$47,8,FALSE)/1000," ")) | Q23: =IF(IFERROR(P23/(IFERROR(VLOOKUP(F23,'Calc - water'!$B$39:$G$48,6,FALSE),"")*IFERROR(VLOOKUP(E23,DefaultAFOLU!$C$32:$G$39,5,FALSE),"")),"")=0," ",IFERROR(P23/(IFERROR(VLOOKUP(F23,'Calc - water'!$B$39:$G$48,6,FALSE),"")*IFERROR(VLOOKUP(E23,DefaultAFOLU!$C$32:$G$39,5,FALSE),"")),"")) | T23: =IF(Y23=0,Intro!$B$16+1,"") | U23: =IFERROR(VLOOKUP(O23,DefaultAFOLU!$D$42:$G$50,4,TRUE)," ") -> 0.3 | V23: =IF(IFERROR(VLOOKUP($K23,'Calc - Crops'!$L$24:$Y$47,11,FALSE)," ")=0," ",IFERROR(VLOOKUP($K23,'Calc - Crops'!$L$24:$Y$47,11,FALSE)/$P23," ")) | W23: =IF(IFERROR(VLOOKUP($K23,'Calc - Crops'!$L$24:$Y$47,10,FALSE)," ")=0," ",IFERROR(VLOOKUP($K23,'Calc - Crops'!$L$24:$Y$47,10,FALSE)/$P23," ")) | X23: =IF(IFERROR(VLOOKUP($K23,'Calc - Crops'!$L$24:$Y$47,9,FALSE)," ")=0," ",IFERROR(VLOOKUP($K23,'Calc - Crops'!$L$24:$Y$47,9,FALSE)/$P23," ")) | Y23: =IFERROR(VLOOKUP($C23,'Calc - Crops'!$L$24:$Y$47,2,FALSE)/1000, " ") | Z23: =IF(E23<>"",SUMIFS('Input data - Other'!$F:$F,'Input data - Other'!$B:$B,Crops!Z$6,'Input data - Other'!$D:$D,Crops!$E23),"") | AA23: =IF(F23<>"",SUMIFS('Input data - Other'!$F:$F,'Input data - Other'!$B:$B,Crops!AA$6,'Input data - Other'!$D:$D,Crops!$E23),"")
B24: =IF(Y24=0,"\I:","DMD") -> DMD | C24: AFOCRPOFIHAGWTRE0 | D24: Afolu Crops Open Field Herbs and greens Existing 0 | E24: Open Field | F24: Herbs and greens | G24: Mton | H24: kha | I24: Annual | K24: =IF(Y24=0,"\I:",C24) -> AFOCRPOFIHAGWTRE0 | L24: Afolu Crops Open Field Herbs and greens Existing 0 | M24: WTRAFO | N24: AFOCRPHAGDEM | P24: =IF(IFERROR(VLOOKUP($K24,'Calc - Crops'!$L$24:$Y$47,8,FALSE)," ")=0," ",IFERROR(VLOOKUP($K24,'Calc - Crops'!$L$24:$Y$47,8,FALSE)/1000," ")) -> 0.0014493778 | Q24: =IF(IFERROR(P24/(IFERROR(VLOOKUP(F24,'Calc - water'!$B$39:$G$48,6,FALSE),"")*IFERROR(VLOOKUP(E24,DefaultAFOLU!$C$32:$G$39,5,FALSE),"")),"")=0," ",IFERROR(P24/(IFERROR(VLOOKUP(F24,'Calc - water'!$B$39:$G$48,6,FALSE),"")*IFERROR(VLOOKUP(E24,DefaultAFOLU!$C$32:$G$39,5,FALSE),"")),"")) -> 14.493778 | R24: 1 | S24: 4 | T24: =IF(Y24=0,Intro!$B$16+1,"") | V24: =IF(IFERROR(VLOOKUP($K24,'Calc - Crops'!$L$24:$Y$47,11,FALSE)," ")=0," ",IFERROR(VLOOKUP($K24,'Calc - Crops'!$L$24:$Y$47,11,FALSE)/$P24," ")) -> 5635.5574 | W24: =IF(IFERROR(VLOOKUP($K24,'Calc - Crops'!$L$24:$Y$47,10,FALSE)," ")=0," ",IFERROR(VLOOKUP($K24,'Calc - Crops'!$L$24:$Y$47,10,FALSE)/$P24," ")) -> 0.28848995 | X24: =IF(IFERROR(VLOOKUP($K24,'Calc - Crops'!$L$24:$Y$47,9,FALSE)," ")=0," ",IFERROR(VLOOKUP($K24,'Calc - Crops'!$L$24:$Y$47,9,FALSE)/$P24," ")) -> 7.8648905 | Y24: =IFERROR(VLOOKUP($C24,'Calc - Crops'!$L$24:$Y$47,2,FALSE)/1000, " ") -> 4.84 | Z24: =IF(E24<>"",SUMIFS('Input data - Other'!$F:$F,'Input data - Other'!$B:$B,Crops!Z$6,'Input data - Other'!$D:$D,Crops!$E24),"") -> 0.156 | AA24: =IF(F24<>"",SUMIFS('Input data - Other'!$F:$F,'Input data - Other'!$B:$B,Crops!AA$6,'Input data - Other'!$D:$D,Crops!$E24),"") -> 0
B25: \I: | K25: =IF(Y24=0,"\I:"," ") | O25: HAGWSB | P25: =IF(IFERROR(VLOOKUP($K25,'Calc - Crops'!$L$24:$Y$47,8,FALSE)," ")=0," ",IFERROR(VLOOKUP($K25,'Calc - Crops'!$L$24:$Y$47,8,FALSE)/1000," ")) | Q25: =IF(IFERROR(P25/(IFERROR(VLOOKUP(F25,'Calc - water'!$B$39:$G$48,6,FALSE),"")*IFERROR(VLOOKUP(E25,DefaultAFOLU!$C$32:$G$39,5,FALSE),"")),"")=0," ",IFERROR(P25/(IFERROR(VLOOKUP(F25,'Calc - water'!$B$39:$G$48,6,FALSE),"")*IFERROR(VLOOKUP(E25,DefaultAFOLU!$C$32:$G$39,5,FALSE),"")),"")) | T25: =IF(Y25=0,Intro!$B$16+1,"") | U25: =IFERROR(VLOOKUP(O25,DefaultAFOLU!$D$42:$G$50,4,TRUE)," ") -> 0.3 | V25: =IF(IFERROR(VLOOKUP($K25,'Calc - Crops'!$L$24:$Y$47,11,FALSE)," ")=0," ",IFERROR(VLOOKUP($K25,'Calc - Crops'!$L$24:$Y$47,11,FALSE)/$P25," ")) | W25: =IF(IFERROR(VLOOKUP($K25,'Calc - Crops'!$L$24:$Y$47,10,FALSE)," ")=0," ",IFERROR(VLOOKUP($K25,'Calc - Crops'!$L$24:$Y$47,10,FALSE)/$P25," ")) | X25: =IF(IFERROR(VLOOKUP($K25,'Calc - Crops'!$L$24:$Y$47,9,FALSE)," ")=0," ",IFERROR(VLOOKUP($K25,'Calc - Crops'!$L$24:$Y$47,9,FALSE)/$P25," ")) | Y25: =IFERROR(VLOOKUP($C25,'Calc - Crops'!$L$24:$Y$47,2,FALSE)/1000, " ") | Z25: =IF(E25<>"",SUMIFS('Input data - Other'!$F:$F,'Input data - Other'!$B:$B,Crops!Z$6,'Input data - Other'!$D:$D,Crops!$E25),"") | AA25: =IF(F25<>"",SUMIFS('Input data - Other'!$F:$F,'Input data - Other'!$B:$B,Crops!AA$6,'Input data - Other'!$D:$D,Crops!$E25),"")
B26: DMD | C26: AFOCRPGRHLEGWTRE0 | D26: Afolu Crops Greenhouse Legumes Existing 0 | E26: Greenhouse | F26: Legumes | G26: Mton | H26: kha | I26: Annual | K26: =IF(Y12=0,"\I:",C26) -> AFOCRPGRHLEGWTRE0 | L26: Afolu Crops Greenhouse Legumes Existing 0 | M26: WTRAFO | N26: AFOCRPLEGDEM | P26: =IF(IFERROR(VLOOKUP($K26,'Calc - Crops'!$L$24:$Y$47,8,FALSE)," ")=0," ",IFERROR(VLOOKUP($K26,'Calc - Crops'!$L$24:$Y$47,8,FALSE)/1000," ")) -> 0.00099658939 | Q26: =IF(IFERROR(P26/(IFERROR(VLOOKUP(F26,'Calc - water'!$B$39:$G$48,6,FALSE),"")*IFERROR(VLOOKUP(E26,DefaultAFOLU!$C$32:$G$39,5,FALSE),"")),"")=0," ",IFERROR(P26/(IFERROR(VLOOKUP(F26,'Calc - water'!$B$39:$G$48,6,FALSE),"")*IFERROR(VLOOKUP(E26,DefaultAFOLU!$C$32:$G$39,5,FALSE),"")),"")) -> 0.026818777 | R26: 1 | S26: 4 | T26: =IF(Y26=0,Intro!$B$16+1,"") -> 2023 | V26: =IF(IFERROR(VLOOKUP($K26,'Calc - Crops'!$L$24:$Y$47,11,FALSE)," ")=0," ",IFERROR(VLOOKUP($K26,'Calc - Crops'!$L$24:$Y$47,11,FALSE)/$P26," ")) -> 8196.005 | W26: =IF(IFERROR(VLOOKUP($K26,'Calc - Crops'!$L$24:$Y$47,10,FALSE)," ")=0," ",IFERROR(VLOOKUP($K26,'Calc - Crops'!$L$24:$Y$47,10,FALSE)/$P26," ")) -> 0.41956188 | X26: =IF(IFERROR(VLOOKUP($K26,'Calc - Crops'!$L$24:$Y$47,9,FALSE)," ")=0," ",IFERROR(VLOOKUP($K26,'Calc - Crops'!$L$24:$Y$47,9,FALSE)/$P26," ")) -> 11.438209 | Y26: =IFERROR(VLOOKUP($C26,'Calc - Crops'!$L$24:$Y$47,2,FALSE)/1000, " ") -> 0 | Z26: =IF(E26<>"",SUMIFS('Input data - Other'!$F:$F,'Input data - Other'!$B:$B,Crops!Z$6,'Input data - Other'!$D:$D,Crops!$E26),"") -> 0.156 | AA26: =IF(F26<>"",SUMIFS('Input data - Other'!$F:$F,'Input data - Other'!$B:$B,Crops!AA$6,'Input data - Other'!$D:$D,Crops!$E26),"") -> 1000
B27: \I: | K27: =IF(Y12=0,"\I:"," ") | O27: LEGWSB | P27: =IF(IFERROR(VLOOKUP($K27,'Calc - Crops'!$L$24:$Y$47,8,FALSE)," ")=0," ",IFERROR(VLOOKUP($K27,'Calc - Crops'!$L$24:$Y$47,8,FALSE)/1000," ")) | Q27: =IF(IFERROR(P27/(IFERROR(VLOOKUP(F27,'Calc - water'!$B$39:$G$48,6,FALSE),"")*IFERROR(VLOOKUP(E27,DefaultAFOLU!$C$32:$G$39,5,FALSE),"")),"")=0," ",IFERROR(P27/(IFERROR(VLOOKUP(F27,'Calc - water'!$B$39:$G$48,6,FALSE),"")*IFERROR(VLOOKUP(E27,DefaultAFOLU!$C$32:$G$39,5,FALSE),"")),"")) | T27: =IF(Y27=0,Intro!$B$16+1,"") | U27: =IFERROR(VLOOKUP(O27,DefaultAFOLU!$D$42:$G$50,4,TRUE)," ") -> 0.3 | V27: =IF(IFERROR(VLOOKUP($K27,'Calc - Crops'!$L$24:$Y$47,11,FALSE)," ")=0," ",IFERROR(VLOOKUP($K27,'Calc - Crops'!$L$24:$Y$47,11,FALSE)/$P27," ")) | W27: =IF(IFERROR(VLOOKUP($K27,'Calc - Crops'!$L$24:$Y$47,10,FALSE)," ")=0," ",IFERROR(VLOOKUP($K27,'Calc - Crops'!$L$24:$Y$47,10,FALSE)/$P27," ")) | X27: =IF(IFERROR(VLOOKUP($K27,'Calc - Crops'!$L$24:$Y$47,9,FALSE)," ")=0," ",IFERROR(VLOOKUP($K27,'Calc - Crops'!$L$24:$Y$47,9,FALSE)/$P27," ")) | Y27: =IFERROR(VLOOKUP($C27,'Calc - Crops'!$L$24:$Y$47,2,FALSE)/1000, " ") | Z27: =IF(E27<>"",SUMIFS('Input data - Other'!$F:$F,'Input data - Other'!$B:$B,Crops!Z$6,'Input data - Other'!$D:$D,Crops!$E27),"") | AA27: =IF(F27<>"",SUMIFS('Input data - Other'!$F:$F,'Input data - Other'!$B:$B,Crops!AA$6,'Input data - Other'!$D:$D,Crops!$E27),"")
B28: DMD | C28: AFOCRPGRHVEGWTRE0 | D28: Afolu Crops Greenhouse Vegetables Existing 0 | E28: Greenhouse | F28: Vegetables | G28: Mton | H28: kha | I28: Annual | K28: =IF(Y18=0,"\I:",C28) -> AFOCRPGRHVEGWTRE0 | L28: Afolu Crops Greenhouse Vegetables Existing 0 | M28: WTRAFO | N28: AFOCRPVEGDEM | P28: =IF(IFERROR(VLOOKUP($K28,'Calc - Crops'!$L$24:$Y$47,8,FALSE)," ")=0," ",IFERROR(VLOOKUP($K28,'Calc - Crops'!$L$24:$Y$47,8,FALSE)/1000," ")) -> 0.014237984 | Q28: =IF(IFERROR(P28/(IFERROR(VLOOKUP(F28,'Calc - water'!$B$39:$G$48,6,FALSE),"")*IFERROR(VLOOKUP(E28,DefaultAFOLU!$C$32:$G$39,5,FALSE),"")),"")=0," ",IFERROR(P28/(IFERROR(VLOOKUP(F28,'Calc - water'!$B$39:$G$48,6,FALSE),"")*IFERROR(VLOOKUP(E28,DefaultAFOLU!$C$32:$G$39,5,FALSE),"")),"")) -> 0.022612715 | R28: 1 | S28: 4 | T28: =IF(Y28=0,Intro!$B$16+1,"") -> 2023 | V28: =IF(IFERROR(VLOOKUP($K28,'Calc - Crops'!$L$24:$Y$47,11,FALSE)," ")=0," ",IFERROR(VLOOKUP($K28,'Calc - Crops'!$L$24:$Y$47,11,FALSE)/$P28," ")) -> 573.68036 | W28: =IF(IFERROR(VLOOKUP($K28,'Calc - Crops'!$L$24:$Y$47,10,FALSE)," ")=0," ",IFERROR(VLOOKUP($K28,'Calc - Crops'!$L$24:$Y$47,10,FALSE)/$P28," ")) -> 0.029367284 | X28: =IF(IFERROR(VLOOKUP($K28,'Calc - Crops'!$L$24:$Y$47,9,FALSE)," ")=0," ",IFERROR(VLOOKUP($K28,'Calc - Crops'!$L$24:$Y$47,9,FALSE)/$P28," ")) -> 0.8006188 | Y28: =IFERROR(VLOOKUP($C28,'Calc - Crops'!$L$24:$Y$47,2,FALSE)/1000, " ") -> 0 | Z28: =IF(E28<>"",SUMIFS('Input data - Other'!$F:$F,'Input data - Other'!$B:$B,Crops!Z$6,'Input data - Other'!$D:$D,Crops!$E28),"") -> 0.156 | AA28: =IF(F28<>"",SUMIFS('Input data - Other'!$F:$F,'Input data - Other'!$B:$B,Crops!AA$6,'Input data - Other'!$D:$D,Crops!$E28),"") -> 1000
B29: \I: | K29: =IF(Y18=0,"\I:"," ") | O29: VEGWSB | P29: =IF(IFERROR(VLOOKUP($K29,'Calc - Crops'!$L$24:$Y$47,8,FALSE)," ")=0," ",IFERROR(VLOOKUP($K29,'Calc - Crops'!$L$24:$Y$47,8,FALSE)/1000," ")) | Q29: =IF(IFERROR(P29/(IFERROR(VLOOKUP(F29,'Calc - water'!$B$39:$G$48,6,FALSE),"")*IFERROR(VLOOKUP(E29,DefaultAFOLU!$C$32:$G$39,5,FALSE),"")),"")=0," ",IFERROR(P29/(IFERROR(VLOOKUP(F29,'Calc - water'!$B$39:$G$48,6,FALSE),"")*IFERROR(VLOOKUP(E29,DefaultAFOLU!$C$32:$G$39,5,FALSE),"")),"")) | T29: =IF(Y29=0,Intro!$B$16+1,"") | U29: =IFERROR(VLOOKUP(O29,DefaultAFOLU!$D$42:$G$50,4,TRUE)," ") -> 0.1 | V29: =IF(IFERROR(VLOOKUP($K29,'Calc - Crops'!$L$24:$Y$47,11,FALSE)," ")=0," ",IFERROR(VLOOKUP($K29,'Calc - Crops'!$L$24:$Y$47,11,FALSE)/$P29," ")) | W29: =IF(IFERROR(VLOOKUP($K29,'Calc - Crops'!$L$24:$Y$47,10,FALSE)," ")=0," ",IFERROR(VLOOKUP($K29,'Calc - Crops'!$L$24:$Y$47,10,FALSE)/$P29," ")) | X29: =IF(IFERROR(VLOOKUP($K29,'Calc - Crops'!$L$24:$Y$47,9,FALSE)," ")=0," ",IFERROR(VLOOKUP($K29,'Calc - Crops'!$L$24:$Y$47,9,FALSE)/$P29," ")) | Y29: =IFERROR(VLOOKUP($C29,'Calc - Crops'!$L$24:$Y$47,2,FALSE)/1000, " ") | Z29: =IF(E29<>"",SUMIFS('Input data - Other'!$F:$F,'Input data - Other'!$B:$B,Crops!Z$6,'Input data - Other'!$D:$D,Crops!$E29),"") | AA29: =IF(F29<>"",SUMIFS('Input data - Other'!$F:$F,'Input data - Other'!$B:$B,Crops!AA$6,'Input data - Other'!$D:$D,Crops!$E29),"")
B30: DMD | C30: AFOCRPGRHWCRWTRE0 | D30: Afolu Crops Greenhouse Woody crops Existing 0 | E30: Greenhouse | F30: Woody crops | G30: Mton | H30: kha | I30: Annual | K30: =IF(Y20=0,"\I:",C30) -> AFOCRPGRHWCRWTRE0 | L30: Afolu Crops Greenhouse Woody crops Existing 0 | M30: WTRAFO | N30: AFOCRPWCRDEM | P30: =IF(IFERROR(VLOOKUP($K30,'Calc - Crops'!$L$24:$Y$47,8,FALSE)," ")=0," ",IFERROR(VLOOKUP($K30,'Calc - Crops'!$L$24:$Y$47,8,FALSE)/1000," ")) -> 0.0045654966 | Q30: =IF(IFERROR(P30/(IFERROR(VLOOKUP(F30,'Calc - water'!$B$39:$G$48,6,FALSE),"")*IFERROR(VLOOKUP(E30,DefaultAFOLU!$C$32:$G$39,5,FALSE),"")),"")=0," ",IFERROR(P30/(IFERROR(VLOOKUP(F30,'Calc - water'!$B$39:$G$48,6,FALSE),"")*IFERROR(VLOOKUP(E30,DefaultAFOLU!$C$32:$G$39,5,FALSE),"")),"")) -> 60.873287 | R30: 1 | S30: 4 | T30: =IF(Y30=0,Intro!$B$16+1,"") -> 2023 | V30: =IF(IFERROR(VLOOKUP($K30,'Calc - Crops'!$L$24:$Y$47,11,FALSE)," ")=0," ",IFERROR(VLOOKUP($K30,'Calc - Crops'!$L$24:$Y$47,11,FALSE)/$P30," ")) -> 1789.0829 | W30: =IF(IFERROR(VLOOKUP($K30,'Calc - Crops'!$L$24:$Y$47,10,FALSE)," ")=0," ",IFERROR(VLOOKUP($K30,'Calc - Crops'!$L$24:$Y$47,10,FALSE)/$P30," ")) -> 0.091584981 | X30: =IF(IFERROR(VLOOKUP($K30,'Calc - Crops'!$L$24:$Y$47,9,FALSE)," ")=0," ",IFERROR(VLOOKUP($K30,'Calc - Crops'!$L$24:$Y$47,9,FALSE)/$P30," ")) -> 2.4968144 | Y30: =IFERROR(VLOOKUP($C30,'Calc - Crops'!$L$24:$Y$47,2,FALSE)/1000, " ") -> 0 | Z30: =IF(E30<>"",SUMIFS('Input data - Other'!$F:$F,'Input data - Other'!$B:$B,Crops!Z$6,'Input data - Other'!$D:$D,Crops!$E30),"") -> 0.156 | AA30: =IF(F30<>"",SUMIFS('Input data - Other'!$F:$F,'Input data - Other'!$B:$B,Crops!AA$6,'Input data - Other'!$D:$D,Crops!$E30),"") -> 1000
B31: \I: | K31: =IF(Y20=0,"\I:"," ") | O31: WCRWOC | P31: =IF(IFERROR(VLOOKUP($K31,'Calc - Crops'!$L$24:$Y$47,8,FALSE)," ")=0," ",IFERROR(VLOOKUP($K31,'Calc - Crops'!$L$24:$Y$47,8,FALSE)/1000," ")) | Q31: =IF(IFERROR(P31/(IFERROR(VLOOKUP(F31,'Calc - water'!$B$39:$G$48,6,FALSE),"")*IFERROR(VLOOKUP(E31,DefaultAFOLU!$C$32:$G$39,5,FALSE),"")),"")=0," ",IFERROR(P31/(IFERROR(VLOOKUP(F31,'Calc - water'!$B$39:$G$48,6,FALSE),"")*IFERROR(VLOOKUP(E31,DefaultAFOLU!$C$32:$G$39,5,FALSE),"")),"")) | T31: =IF(Y31=0,Intro!$B$16+1,"") | U31: =IFERROR(VLOOKUP(O31,DefaultAFOLU!$D$42:$G$50,4,TRUE)," ") -> 0.1 | V31: =IF(IFERROR(VLOOKUP($K31,'Calc - Crops'!$L$24:$Y$47,11,FALSE)," ")=0," ",IFERROR(VLOOKUP($K31,'Calc - Crops'!$L$24:$Y$47,11,FALSE)/$P31," ")) | W31: =IF(IFERROR(VLOOKUP($K31,'Calc - Crops'!$L$24:$Y$47,10,FALSE)," ")=0," ",IFERROR(VLOOKUP($K31,'Calc - Crops'!$L$24:$Y$47,10,FALSE)/$P31," ")) | X31: =IF(IFERROR(VLOOKUP($K31,'Calc - Crops'!$L$24:$Y$47,9,FALSE)," ")=0," ",IFERROR(VLOOKUP($K31,'Calc - Crops'!$L$24:$Y$47,9,FALSE)/$P31," ")) | Y31: =IFERROR(VLOOKUP($C31,'Calc - Crops'!$L$24:$Y$47,2,FALSE)/1000, " ") | Z31: =IF(E31<>"",SUMIFS('Input data - Other'!$F:$F,'Input data - Other'!$B:$B,Crops!Z$6,'Input data - Other'!$D:$D,Crops!$E31),"") | AA31: =IF(F31<>"",SUMIFS('Input data - Other'!$F:$F,'Input data - Other'!$B:$B,Crops!AA$6,'Input data - Other'!$D:$D,Crops!$E31),"")
B32: DMD | C32: AFOCRPGRHHAGWTRE0 | D32: Afolu Crops Greenhouse Herbs and greens Existing 0 | E32: Greenhouse | F32: Herbs and greens | G32: Mton | H32: kha | I32: Annual | K32: =IF(Y24=0,"\I:",C32) -> AFOCRPGRHHAGWTRE0 | L32: Afolu Crops Greenhouse Herbs and greens Existing 0 | M32: WTRAFO | N32: AFOCRPHAGDEM | P32: =IF(IFERROR(VLOOKUP($K32,'Calc - Crops'!$L$24:$Y$47,8,FALSE)," ")=0," ",IFERROR(VLOOKUP($K32,'Calc - Crops'!$L$24:$Y$47,8,FALSE)/1000," ")) -> 0.0043481333 | Q32: =IF(IFERROR(P32/(IFERROR(VLOOKUP(F32,'Calc - water'!$B$39:$G$48,6,FALSE),"")*IFERROR(VLOOKUP(E32,DefaultAFOLU!$C$32:$G$39,5,FALSE),"")),"")=0," ",IFERROR(P32/(IFERROR(VLOOKUP(F32,'Calc - water'!$B$39:$G$48,6,FALSE),"")*IFERROR(VLOOKUP(E32,DefaultAFOLU!$C$32:$G$39,5,FALSE),"")),"")) -> 57.975111 | R32: 1 | S32: 4 | T32: =IF(Y32=0,Intro!$B$16+1,"") -> 2023 | V32: =IF(IFERROR(VLOOKUP($K32,'Calc - Crops'!$L$24:$Y$47,11,FALSE)," ")=0," ",IFERROR(VLOOKUP($K32,'Calc - Crops'!$L$24:$Y$47,11,FALSE)/$P32," ")) -> 1878.5191 | W32: =IF(IFERROR(VLOOKUP($K32,'Calc - Crops'!$L$24:$Y$47,10,FALSE)," ")=0," ",IFERROR(VLOOKUP($K32,'Calc - Crops'!$L$24:$Y$47,10,FALSE)/$P32," ")) -> 0.096163315 | X32: =IF(IFERROR(VLOOKUP($K32,'Calc - Crops'!$L$24:$Y$47,9,FALSE)," ")=0," ",IFERROR(VLOOKUP($K32,'Calc - Crops'!$L$24:$Y$47,9,FALSE)/$P32," ")) -> 2.6216302 | Y32: =IFERROR(VLOOKUP($C32,'Calc - Crops'!$L$24:$Y$47,2,FALSE)/1000, " ") -> 0 | Z32: =IF(E32<>"",SUMIFS('Input data - Other'!$F:$F,'Input data - Other'!$B:$B,Crops!Z$6,'Input data - Other'!$D:$D,Crops!$E32),"") -> 0.156 | AA32: =IF(F32<>"",SUMIFS('Input data - Other'!$F:$F,'Input data - Other'!$B:$B,Crops!AA$6,'Input data - Other'!$D:$D,Crops!$E32),"") -> 1000
B33: \I: | K33: =IF(Y25=0,"\I:"," ") | O33: HAGWSB | P33: =IF(IFERROR(VLOOKUP($K33,'Calc - Crops'!$L$24:$Y$47,8,FALSE)," ")=0," ",IFERROR(VLOOKUP($K33,'Calc - Crops'!$L$24:$Y$47,8,FALSE)/1000," ")) | Q33: =IF(IFERROR(P33/(IFERROR(VLOOKUP(F33,'Calc - water'!$B$39:$G$48,6,FALSE),"")*IFERROR(VLOOKUP(E33,DefaultAFOLU!$C$32:$G$39,5,FALSE),"")),"")=0," ",IFERROR(P33/(IFERROR(VLOOKUP(F33,'Calc - water'!$B$39:$G$48,6,FALSE),"")*IFERROR(VLOOKUP(E33,DefaultAFOLU!$C$32:$G$39,5,FALSE),"")),"")) | T33: =IF(Y33=0,Intro!$B$16+1,"") | U33: =IFERROR(VLOOKUP(O33,DefaultAFOLU!$D$42:$G$50,4,TRUE)," ") -> 0.3 | V33: =IF(IFERROR(VLOOKUP($K33,'Calc - Crops'!$L$24:$Y$47,11,FALSE)," ")=0," ",IFERROR(VLOOKUP($K33,'Calc - Crops'!$L$24:$Y$47,11,FALSE)/$P33," ")) | W33: =IF(IFERROR(VLOOKUP($K33,'Calc - Crops'!$L$24:$Y$47,10,FALSE)," ")=0," ",IFERROR(VLOOKUP($K33,'Calc - Crops'!$L$24:$Y$47,10,FALSE)/$P33," ")) | X33: =IF(IFERROR(VLOOKUP($K33,'Calc - Crops'!$L$24:$Y$47,9,FALSE)," ")=0," ",IFERROR(VLOOKUP($K33,'Calc - Crops'!$L$24:$Y$47,9,FALSE)/$P33," ")) | Y33: =IFERROR(VLOOKUP($C33,'Calc - Crops'!$L$24:$Y$47,2,FALSE)/1000, " ") | Z33: =IF(E33<>"",SUMIFS('Input data - Other'!$F:$F,'Input data - Other'!$B:$B,Crops!Z$6,'Input data - Other'!$D:$D,Crops!$E33),"") | AA33: =IF(F33<>"",SUMIFS('Input data - Other'!$F:$F,'Input data - Other'!$B:$B,Crops!AA$6,'Input data - Other'!$D:$D,Crops!$E33),"")
B34: DMD | C34: AFOCRPAQPVEGWTRE0 | D34: Afolu Crops Aquaponics Vegetables Existing 0 | E34: Aquaponics | F34: Vegetables | G34: Mton | H34: kha | I34: Annual | K34: =IF(Y18=0,"\I:",C34) -> AFOCRPAQPVEGWTRE0 | L34: Afolu Crops Aquaponics Vegetables Existing 0 | M34: WTRAFO | N34: AFOCRPVEGDEM | P34: =IF(IFERROR(VLOOKUP($K34,'Calc - Crops'!$L$24:$Y$47,8,FALSE)," ")=0," ",IFERROR(VLOOKUP($K34,'Calc - Crops'!$L$24:$Y$47,8,FALSE)/1000," ")) -> 0.028475967 | Q34: =IF(IFERROR(P34/(IFERROR(VLOOKUP(F34,'Calc - water'!$B$39:$G$48,6,FALSE),"")*IFERROR(VLOOKUP(E34,DefaultAFOLU!$C$32:$G$39,5,FALSE),"")),"")=0," ",IFERROR(P34/(IFERROR(VLOOKUP(F34,'Calc - water'!$B$39:$G$48,6,FALSE),"")*IFERROR(VLOOKUP(E34,DefaultAFOLU!$C$32:$G$39,5,FALSE),"")),"")) -> 0.067838146 | R34: 1 | S34: 4 | T34: =IF(Y34=0,Intro!$B$16+1,"") -> 2023 | V34: =IF(IFERROR(VLOOKUP($K34,'Calc - Crops'!$L$24:$Y$47,11,FALSE)," ")=0," ",IFERROR(VLOOKUP($K34,'Calc - Crops'!$L$24:$Y$47,11,FALSE)/$P34," ")) -> 286.84018 | W34: =IF(IFERROR(VLOOKUP($K34,'Calc - Crops'!$L$24:$Y$47,10,FALSE)," ")=0," ",IFERROR(VLOOKUP($K34,'Calc - Crops'!$L$24:$Y$47,10,FALSE)/$P34," ")) -> 0.014683642 | X34: =IF(IFERROR(VLOOKUP($K34,'Calc - Crops'!$L$24:$Y$47,9,FALSE)," ")=0," ",IFERROR(VLOOKUP($K34,'Calc - Crops'!$L$24:$Y$47,9,FALSE)/$P34," ")) -> 0.4003094 | Y34: =IFERROR(VLOOKUP($C34,'Calc - Crops'!$L$24:$Y$47,2,FALSE)/1000, " ") -> 0 | Z34: =IF(E34<>"",SUMIFS('Input data - Other'!$F:$F,'Input data - Other'!$B:$B,Crops!Z$6,'Input data - Other'!$D:$D,Crops!$E34),"") -> 0.156 | AA34: =IF(F34<>"",SUMIFS('Input data - Other'!$F:$F,'Input data - Other'!$B:$B,Crops!AA$6,'Input data - Other'!$D:$D,Crops!$E34),"") -> 1500
B35: \I: | K35: =IF(Y18=0,"\I:"," ") | O35: VEGWSB | P35: =IF(IFERROR(VLOOKUP($K35,'Calc - Crops'!$L$24:$Y$47,8,FALSE)," ")=0," ",IFERROR(VLOOKUP($K35,'Calc - Crops'!$L$24:$Y$47,8,FALSE)/1000," ")) | Q35: =IF(IFERROR(P35/(IFERROR(VLOOKUP(F35,'Calc - water'!$B$39:$G$48,6,FALSE),"")*IFERROR(VLOOKUP(E35,DefaultAFOLU!$C$32:$G$39,5,FALSE),"")),"")=0," ",IFERROR(P35/(IFERROR(VLOOKUP(F35,'Calc - water'!$B$39:$G$48,6,FALSE),"")*IFERROR(VLOOKUP(E35,DefaultAFOLU!$C$32:$G$39,5,FALSE),"")),"")) | T35: =IF(Y35=0,Intro!$B$16+1,"") | U35: =IFERROR(VLOOKUP(O35,DefaultAFOLU!$D$42:$G$50,4,TRUE)," ") -> 0.1 | V35: =IF(IFERROR(VLOOKUP($K35,'Calc - Crops'!$L$24:$Y$47,11,FALSE)," ")=0," ",IFERROR(VLOOKUP($K35,'Calc - Crops'!$L$24:$Y$47,11,FALSE)/$P35," ")) | W35: =IF(IFERROR(VLOOKUP($K35,'Calc - Crops'!$L$24:$Y$47,10,FALSE)," ")=0," ",IFERROR(VLOOKUP($K35,'Calc - Crops'!$L$24:$Y$47,10,FALSE)/$P35," ")) | X35: =IF(IFERROR(VLOOKUP($K35,'Calc - Crops'!$L$24:$Y$47,9,FALSE)," ")=0," ",IFERROR(VLOOKUP($K35,'Calc - Crops'!$L$24:$Y$47,9,FALSE)/$P35," ")) | Y35: =IFERROR(VLOOKUP($C35,'Calc - Crops'!$L$24:$Y$47,2,FALSE)/1000, " ") | Z35: =IF(E35<>"",SUMIFS('Input data - Other'!$F:$F,'Input data - Other'!$B:$B,Crops!Z$6,'Input data - Other'!$D:$D,Crops!$E35),"") | AA35: =IF(F35<>"",SUMIFS('Input data - Other'!$F:$F,'Input data - Other'!$B:$B,Crops!AA$6,'Input data - Other'!$D:$D,Crops!$E35),"")
B36: DMD | C36: AFOCRPAQPHAGWTRE0 | D36: Afolu Crops Aquaponics Herbs and greens Existing 0 | E36: Aquaponics | F36: Herbs and greens | G36: Mton | H36: kha | I36: Annual | K36: =IF(Y24=0,"\I:",C36) -> AFOCRPAQPHAGWTRE0 | L36: Afolu Crops Aquaponics Herbs and greens Existing 0 | M36: WTRAFO | N36: AFOCRPHAGDEM | P36: =IF(IFERROR(VLOOKUP($K36,'Calc - Crops'!$L$24:$Y$47,8,FALSE)," ")=0," ",IFERROR(VLOOKUP($K36,'Calc - Crops'!$L$24:$Y$47,8,FALSE)/1000," ")) -> 0.0086962666 | Q36: =IF(IFERROR(P36/(IFERROR(VLOOKUP(F36,'Calc - water'!$B$39:$G$48,6,FALSE),"")*IFERROR(VLOOKUP(E36,DefaultAFOLU!$C$32:$G$39,5,FALSE),"")),"")=0," ",IFERROR(P36/(IFERROR(VLOOKUP(F36,'Calc - water'!$B$39:$G$48,6,FALSE),"")*IFERROR(VLOOKUP(E36,DefaultAFOLU!$C$32:$G$39,5,FALSE),"")),"")) -> 173.92533 | R36: 1 | S36: 4 | T36: =IF(Y36=0,Intro!$B$16+1,"") -> 2023 | V36: =IF(IFERROR(VLOOKUP($K36,'Calc - Crops'!$L$24:$Y$47,11,FALSE)," ")=0," ",IFERROR(VLOOKUP($K36,'Calc - Crops'!$L$24:$Y$47,11,FALSE)/$P36," ")) -> 939.25957 | W36: =IF(IFERROR(VLOOKUP($K36,'Calc - Crops'!$L$24:$Y$47,10,FALSE)," ")=0," ",IFERROR(VLOOKUP($K36,'Calc - Crops'!$L$24:$Y$47,10,FALSE)/$P36," ")) -> 0.048081658 | X36: =IF(IFERROR(VLOOKUP($K36,'Calc - Crops'!$L$24:$Y$47,9,FALSE)," ")=0," ",IFERROR(VLOOKUP($K36,'Calc - Crops'!$L$24:$Y$47,9,FALSE)/$P36," ")) -> 1.3108151 | Y36: =IFERROR(VLOOKUP($C36,'Calc - Crops'!$L$24:$Y$47,2,FALSE)/1000, " ") -> 0 | Z36: =IF(E36<>"",SUMIFS('Input data - Other'!$F:$F,'Input data - Other'!$B:$B,Crops!Z$6,'Input data - Other'!$D:$D,Crops!$E36),"") -> 0.156 | AA36: =IF(F36<>"",SUMIFS('Input data - Other'!$F:$F,'Input data - Other'!$B:$B,Crops!AA$6,'Input data - Other'!$D:$D,Crops!$E36),"") -> 1500
B37: \I: | K37: =IF(Y24=0,"\I:"," ") | O37: HAGWSB | P37: =IF(IFERROR(VLOOKUP($K37,'Calc - Crops'!$L$24:$Y$47,8,FALSE)," ")=0," ",IFERROR(VLOOKUP($K37,'Calc - Crops'!$L$24:$Y$47,8,FALSE)/1000," ")) | Q37: =IF(IFERROR(P37/(IFERROR(VLOOKUP(F37,'Calc - water'!$B$39:$G$48,6,FALSE),"")*IFERROR(VLOOKUP(E37,DefaultAFOLU!$C$32:$G$39,5,FALSE),"")),"")=0," ",IFERROR(P37/(IFERROR(VLOOKUP(F37,'Calc - water'!$B$39:$G$48,6,FALSE),"")*IFERROR(VLOOKUP(E37,DefaultAFOLU!$C$32:$G$39,5,FALSE),"")),"")) | T37: =IF(Y37=0,Intro!$B$16+1,"") | U37: =IFERROR(VLOOKUP(O37,DefaultAFOLU!$D$42:$G$50,4,TRUE)," ") -> 0.3 | V37: =IF(IFERROR(VLOOKUP($K37,'Calc - Crops'!$L$24:$Y$47,11,FALSE)," ")=0," ",IFERROR(VLOOKUP($K37,'Calc - Crops'!$L$24:$Y$47,11,FALSE)/$P37," ")) | W37: =IF(IFERROR(VLOOKUP($K37,'Calc - Crops'!$L$24:$Y$47,10,FALSE)," ")=0," ",IFERROR(VLOOKUP($K37,'Calc - Crops'!$L$24:$Y$47,10,FALSE)/$P37," ")) | X37: =IF(IFERROR(VLOOKUP($K37,'Calc - Crops'!$L$24:$Y$47,9,FALSE)," ")=0," ",IFERROR(VLOOKUP($K37,'Calc - Crops'!$L$24:$Y$47,9,FALSE)/$P37," ")) | Y37: =IFERROR(VLOOKUP($C37,'Calc - Crops'!$L$24:$Y$47,2,FALSE)/1000, " ") | Z37: =IF(E37<>"",SUMIFS('Input data - Other'!$F:$F,'Input data - Other'!$B:$B,Crops!Z$6,'Input data - Other'!$D:$D,Crops!$E37),"") | AA37: =IF(F37<>"",SUMIFS('Input data - Other'!$F:$F,'Input data - Other'!$B:$B,Crops!AA$6,'Input data - Other'!$D:$D,Crops!$E37),"")
B38: =IF(Y8=0,"\I:","DMD") -> DMD | C38: AFOCRPOFOCERWTRE0 | D38: Afolu Crops Organic Cereals Existing 0 | E38: Organic | F38: Cereals | G38: Mton | H38: kha | I38: Annual | K38: =IF(Y8=0,"\I:",C38) -> AFOCRPOFOCERWTRE0 | L38: Afolu Crops Organic Cereals Existing 0 | M38: WTRAFO | N38: AFOCRPCERDEM | P38: =IF(IFERROR(VLOOKUP($K38,'Calc - Crops'!$L$24:$Y$47,8,FALSE)," ")=0," ",IFERROR(VLOOKUP($K38,'Calc - Crops'!$L$24:$Y$47,8,FALSE)/1000," ")) -> 0.0004580524 | Q38: =IF(IFERROR(P38/(IFERROR(VLOOKUP(F38,'Calc - water'!$B$39:$G$48,6,FALSE),"")*IFERROR(VLOOKUP(E38,DefaultAFOLU!$C$32:$G$39,5,FALSE),"")),"")=0," ",IFERROR(P38/(IFERROR(VLOOKUP(F38,'Calc - water'!$B$39:$G$48,6,FALSE),"")*IFERROR(VLOOKUP(E38,DefaultAFOLU!$C$32:$G$39,5,FALSE),"")),"")) -> 4.580524 | R38: 1 | S38: 4 | T38: =IF(Y38=0,Intro!$B$16+1,"") -> 2023 | V38: =IF(IFERROR(VLOOKUP($K38,'Calc - Crops'!$L$24:$Y$47,11,FALSE)," ")=0," ",IFERROR(VLOOKUP($K38,'Calc - Crops'!$L$24:$Y$47,11,FALSE)/$P38," ")) -> 17832.134 | W38: =IF(IFERROR(VLOOKUP($K38,'Calc - Crops'!$L$24:$Y$47,10,FALSE)," ")=0," ",IFERROR(VLOOKUP($K38,'Calc - Crops'!$L$24:$Y$47,10,FALSE)/$P38," ")) -> 0.91284515 | X38: =IF(IFERROR(VLOOKUP($K38,'Calc - Crops'!$L$24:$Y$47,9,FALSE)," ")=0," ",IFERROR(VLOOKUP($K38,'Calc - Crops'!$L$24:$Y$47,9,FALSE)/$P38," ")) -> 17.90359 | Y38: =IFERROR(VLOOKUP($C38,'Calc - Crops'!$L$24:$Y$47,2,FALSE)/1000, " ") -> 0 | Z38: =IF(E38<>"",SUMIFS('Input data - Other'!$F:$F,'Input data - Other'!$B:$B,Crops!Z$6,'Input data - Other'!$D:$D,Crops!$E38),"") -> 0.156 | AA38: =IF(F38<>"",SUMIFS('Input data - Other'!$F:$F,'Input data - Other'!$B:$B,Crops!AA$6,'Input data - Other'!$D:$D,Crops!$E38),"") -> 0
B39: \I: | K39: =IF(Y8=0,"\I:"," ") | O39: CERSTR | P39: =IF(IFERROR(VLOOKUP($K39,'Calc - Crops'!$L$24:$Y$47,8,FALSE)," ")=0," ",IFERROR(VLOOKUP($K39,'Calc - Crops'!$L$24:$Y$47,8,FALSE)/1000," ")) | Q39: =IF(IFERROR(P39/(IFERROR(VLOOKUP(F39,'Calc - water'!$B$39:$G$48,6,FALSE),"")*IFERROR(VLOOKUP(E39,DefaultAFOLU!$C$32:$G$39,5,FALSE),"")),"")=0," ",IFERROR(P39/(IFERROR(VLOOKUP(F39,'Calc - water'!$B$39:$G$48,6,FALSE),"")*IFERROR(VLOOKUP(E39,DefaultAFOLU!$C$32:$G$39,5,FALSE),"")),"")) | T39: =IF(Y39=0,Intro!$B$16+1,"") | U39: =IFERROR(VLOOKUP(O39,DefaultAFOLU!$D$42:$G$50,4,TRUE)," ") -> 0.3 | V39: =IF(IFERROR(VLOOKUP($K39,'Calc - Crops'!$L$24:$Y$47,11,FALSE)," ")=0," ",IFERROR(VLOOKUP($K39,'Calc - Crops'!$L$24:$Y$47,11,FALSE)/$P39," ")) | W39: =IF(IFERROR(VLOOKUP($K39,'Calc - Crops'!$L$24:$Y$47,10,FALSE)," ")=0," ",IFERROR(VLOOKUP($K39,'Calc - Crops'!$L$24:$Y$47,10,FALSE)/$P39," ")) | X39: =IF(IFERROR(VLOOKUP($K39,'Calc - Crops'!$L$24:$Y$47,9,FALSE)," ")=0," ",IFERROR(VLOOKUP($K39,'Calc - Crops'!$L$24:$Y$47,9,FALSE)/$P39," ")) | Y39: =IFERROR(VLOOKUP($C39,'Calc - Crops'!$L$24:$Y$47,2,FALSE)/1000, " ") | Z39: =IF(E39<>"",SUMIFS('Input data - Other'!$F:$F,'Input data - Other'!$B:$B,Crops!Z$6,'Input data - Other'!$D:$D,Crops!$E39),"") | AA39: =IF(F39<>"",SUMIFS('Input data - Other'!$F:$F,'Input data - Other'!$B:$B,Crops!AA$6,'Input data - Other'!$D:$D,Crops!$E39),"")
B40: =IF(Y10=0,"\I:","DMD") -> \I: | C40: AFOCRPOFORICWTRE0 | D40: Afolu Crops Organic Rice Existing 0 | E40: Organic | F40: Rice | G40: Mton | H40: kha | I40: Annual | K40: =IF(Y10=0,"\I:",C40) -> \I: | L40: Afolu Crops Organic Rice Existing 0 | M40: WTRAFO | N40: AFOCRPRICDEM | P40: =IF(IFERROR(VLOOKUP($K40,'Calc - Crops'!$L$24:$Y$47,8,FALSE)," ")=0," ",IFERROR(VLOOKUP($K40,'Calc - Crops'!$L$24:$Y$47,8,FALSE)/1000," ")) | Q40: =IF(IFERROR(P40/(IFERROR(VLOOKUP(F40,'Calc - water'!$B$39:$G$48,6,FALSE),"")*IFERROR(VLOOKUP(E40,DefaultAFOLU!$C$32:$G$39,5,FALSE),"")),"")=0," ",IFERROR(P40/(IFERROR(VLOOKUP(F40,'Calc - water'!$B$39:$G$48,6,FALSE),"")*IFERROR(VLOOKUP(E40,DefaultAFOLU!$C$32:$G$39,5,FALSE),"")),"")) | R40: 1 | S40: 4 | T40: =IF(Y40=0,Intro!$B$16+1,"") -> 2023 | V40: =IF(IFERROR(VLOOKUP($K40,'Calc - Crops'!$L$24:$Y$47,11,FALSE)," ")=0," ",IFERROR(VLOOKUP($K40,'Calc - Crops'!$L$24:$Y$47,11,FALSE)/$P40," ")) | W40: =IF(IFERROR(VLOOKUP($K40,'Calc - Crops'!$L$24:$Y$47,10,FALSE)," ")=0," ",IFERROR(VLOOKUP($K40,'Calc - Crops'!$L$24:$Y$47,10,FALSE)/$P40," ")) | X40: =IF(IFERROR(VLOOKUP($K40,'Calc - Crops'!$L$24:$Y$47,9,FALSE)," ")=0," ",IFERROR(VLOOKUP($K40,'Calc - Crops'!$L$24:$Y$47,9,FALSE)/$P40," ")) | Y40: =IFERROR(VLOOKUP($C40,'Calc - Crops'!$L$24:$Y$47,2,FALSE)/1000, " ") -> 0 | Z40: =IF(E40<>"",SUMIFS('Input data - Other'!$F:$F,'Input data - Other'!$B:$B,Crops!Z$6,'Input data - Other'!$D:$D,Crops!$E40),"") -> 0.156 | AA40: =IF(F40<>"",SUMIFS('Input data - Other'!$F:$F,'Input data - Other'!$B:$B,Crops!AA$6,'Input data - Other'!$D:$D,Crops!$E40),"") -> 0
B41: \I: | K41: =IF(Y10=0,"\I:"," ") -> \I: | O41: RICSTR | P41: =IF(IFERROR(VLOOKUP($K41,'Calc - Crops'!$L$24:$Y$47,8,FALSE)," ")=0," ",IFERROR(VLOOKUP($K41,'Calc - Crops'!$L$24:$Y$47,8,FALSE)/1000," ")) | Q41: =IF(IFERROR(P41/(IFERROR(VLOOKUP(F41,'Calc - water'!$B$39:$G$48,6,FALSE),"")*IFERROR(VLOOKUP(E41,DefaultAFOLU!$C$32:$G$39,5,FALSE),"")),"")=0," ",IFERROR(P41/(IFERROR(VLOOKUP(F41,'Calc - water'!$B$39:$G$48,6,FALSE),"")*IFERROR(VLOOKUP(E41,DefaultAFOLU!$C$32:$G$39,5,FALSE),"")),"")) | T41: =IF(Y41=0,Intro!$B$16+1,"") | U41: =IFERROR(VLOOKUP(O41,DefaultAFOLU!$D$42:$G$50,4,TRUE)," ") -> 0.3 | V41: =IF(IFERROR(VLOOKUP($K41,'Calc - Crops'!$L$24:$Y$47,11,FALSE)," ")=0," ",IFERROR(VLOOKUP($K41,'Calc - Crops'!$L$24:$Y$47,11,FALSE)/$P41," ")) | W41: =IF(IFERROR(VLOOKUP($K41,'Calc - Crops'!$L$24:$Y$47,10,FALSE)," ")=0," ",IFERROR(VLOOKUP($K41,'Calc - Crops'!$L$24:$Y$47,10,FALSE)/$P41," ")) | X41: =IF(IFERROR(VLOOKUP($K41,'Calc - Crops'!$L$24:$Y$47,9,FALSE)," ")=0," ",IFERROR(VLOOKUP($K41,'Calc - Crops'!$L$24:$Y$47,9,FALSE)/$P41," ")) | Y41: =IFERROR(VLOOKUP($C41,'Calc - Crops'!$L$24:$Y$47,2,FALSE)/1000, " ") | Z41: =IF(E41<>"",SUMIFS('Input data - Other'!$F:$F,'Input data - Other'!$B:$B,Crops!Z$6,'Input data - Other'!$D:$D,Crops!$E41),"") | AA41: =IF(F41<>"",SUMIFS('Input data - Other'!$F:$F,'Input data - Other'!$B:$B,Crops!AA$6,'Input data - Other'!$D:$D,Crops!$E41),"")
B42: =IF(Y12=0,"\I:","DMD") -> DMD | C42: AFOCRPOFOLEGWTRE0 | D42: Afolu Crops Organic Legumes Existing 0 | E42: Organic | F42: Legumes | G42: Mton | H42: kha | I42: Annual | K42: =IF(Y12=0,"\I:",C42) -> AFOCRPOFOLEGWTRE0 | L42: Afolu Crops Organic Legumes Existing 0 | M42: WTRAFO | N42: AFOCRPLEGDEM | P42: =IF(IFERROR(VLOOKUP($K42,'Calc - Crops'!$L$24:$Y$47,8,FALSE)," ")=0," ",IFERROR(VLOOKUP($K42,'Calc - Crops'!$L$24:$Y$47,8,FALSE)/1000," ")) -> 0.00024914735 | Q42: =IF(IFERROR(P42/(IFERROR(VLOOKUP(F42,'Calc - water'!$B$39:$G$48,6,FALSE),"")*IFERROR(VLOOKUP(E42,DefaultAFOLU!$C$32:$G$39,5,FALSE),"")),"")=0," ",IFERROR(P42/(IFERROR(VLOOKUP(F42,'Calc - water'!$B$39:$G$48,6,FALSE),"")*IFERROR(VLOOKUP(E42,DefaultAFOLU!$C$32:$G$39,5,FALSE),"")),"")) -> 0.0050285207 | R42: 1 | S42: 4 | T42: =IF(Y42=0,Intro!$B$16+1,"") -> 2023 | V42: =IF(IFERROR(VLOOKUP($K42,'Calc - Crops'!$L$24:$Y$47,11,FALSE)," ")=0," ",IFERROR(VLOOKUP($K42,'Calc - Crops'!$L$24:$Y$47,11,FALSE)/$P42," ")) -> 32784.02 | W42: =IF(IFERROR(VLOOKUP($K42,'Calc - Crops'!$L$24:$Y$47,10,FALSE)," ")=0," ",IFERROR(VLOOKUP($K42,'Calc - Crops'!$L$24:$Y$47,10,FALSE)/$P42," ")) -> 1.6782475 | X42: =IF(IFERROR(VLOOKUP($K42,'Calc - Crops'!$L$24:$Y$47,9,FALSE)," ")=0," ",IFERROR(VLOOKUP($K42,'Calc - Crops'!$L$24:$Y$47,9,FALSE)/$P42," ")) -> 32.915392 | Y42: =IFERROR(VLOOKUP($C42,'Calc - Crops'!$L$24:$Y$47,2,FALSE)/1000, " ") -> 0 | Z42: =IF(E42<>"",SUMIFS('Input data - Other'!$F:$F,'Input data - Other'!$B:$B,Crops!Z$6,'Input data - Other'!$D:$D,Crops!$E42),"") -> 0.156 | AA42: =IF(F42<>"",SUMIFS('Input data - Other'!$F:$F,'Input data - Other'!$B:$B,Crops!AA$6,'Input data - Other'!$D:$D,Crops!$E42),"") -> 0
B43: \I: | K43: =IF(Y12=0,"\I:"," ") | O43: LEGWSB | P43: =IF(IFERROR(VLOOKUP($K43,'Calc - Crops'!$L$24:$Y$47,8,FALSE)," ")=0," ",IFERROR(VLOOKUP($K43,'Calc - Crops'!$L$24:$Y$47,8,FALSE)/1000," ")) | Q43: =IF(IFERROR(P43/(IFERROR(VLOOKUP(F43,'Calc - water'!$B$39:$G$48,6,FALSE),"")*IFERROR(VLOOKUP(E43,DefaultAFOLU!$C$32:$G$39,5,FALSE),"")),"")=0," ",IFERROR(P43/(IFERROR(VLOOKUP(F43,'Calc - water'!$B$39:$G$48,6,FALSE),"")*IFERROR(VLOOKUP(E43,DefaultAFOLU!$C$32:$G$39,5,FALSE),"")),"")) | T43: =IF(Y43=0,Intro!$B$16+1,"") | U43: =IFERROR(VLOOKUP(O43,DefaultAFOLU!$D$42:$G$50,4,TRUE)," ") -> 0.3 | V43: =IF(IFERROR(VLOOKUP($K43,'Calc - Crops'!$L$24:$Y$47,11,FALSE)," ")=0," ",IFERROR(VLOOKUP($K43,'Calc - Crops'!$L$24:$Y$47,11,FALSE)/$P43," ")) | W43: =IF(IFERROR(VLOOKUP($K43,'Calc - Crops'!$L$24:$Y$47,10,FALSE)," ")=0," ",IFERROR(VLOOKUP($K43,'Calc - Crops'!$L$24:$Y$47,10,FALSE)/$P43," ")) | X43: =IF(IFERROR(VLOOKUP($K43,'Calc - Crops'!$L$24:$Y$47,9,FALSE)," ")=0," ",IFERROR(VLOOKUP($K43,'Calc - Crops'!$L$24:$Y$47,9,FALSE)/$P43," ")) | Y43: =IFERROR(VLOOKUP($C43,'Calc - Crops'!$L$24:$Y$47,2,FALSE)/1000, " ") | Z43: =IF(E43<>"",SUMIFS('Input data - Other'!$F:$F,'Input data - Other'!$B:$B,Crops!Z$6,'Input data - Other'!$D:$D,Crops!$E43),"") | AA43: =IF(F43<>"",SUMIFS('Input data - Other'!$F:$F,'Input data - Other'!$B:$B,Crops!AA$6,'Input data - Other'!$D:$D,Crops!$E43),"")
B44: =IF(Y14=0,"\I:","DMD") -> DMD | C44: AFOCRPOFOSEEWTRE0 | D44: Afolu Crops Organic Seeds Existing 0 | E44: Organic | F44: Seeds | G44: Mton | H44: kha | I44: Annual | K44: =IF(Y14=0,"\I:",C44) -> AFOCRPOFOSEEWTRE0 | L44: Afolu Crops Organic Seeds Existing 0 | M44: WTRAFO | N44: AFOCRPSEEDEM | P44: =IF(IFERROR(VLOOKUP($K44,'Calc - Crops'!$L$24:$Y$47,8,FALSE)," ")=0," ",IFERROR(VLOOKUP($K44,'Calc - Crops'!$L$24:$Y$47,8,FALSE)/1000," ")) -> 0.0002517075 | Q44: =IF(IFERROR(P44/(IFERROR(VLOOKUP(F44,'Calc - water'!$B$39:$G$48,6,FALSE),"")*IFERROR(VLOOKUP(E44,DefaultAFOLU!$C$32:$G$39,5,FALSE),"")),"")=0," ",IFERROR(P44/(IFERROR(VLOOKUP(F44,'Calc - water'!$B$39:$G$48,6,FALSE),"")*IFERROR(VLOOKUP(E44,DefaultAFOLU!$C$32:$G$39,5,FALSE),"")),"")) -> 0.0039965098 | R44: 1 | S44: 4 | T44: =IF(Y44=0,Intro!$B$16+1,"") -> 2023 | V44: =IF(IFERROR(VLOOKUP($K44,'Calc - Crops'!$L$24:$Y$47,11,FALSE)," ")=0," ",IFERROR(VLOOKUP($K44,'Calc - Crops'!$L$24:$Y$47,11,FALSE)/$P44," ")) -> 32450.569 | W44: =IF(IFERROR(VLOOKUP($K44,'Calc - Crops'!$L$24:$Y$47,10,FALSE)," ")=0," ",IFERROR(VLOOKUP($K44,'Calc - Crops'!$L$24:$Y$47,10,FALSE)/$P44," ")) -> 1.6611778 | X44: =IF(IFERROR(VLOOKUP($K44,'Calc - Crops'!$L$24:$Y$47,9,FALSE)," ")=0," ",IFERROR(VLOOKUP($K44,'Calc - Crops'!$L$24:$Y$47,9,FALSE)/$P44," ")) -> 32.580605 | Y44: =IFERROR(VLOOKUP($C44,'Calc - Crops'!$L$24:$Y$47,2,FALSE)/1000, " ") -> 0 | Z44: =IF(E44<>"",SUMIFS('Input data - Other'!$F:$F,'Input data - Other'!$B:$B,Crops!Z$6,'Input data - Other'!$D:$D,Crops!$E44),"") -> 0.156 | AA44: =IF(F44<>"",SUMIFS('Input data - Other'!$F:$F,'Input data - Other'!$B:$B,Crops!AA$6,'Input data - Other'!$D:$D,Crops!$E44),"") -> 0
B45: \I: | K45: =IF(Y14=0,"\I:"," ") | O45: SEEWSB | P45: =IF(IFERROR(VLOOKUP($K45,'Calc - Crops'!$L$24:$Y$47,8,FALSE)," ")=0," ",IFERROR(VLOOKUP($K45,'Calc - Crops'!$L$24:$Y$47,8,FALSE)/1000," ")) | Q45: =IF(IFERROR(P45/(IFERROR(VLOOKUP(F45,'Calc - water'!$B$39:$G$48,6,FALSE),"")*IFERROR(VLOOKUP(E45,DefaultAFOLU!$C$32:$G$39,5,FALSE),"")),"")=0," ",IFERROR(P45/(IFERROR(VLOOKUP(F45,'Calc - water'!$B$39:$G$48,6,FALSE),"")*IFERROR(VLOOKUP(E45,DefaultAFOLU!$C$32:$G$39,5,FALSE),"")),"")) | T45: =IF(Y45=0,Intro!$B$16+1,"") | U45: =IFERROR(VLOOKUP(O45,DefaultAFOLU!$D$42:$G$50,4,TRUE)," ") -> 0.3 | V45: =IF(IFERROR(VLOOKUP($K45,'Calc - Crops'!$L$24:$Y$47,11,FALSE)," ")=0," ",IFERROR(VLOOKUP($K45,'Calc - Crops'!$L$24:$Y$47,11,FALSE)/$P45," ")) | W45: =IF(IFERROR(VLOOKUP($K45,'Calc - Crops'!$L$24:$Y$47,10,FALSE)," ")=0," ",IFERROR(VLOOKUP($K45,'Calc - Crops'!$L$24:$Y$47,10,FALSE)/$P45," ")) | X45: =IF(IFERROR(VLOOKUP($K45,'Calc - Crops'!$L$24:$Y$47,9,FALSE)," ")=0," ",IFERROR(VLOOKUP($K45,'Calc - Crops'!$L$24:$Y$47,9,FALSE)/$P45," ")) | Y45: =IFERROR(VLOOKUP($C45,'Calc - Crops'!$L$24:$Y$47,2,FALSE)/1000, " ") | Z45: =IF(E45<>"",SUMIFS('Input data - Other'!$F:$F,'Input data - Other'!$B:$B,Crops!Z$6,'Input data - Other'!$D:$D,Crops!$E45),"") | AA45: =IF(F45<>"",SUMIFS('Input data - Other'!$F:$F,'Input data - Other'!$B:$B,Crops!AA$6,'Input data - Other'!$D:$D,Crops!$E45),"")
B46: =IF(Y16=0,"\I:","DMD") -> \I: | C46: AFOCRPOFOFCRWTRE0 | D46: Afolu Crops Organic Fiber crops Existing 0 | E46: Organic | F46: Fiber crops | G46: Mton | H46: kha | I46: Annual | K46: =IF(Y16=0,"\I:",C46) -> \I: | L46: Afolu Crops Organic Fiber crops Existing 0 | M46: WTRAFO | N46: AFOCRPFCRDEM | P46: =IF(IFERROR(VLOOKUP($K46,'Calc - Crops'!$L$24:$Y$47,8,FALSE)," ")=0," ",IFERROR(VLOOKUP($K46,'Calc - Crops'!$L$24:$Y$47,8,FALSE)/1000," ")) | Q46: =IF(IFERROR(P46/(IFERROR(VLOOKUP(F46,'Calc - water'!$B$39:$G$48,6,FALSE),"")*IFERROR(VLOOKUP(E46,DefaultAFOLU!$C$32:$G$39,5,FALSE),"")),"")=0," ",IFERROR(P46/(IFERROR(VLOOKUP(F46,'Calc - water'!$B$39:$G$48,6,FALSE),"")*IFERROR(VLOOKUP(E46,DefaultAFOLU!$C$32:$G$39,5,FALSE),"")),"")) | R46: 1 | S46: 4 | T46: =IF(Y46=0,Intro!$B$16+1,"") -> 2023 | V46: =IF(IFERROR(VLOOKUP($K46,'Calc - Crops'!$L$24:$Y$47,11,FALSE)," ")=0," ",IFERROR(VLOOKUP($K46,'Calc - Crops'!$L$24:$Y$47,11,FALSE)/$P46," ")) | W46: =IF(IFERROR(VLOOKUP($K46,'Calc - Crops'!$L$24:$Y$47,10,FALSE)," ")=0," ",IFERROR(VLOOKUP($K46,'Calc - Crops'!$L$24:$Y$47,10,FALSE)/$P46," ")) | X46: =IF(IFERROR(VLOOKUP($K46,'Calc - Crops'!$L$24:$Y$47,9,FALSE)," ")=0," ",IFERROR(VLOOKUP($K46,'Calc - Crops'!$L$24:$Y$47,9,FALSE)/$P46," ")) | Y46: =IFERROR(VLOOKUP($C46,'Calc - Crops'!$L$24:$Y$47,2,FALSE)/1000, " ") -> 0 | Z46: =IF(E46<>"",SUMIFS('Input data - Other'!$F:$F,'Input data - Other'!$B:$B,Crops!Z$6,'Input data - Other'!$D:$D,Crops!$E46),"") -> 0.156 | AA46: =IF(F46<>"",SUMIFS('Input data - Other'!$F:$F,'Input data - Other'!$B:$B,Crops!AA$6,'Input data - Other'!$D:$D,Crops!$E46),"") -> 0
B47: \I: | K47: =IF(Y16=0,"\I:"," ") -> \I: | O47: FCRWSB | P47: =IF(IFERROR(VLOOKUP($K47,'Calc - Crops'!$L$24:$Y$47,8,FALSE)," ")=0," ",IFERROR(VLOOKUP($K47,'Calc - Crops'!$L$24:$Y$47,8,FALSE)/1000," ")) | Q47: =IF(IFERROR(P47/(IFERROR(VLOOKUP(F47,'Calc - water'!$B$39:$G$48,6,FALSE),"")*IFERROR(VLOOKUP(E47,DefaultAFOLU!$C$32:$G$39,5,FALSE),"")),"")=0," ",IFERROR(P47/(IFERROR(VLOOKUP(F47,'Calc - water'!$B$39:$G$48,6,FALSE),"")*IFERROR(VLOOKUP(E47,DefaultAFOLU!$C$32:$G$39,5,FALSE),"")),"")) | T47: =IF(Y47=0,Intro!$B$16+1,"") | U47: =IFERROR(VLOOKUP(O47,DefaultAFOLU!$D$42:$G$50,4,TRUE)," ") -> 0.3 | V47: =IF(IFERROR(VLOOKUP($K47,'Calc - Crops'!$L$24:$Y$47,11,FALSE)," ")=0," ",IFERROR(VLOOKUP($K47,'Calc - Crops'!$L$24:$Y$47,11,FALSE)/$P47," ")) | W47: =IF(IFERROR(VLOOKUP($K47,'Calc - Crops'!$L$24:$Y$47,10,FALSE)," ")=0," ",IFERROR(VLOOKUP($K47,'Calc - Crops'!$L$24:$Y$47,10,FALSE)/$P47," ")) | X47: =IF(IFERROR(VLOOKUP($K47,'Calc - Crops'!$L$24:$Y$47,9,FALSE)," ")=0," ",IFERROR(VLOOKUP($K47,'Calc - Crops'!$L$24:$Y$47,9,FALSE)/$P47," ")) | Y47: =IFERROR(VLOOKUP($C47,'Calc - Crops'!$L$24:$Y$47,2,FALSE)/1000, " ") | Z47: =IF(E47<>"",SUMIFS('Input data - Other'!$F:$F,'Input data - Other'!$B:$B,Crops!Z$6,'Input data - Other'!$D:$D,Crops!$E47),"") | AA47: =IF(F47<>"",SUMIFS('Input data - Other'!$F:$F,'Input data - Other'!$B:$B,Crops!AA$6,'Input data - Other'!$D:$D,Crops!$E47),"")
B48: =IF(Y18=0,"\I:","DMD") -> DMD | C48: AFOCRPOFOVEGWTRE0 | D48: Afolu Crops Organic Vegetables Existing 0 | E48: Organic | F48: Vegetables | G48: Mton | H48: kha | I48: Annual | K48: =IF(Y18=0,"\I:",C48) -> AFOCRPOFOVEGWTRE0 | L48: Afolu Crops Organic Vegetables Existing 0 | M48: WTRAFO | N48: AFOCRPVEGDEM | P48: =IF(IFERROR(VLOOKUP($K48,'Calc - Crops'!$L$24:$Y$47,8,FALSE)," ")=0," ",IFERROR(VLOOKUP($K48,'Calc - Crops'!$L$24:$Y$47,8,FALSE)/1000," ")) -> 0.0035594959 | Q48: =IF(IFERROR(P48/(IFERROR(VLOOKUP(F48,'Calc - water'!$B$39:$G$48,6,FALSE),"")*IFERROR(VLOOKUP(E48,DefaultAFOLU!$C$32:$G$39,5,FALSE),"")),"")=0," ",IFERROR(P48/(IFERROR(VLOOKUP(F48,'Calc - water'!$B$39:$G$48,6,FALSE),"")*IFERROR(VLOOKUP(E48,DefaultAFOLU!$C$32:$G$39,5,FALSE),"")),"")) -> 0.0042398841 | R48: 1 | S48: 4 | T48: =IF(Y48=0,Intro!$B$16+1,"") | V48: =IF(IFERROR(VLOOKUP($K48,'Calc - Crops'!$L$24:$Y$47,11,FALSE)," ")=0," ",IFERROR(VLOOKUP($K48,'Calc - Crops'!$L$24:$Y$47,11,FALSE)/$P48," ")) -> 2294.7214 | W48: =IF(IFERROR(VLOOKUP($K48,'Calc - Crops'!$L$24:$Y$47,10,FALSE)," ")=0," ",IFERROR(VLOOKUP($K48,'Calc - Crops'!$L$24:$Y$47,10,FALSE)/$P48," ")) -> 0.11746914 | X48: =IF(IFERROR(VLOOKUP($K48,'Calc - Crops'!$L$24:$Y$47,9,FALSE)," ")=0," ",IFERROR(VLOOKUP($K48,'Calc - Crops'!$L$24:$Y$47,9,FALSE)/$P48," ")) -> 2.3039168 | Y48: =IFERROR(VLOOKUP($C48,'Calc - Crops'!$L$24:$Y$47,2,FALSE)/1000, " ") -> 0.644 | Z48: =IF(E48<>"",SUMIFS('Input data - Other'!$F:$F,'Input data - Other'!$B:$B,Crops!Z$6,'Input data - Other'!$D:$D,Crops!$E48),"") -> 0.156 | AA48: =IF(F48<>"",SUMIFS('Input data - Other'!$F:$F,'Input data - Other'!$B:$B,Crops!AA$6,'Input data - Other'!$D:$D,Crops!$E48),"") -> 0
B49: \I: | K49: =IF(Y18=0,"\I:"," ") | O49: VEGWSB | P49: =IF(IFERROR(VLOOKUP($K49,'Calc - Crops'!$L$24:$Y$47,8,FALSE)," ")=0," ",IFERROR(VLOOKUP($K49,'Calc - Crops'!$L$24:$Y$47,8,FALSE)/1000," ")) | Q49: =IF(IFERROR(P49/(IFERROR(VLOOKUP(F49,'Calc - water'!$B$39:$G$48,6,FALSE),"")*IFERROR(VLOOKUP(E49,DefaultAFOLU!$C$32:$G$39,5,FALSE),"")),"")=0," ",IFERROR(P49/(IFERROR(VLOOKUP(F49,'Calc - water'!$B$39:$G$48,6,FALSE),"")*IFERROR(VLOOKUP(E49,DefaultAFOLU!$C$32:$G$39,5,FALSE),"")),"")) | T49: =IF(Y49=0,Intro!$B$16+1,"") | U49: =IFERROR(VLOOKUP(O49,DefaultAFOLU!$D$42:$G$50,4,TRUE)," ") -> 0.1 | V49: =IF(IFERROR(VLOOKUP($K49,'Calc - Crops'!$L$24:$Y$47,11,FALSE)," ")=0," ",IFERROR(VLOOKUP($K49,'Calc - Crops'!$L$24:$Y$47,11,FALSE)/$P49," ")) | W49: =IF(IFERROR(VLOOKUP($K49,'Calc - Crops'!$L$24:$Y$47,10,FALSE)," ")=0," ",IFERROR(VLOOKUP($K49,'Calc - Crops'!$L$24:$Y$47,10,FALSE)/$P49," ")) | X49: =IF(IFERROR(VLOOKUP($K49,'Calc - Crops'!$L$24:$Y$47,9,FALSE)," ")=0," ",IFERROR(VLOOKUP($K49,'Calc - Crops'!$L$24:$Y$47,9,FALSE)/$P49," ")) | Y49: =IFERROR(VLOOKUP($C49,'Calc - Crops'!$L$24:$Y$47,2,FALSE)/1000, " ") | Z49: =IF(E49<>"",SUMIFS('Input data - Other'!$F:$F,'Input data - Other'!$B:$B,Crops!Z$6,'Input data - Other'!$D:$D,Crops!$E49),"") | AA49: =IF(F49<>"",SUMIFS('Input data - Other'!$F:$F,'Input data - Other'!$B:$B,Crops!AA$6,'Input data - Other'!$D:$D,Crops!$E49),"")
B50: =IF(Y20=0,"\I:","DMD") -> DMD | C50: AFOCRPOFOWCRWTRE0 | D50: Afolu Crops Organic Woody crops Existing 0 | E50: Organic | F50: Woody crops | G50: Mton | H50: kha | I50: Annual | K50: =IF(Y20=0,"\I:",C50) -> AFOCRPOFOWCRWTRE0 | L50: Afolu Crops Organic Woody crops Existing 0 | M50: WTRAFO | N50: AFOCRPWCRDEM | P50: =IF(IFERROR(VLOOKUP($K50,'Calc - Crops'!$L$24:$Y$47,8,FALSE)," ")=0," ",IFERROR(VLOOKUP($K50,'Calc - Crops'!$L$24:$Y$47,8,FALSE)/1000," ")) -> 0.0011413741 | Q50: =IF(IFERROR(P50/(IFERROR(VLOOKUP(F50,'Calc - water'!$B$39:$G$48,6,FALSE),"")*IFERROR(VLOOKUP(E50,DefaultAFOLU!$C$32:$G$39,5,FALSE),"")),"")=0," ",IFERROR(P50/(IFERROR(VLOOKUP(F50,'Calc - water'!$B$39:$G$48,6,FALSE),"")*IFERROR(VLOOKUP(E50,DefaultAFOLU!$C$32:$G$39,5,FALSE),"")),"")) -> 11.413741 | R50: 1 | S50: 4 | T50: =IF(Y50=0,Intro!$B$16+1,"") -> 2023 | V50: =IF(IFERROR(VLOOKUP($K50,'Calc - Crops'!$L$24:$Y$47,11,FALSE)," ")=0," ",IFERROR(VLOOKUP($K50,'Calc - Crops'!$L$24:$Y$47,11,FALSE)/$P50," ")) -> 7156.3315 | W50: =IF(IFERROR(VLOOKUP($K50,'Calc - Crops'!$L$24:$Y$47,10,FALSE)," ")=0," ",IFERROR(VLOOKUP($K50,'Calc - Crops'!$L$24:$Y$47,10,FALSE)/$P50," ")) -> 0.36633992 | X50: =IF(IFERROR(VLOOKUP($K50,'Calc - Crops'!$L$24:$Y$47,9,FALSE)," ")=0," ",IFERROR(VLOOKUP($K50,'Calc - Crops'!$L$24:$Y$47,9,FALSE)/$P50," ")) -> 7.1850082 | Y50: =IFERROR(VLOOKUP($C50,'Calc - Crops'!$L$24:$Y$47,2,FALSE)/1000, " ") -> 0 | Z50: =IF(E50<>"",SUMIFS('Input data - Other'!$F:$F,'Input data - Other'!$B:$B,Crops!Z$6,'Input data - Other'!$D:$D,Crops!$E50),"") -> 0.156 | AA50: =IF(F50<>"",SUMIFS('Input data - Other'!$F:$F,'Input data - Other'!$B:$B,Crops!AA$6,'Input data - Other'!$D:$D,Crops!$E50),"") -> 0
B51: \I: | K51: =IF(Y20=0,"\I:"," ") | O51: WCRWOC | P51: =IF(IFERROR(VLOOKUP($K51,'Calc - Crops'!$L$24:$Y$47,8,FALSE)," ")=0," ",IFERROR(VLOOKUP($K51,'Calc - Crops'!$L$24:$Y$47,8,FALSE)/1000," ")) | Q51: =IF(IFERROR(P51/(IFERROR(VLOOKUP(F51,'Calc - water'!$B$39:$G$48,6,FALSE),"")*IFERROR(VLOOKUP(E51,DefaultAFOLU!$C$32:$G$39,5,FALSE),"")),"")=0," ",IFERROR(P51/(IFERROR(VLOOKUP(F51,'Calc - water'!$B$39:$G$48,6,FALSE),"")*IFERROR(VLOOKUP(E51,DefaultAFOLU!$C$32:$G$39,5,FALSE),"")),"")) | T51: =IF(Y51=0,Intro!$B$16+1,"") | U51: =IFERROR(VLOOKUP(O51,DefaultAFOLU!$D$42:$G$50,4,TRUE)," ") -> 0.1 | V51: =IF(IFERROR(VLOOKUP($K51,'Calc - Crops'!$L$24:$Y$47,11,FALSE)," ")=0," ",IFERROR(VLOOKUP($K51,'Calc - Crops'!$L$24:$Y$47,11,FALSE)/$P51," ")) | W51: =IF(IFERROR(VLOOKUP($K51,'Calc - Crops'!$L$24:$Y$47,10,FALSE)," ")=0," ",IFERROR(VLOOKUP($K51,'Calc - Crops'!$L$24:$Y$47,10,FALSE)/$P51," ")) | X51: =IF(IFERROR(VLOOKUP($K51,'Calc - Crops'!$L$24:$Y$47,9,FALSE)," ")=0," ",IFERROR(VLOOKUP($K51,'Calc - Crops'!$L$24:$Y$47,9,FALSE)/$P51," ")) | Y51: =IFERROR(VLOOKUP($C51,'Calc - Crops'!$L$24:$Y$47,2,FALSE)/1000, " ") | Z51: =IF(E51<>"",SUMIFS('Input data - Other'!$F:$F,'Input data - Other'!$B:$B,Crops!Z$6,'Input data - Other'!$D:$D,Crops!$E51),"") | AA51: =IF(F51<>"",SUMIFS('Input data - Other'!$F:$F,'Input data - Other'!$B:$B,Crops!AA$6,'Input data - Other'!$D:$D,Crops!$E51),"")
B52: =IF(Y22=0,"\I:","DMD") -> DMD | C52: AFOCRPOFOROOWTRE0 | D52: Afolu Crops Organic Roots Existing 0 | E52: Organic | F52: Roots | G52: Mton | H52: kha | I52: Annual | K52: =IF(Y22=0,"\I:",C52) -> AFOCRPOFOROOWTRE0 | L52: Afolu Crops Organic Roots Existing 0 | M52: WTRAFO | N52: AFOCRPROODEM | P52: =IF(IFERROR(VLOOKUP($K52,'Calc - Crops'!$L$24:$Y$47,8,FALSE)," ")=0," ",IFERROR(VLOOKUP($K52,'Calc - Crops'!$L$24:$Y$47,8,FALSE)/1000," ")) -> 0.0039404283 | Q52: =IF(IFERROR(P52/(IFERROR(VLOOKUP(F52,'Calc - water'!$B$39:$G$48,6,FALSE),"")*IFERROR(VLOOKUP(E52,DefaultAFOLU!$C$32:$G$39,5,FALSE),"")),"")=0," ",IFERROR(P52/(IFERROR(VLOOKUP(F52,'Calc - water'!$B$39:$G$48,6,FALSE),"")*IFERROR(VLOOKUP(E52,DefaultAFOLU!$C$32:$G$39,5,FALSE),"")),"")) -> 0.011969969 | R52: 1 | S52: 4 | T52: =IF(Y52=0,Intro!$B$16+1,"") -> 2023 | V52: =IF(IFERROR(VLOOKUP($K52,'Calc - Crops'!$L$24:$Y$47,11,FALSE)," ")=0," ",IFERROR(VLOOKUP($K52,'Calc - Crops'!$L$24:$Y$47,11,FALSE)/$P52," ")) -> 2072.8842 | W52: =IF(IFERROR(VLOOKUP($K52,'Calc - Crops'!$L$24:$Y$47,10,FALSE)," ")=0," ",IFERROR(VLOOKUP($K52,'Calc - Crops'!$L$24:$Y$47,10,FALSE)/$P52," ")) -> 0.10611306 | X52: =IF(IFERROR(VLOOKUP($K52,'Calc - Crops'!$L$24:$Y$47,9,FALSE)," ")=0," ",IFERROR(VLOOKUP($K52,'Calc - Crops'!$L$24:$Y$47,9,FALSE)/$P52," ")) -> 2.0811907 | Y52: =IFERROR(VLOOKUP($C52,'Calc - Crops'!$L$24:$Y$47,2,FALSE)/1000, " ") -> 0 | Z52: =IF(E52<>"",SUMIFS('Input data - Other'!$F:$F,'Input data - Other'!$B:$B,Crops!Z$6,'Input data - Other'!$D:$D,Crops!$E52),"") -> 0.156 | AA52: =IF(F52<>"",SUMIFS('Input data - Other'!$F:$F,'Input data - Other'!$B:$B,Crops!AA$6,'Input data - Other'!$D:$D,Crops!$E52),"") -> 0
B53: \I: | K53: =IF(Y22=0,"\I:"," ") | O53: ROOWSB | P53: =IF(IFERROR(VLOOKUP($K53,'Calc - Crops'!$L$24:$Y$47,8,FALSE)," ")=0," ",IFERROR(VLOOKUP($K53,'Calc - Crops'!$L$24:$Y$47,8,FALSE)/1000," ")) | Q53: =IF(IFERROR(P53/(IFERROR(VLOOKUP(F53,'Calc - water'!$B$39:$G$48,6,FALSE),"")*IFERROR(VLOOKUP(E53,DefaultAFOLU!$C$32:$G$39,5,FALSE),"")),"")=0," ",IFERROR(P53/(IFERROR(VLOOKUP(F53,'Calc - water'!$B$39:$G$48,6,FALSE),"")*IFERROR(VLOOKUP(E53,DefaultAFOLU!$C$32:$G$39,5,FALSE),"")),"")) | T53: =IF(Y53=0,Intro!$B$16+1,"") | U53: =IFERROR(VLOOKUP(O53,DefaultAFOLU!$D$42:$G$50,4,TRUE)," ") -> 0.3 | V53: =IF(IFERROR(VLOOKUP($K53,'Calc - Crops'!$L$24:$Y$47,11,FALSE)," ")=0," ",IFERROR(VLOOKUP($K53,'Calc - Crops'!$L$24:$Y$47,11,FALSE)/$P53," ")) | W53: =IF(IFERROR(VLOOKUP($K53,'Calc - Crops'!$L$24:$Y$47,10,FALSE)," ")=0," ",IFERROR(VLOOKUP($K53,'Calc - Crops'!$L$24:$Y$47,10,FALSE)/$P53," ")) | X53: =IF(IFERROR(VLOOKUP($K53,'Calc - Crops'!$L$24:$Y$47,9,FALSE)," ")=0," ",IFERROR(VLOOKUP($K53,'Calc - Crops'!$L$24:$Y$47,9,FALSE)/$P53," ")) | Y53: =IFERROR(VLOOKUP($C53,'Calc - Crops'!$L$24:$Y$47,2,FALSE)/1000, " ") | Z53: =IF(E53<>"",SUMIFS('Input data - Other'!$F:$F,'Input data - Other'!$B:$B,Crops!Z$6,'Input data - Other'!$D:$D,Crops!$E53),"") | AA53: =IF(F53<>"",SUMIFS('Input data - Other'!$F:$F,'Input data - Other'!$B:$B,Crops!AA$6,'Input data - Other'!$D:$D,Crops!$E53),"")
B54: =IF(Y24=0,"\I:","DMD") -> DMD | C54: AFOCRPOFOHAGWTRE0 | D54: Afolu Crops Organic Herbs and greens Existing 0 | E54: Organic | F54: Herbs and greens | G54: Mton | H54: kha | I54: Annual | K54: =IF(Y24=0,"\I:",C54) -> AFOCRPOFOHAGWTRE0 | L54: Afolu Crops Organic Herbs and greens Existing 0 | M54: WTRAFO | N54: AFOCRPHAGDEM | P54: =IF(IFERROR(VLOOKUP($K54,'Calc - Crops'!$L$24:$Y$47,8,FALSE)," ")=0," ",IFERROR(VLOOKUP($K54,'Calc - Crops'!$L$24:$Y$47,8,FALSE)/1000," ")) -> 0.0010870333 | Q54: =IF(IFERROR(P54/(IFERROR(VLOOKUP(F54,'Calc - water'!$B$39:$G$48,6,FALSE),"")*IFERROR(VLOOKUP(E54,DefaultAFOLU!$C$32:$G$39,5,FALSE),"")),"")=0," ",IFERROR(P54/(IFERROR(VLOOKUP(F54,'Calc - water'!$B$39:$G$48,6,FALSE),"")*IFERROR(VLOOKUP(E54,DefaultAFOLU!$C$32:$G$39,5,FALSE),"")),"")) -> 10.870333 | R54: 1 | S54: 4 | T54: =IF(Y54=0,Intro!$B$16+1,"") -> 2023 | V54: =IF(IFERROR(VLOOKUP($K54,'Calc - Crops'!$L$24:$Y$47,11,FALSE)," ")=0," ",IFERROR(VLOOKUP($K54,'Calc - Crops'!$L$24:$Y$47,11,FALSE)/$P54," ")) -> 7514.0766 | W54: =IF(IFERROR(VLOOKUP($K54,'Calc - Crops'!$L$24:$Y$47,10,FALSE)," ")=0," ",IFERROR(VLOOKUP($K54,'Calc - Crops'!$L$24:$Y$47,10,FALSE)/$P54," ")) -> 0.38465326 | X54: =IF(IFERROR(VLOOKUP($K54,'Calc - Crops'!$L$24:$Y$47,9,FALSE)," ")=0," ",IFERROR(VLOOKUP($K54,'Calc - Crops'!$L$24:$Y$47,9,FALSE)/$P54," ")) -> 7.5441869 | Y54: =IFERROR(VLOOKUP($C54,'Calc - Crops'!$L$24:$Y$47,2,FALSE)/1000, " ") -> 0 | Z54: =IF(E54<>"",SUMIFS('Input data - Other'!$F:$F,'Input data - Other'!$B:$B,Crops!Z$6,'Input data - Other'!$D:$D,Crops!$E54),"") -> 0.156 | AA54: =IF(F54<>"",SUMIFS('Input data - Other'!$F:$F,'Input data - Other'!$B:$B,Crops!AA$6,'Input data - Other'!$D:$D,Crops!$E54),"") -> 0
B55: \I: | K55: =IF(Y24=0,"\I:"," ") | O55: HAGWSB | P55: =IF(IFERROR(VLOOKUP($K55,'Calc - Crops'!$L$24:$Y$47,8,FALSE)," ")=0," ",IFERROR(VLOOKUP($K55,'Calc - Crops'!$L$24:$Y$47,8,FALSE)/1000," ")) | Q55: =IF(IFERROR(P55/(IFERROR(VLOOKUP(F55,'Calc - water'!$B$39:$G$48,6,FALSE),"")*IFERROR(VLOOKUP(E55,DefaultAFOLU!$C$32:$G$39,5,FALSE),"")),"")=0," ",IFERROR(P55/(IFERROR(VLOOKUP(F55,'Calc - water'!$B$39:$G$48,6,FALSE),"")*IFERROR(VLOOKUP(E55,DefaultAFOLU!$C$32:$G$39,5,FALSE),"")),"")) | T55: =IF(Y55=0,Intro!$B$16+1,"") | U55: =IFERROR(VLOOKUP(O55,DefaultAFOLU!$D$42:$G$50,4,TRUE)," ") -> 0.3 | V55: =IF(IFERROR(VLOOKUP($K55,'Calc - Crops'!$L$24:$Y$47,11,FALSE)," ")=0," ",IFERROR(VLOOKUP($K55,'Calc - Crops'!$L$24:$Y$47,11,FALSE)/$P55," ")) | W55: =IF(IFERROR(VLOOKUP($K55,'Calc - Crops'!$L$24:$Y$47,10,FALSE)," ")=0," ",IFERROR(VLOOKUP($K55,'Calc - Crops'!$L$24:$Y$47,10,FALSE)/$P55," ")) | X55: =IF(IFERROR(VLOOKUP($K55,'Calc - Crops'!$L$24:$Y$47,9,FALSE)," ")=0," ",IFERROR(VLOOKUP($K55,'Calc - Crops'!$L$24:$Y$47,9,FALSE)/$P55," ")) | Y55: =IFERROR(VLOOKUP($C55,'Calc - Crops'!$L$24:$Y$47,2,FALSE)/1000, " ") | Z55: =IF(E55<>"",SUMIFS('Input data - Other'!$F:$F,'Input data - Other'!$B:$B,Crops!Z$6,'Input data - Other'!$D:$D,Crops!$E55),"") | AA55: =IF(F55<>"",SUMIFS('Input data - Other'!$F:$F,'Input data - Other'!$B:$B,Crops!AA$6,'Input data - Other'!$D:$D,Crops!$E55),"")
B57: ~FI_Process | K57: ~FI_T
B58: Sets | C58: TechName | D58: TechDesc | E58: Tact | F58: Tcap | G58: Tslvl | K58: TechName | L58: Comm-IN | M58: Comm-OUT | N58: CAP2ACT | O58: EFF
B59: * | C59: Name | D59: Description | E59: Activity | F59: Capacity | G59: Timeslice levels | K59: \I: Unit | L59: Mm3 | M59: Mton | N59: TJA/TJ | O59: TJ/Mton
B60: NRG | C60: AFOCRPCERTRA | D60: Transforming CER to biomass in upstream | E60: TJ | F60: TJA | G60: Annual | K60: AFOCRPCERTRA | L60: CERSTR | M60: STR | N60: 1 | O60: =VLOOKUP(L60,DefaultAFOLU!$E$64:$G$72,3,FALSE) -> 14400
B61: NRG | C61: AFOCRPRICTRA | D61: Transforming RIC to biomass in upstream | E61: TJ | F61: TJA | G61: Annual | K61: AFOCRPRICTRA | L61: RICSTR | M61: STR | N61: 1 | O61: =VLOOKUP(L61,DefaultAFOLU!$E$64:$G$72,3,FALSE) -> 14500
B62: NRG | C62: AFOCRPLEGTRA | D62: Transforming LEG to biomass in upstream | E62: TJ | F62: TJA | G62: Annual | K62: AFOCRPLEGTRA | L62: LEGWSB | M62: WSA | N62: 1 | O62: =VLOOKUP(L62,DefaultAFOLU!$E$64:$G$72,3,FALSE) -> 14400
B63: NRG | C63: AFOCRPSEETRA | D63: Transforming SEE to biomass in upstream | E63: TJ | F63: TJA | G63: Annual | K63: AFOCRPSEETRA | L63: SEEWSB | M63: WSA | N63: 1 | O63: =VLOOKUP(L63,DefaultAFOLU!$E$64:$G$72,3,FALSE) -> 20000
B64: NRG | C64: AFOCRPFCRTRA | D64: Transforming FCR to biomass in upstream | E64: TJ | F64: TJA | G64: Annual | K64: AFOCRPFCRTRA | L64: FCRWSB | M64: WSA | N64: 1 | O64: =VLOOKUP(L64,DefaultAFOLU!$E$64:$G$72,3,FALSE) -> 14400
B65: NRG | C65: AFOCRPVEGTRA | D65: Transforming VEG to biomass in upstream | E65: TJ | F65: TJA | G65: Annual | K65: AFOCRPVEGTRA | L65: VEGWSB | M65: WSA | N65: 1 | O65: =VLOOKUP(L65,DefaultAFOLU!$E$64:$G$72,3,FALSE) -> 12800
B66: NRG | C66: AFOCRPWCRTRA | D66: Transforming WCR to biomass in upstream | E66: TJ | F66: TJA | G66: Annual | K66: AFOCRPWCRTRA | L66: WCRWOC | M66: WOC | N66: 1 | O66: =VLOOKUP(L66,DefaultAFOLU!$E$64:$G$72,3,FALSE) -> 14400
B67: NRG | C67: AFOCRPROOTRA | D67: Transforming ROO to biomass in upstream | E67: TJ | F67: TJA | G67: Annual | K67: AFOCRPROOTRA | L67: ROOWSB | M67: WSA | N67: 1 | O67: =VLOOKUP(L67,DefaultAFOLU!$E$64:$G$72,3,FALSE) -> 14400
B68: NRG | C68: AFOCRPHAGTRA | D68: Transforming HAG to biomass in upstream | E68: TJ | F68: TJA | G68: Annual | K68: AFOCRPHAGTRA | L68: HAGWSB | M68: WSA | N68: 1 | O68: =VLOOKUP(L68,DefaultAFOLU!$E$64:$G$72,3,FALSE) -> 18000

Sheet CropsDemands
A1: This sheet contains the Demand for crops
B3: ~FI_Comm | I3: ~FI_T
B4: CSet | C4: CommName | D4: CommDesc | E4: Unit | F4: LimType | H4: CommName | I4: *Description | J4: DEMAND
B5: \I: | C5: Name | D5: Description | E5: Activity | H5: \I: Unit | J5: Mton
B6: =IF(H6="\I:","\I:","DEM") -> DEM | C6: AFOCRPCERDEM | D6: Cereal demand | E6: Mton | F6: FX | H6: =IF(SUM(J6:J6)=0,"\I:",C6) -> AFOCRPCERDEM | I6: Cereals | J6: =IFERROR(VLOOKUP($I6,'Calc - Crops'!$K$24:$O$32,5,FALSE)/1000000," ") -> 0.58231897
B7: =IF(H7="\I:","\I:","DEM") -> \I: | C7: AFOCRPRICDEM | D7: Rice demand | E7: Mton | F7: FX | H7: =IF(SUM(J7:J7)=0,"\I:",C7) -> \I: | I7: Rice | J7: =IFERROR(VLOOKUP($I7,'Calc - Crops'!$K$24:$O$32,5,FALSE)/1000000," ") -> 0
B8: =IF(H8="\I:","\I:","DEM") -> DEM | C8: AFOCRPLEGDEM | D8: Legumes demand | E8: Mton | F8: FX | H8: =IF(SUM(J8:J8)=0,"\I:",C8) -> AFOCRPLEGDEM | I8: Legumes | J8: =IFERROR(VLOOKUP($I8,'Calc - Crops'!$K$24:$O$32,5,FALSE)/1000000," ") -> 0.019293971
B9: =IF(H9="\I:","\I:","DEM") -> DEM | C9: AFOCRPSEEDEM | D9: Seed demand | E9: Mton | F9: FX | H9: =IF(SUM(J9:J9)=0,"\I:",C9) -> AFOCRPSEEDEM | I9: Seeds | J9: =IFERROR(VLOOKUP($I9,'Calc - Crops'!$K$24:$O$32,5,FALSE)/1000000," ") -> 0.042750002
B10: =IF(H10="\I:","\I:","DEM") -> \I: | C10: AFOCRPFCRDEM | D10: Fiber crops demand | E10: Mton | F10: FX | H10: =IF(SUM(J10:J10)=0,"\I:",C10) -> \I: | I10: Fiber crops | J10: =IFERROR(VLOOKUP($I10,'Calc - Crops'!$K$24:$O$32,5,FALSE)/1000000," ") -> 0
B11: =IF(H11="\I:","\I:","DEM") -> DEM | C11: AFOCRPVEGDEM | D11: Vegetables demand | E11: Mton | F11: FX | H11: =IF(SUM(J11:J11)=0,"\I:",C11) -> AFOCRPVEGDEM | I11: Vegetables | J11: =IFERROR(VLOOKUP($I11,'Calc - Crops'!$K$24:$O$32,5,FALSE)/1000000," ") -> 0.014517997
B12: =IF(H12="\I:","\I:","DEM") -> DEM | C12: AFOCRPWCRDEM | D12: Woody crops demand | E12: Mton | F12: FX | H12: =IF(SUM(J12:J12)=0,"\I:",C12) -> AFOCRPWCRDEM | I12: Woody crops | J12: =IFERROR(VLOOKUP($I12,'Calc - Crops'!$K$24:$O$32,5,FALSE)/1000000," ") -> 0.0034849957
B13: =IF(H13="\I:","\I:","DEM") -> DEM | C13: AFOCRPROODEM | D13: Roots demand | E13: Mton | F13: FX | H13: =IF(SUM(J13:J13)=0,"\I:",C13) -> AFOCRPROODEM | I13: Roots | J13: =IFERROR(VLOOKUP($I13,'Calc - Crops'!$K$24:$O$32,5,FALSE)/1000000," ") -> 0.28586494
B14: =IF(H14="\I:","\I:","DEM") -> DEM | C14: AFOCRPHAGDEM | D14: Herbs and greens demand | E14: Mton | F14: FX | H14: =IF(SUM(J14:J14)=0,"\I:",C14) -> AFOCRPHAGDEM | I14: Herbs and greens | J14: =IFERROR(VLOOKUP($I14,'Calc - Crops'!$K$24:$O$32,5,FALSE)/1000000," ") -> 0.0070149884

Sheet Livestock
A1: This sheet contains the Afolu sectors Livestock
B3: ~FI_Process | K3: ~FI_T
B4: Sets | C4: TechName | D4: TechDesc | E4: Tact | F4: Tcap | G4: Tslvl | H4: Vintage | J4: TechName | K4: *TechDesc | L4: Comm-IN | M4: Comm-OUT | N4: Comm-OUT-A | O4: CAP2ACT | P4: EFF | Q4: AFA~FX | R4: LIFE | S4: OUTPUT | T4: EMISSIONS~AFOLIVCH4 | U4: EMISSIONS~AFOMNRCH4 | V4: EMISSIONS~AFOMNRN2O | W4: NCAP_PASTI | X4: NCAP_COST | Z4: *For internal calculation purposes | AA4: *For internal calculation purposes | AB4: *For internal calculation purposes
B5: \I: | C5: Name | D5: Description | E5: Activity | F5: Capacity | G5: Timeslice levels | H5: Tracking of investment year | J5: \I: Unit | L5: Mm3 | M5: kHeads | N5: kHeadsA | O5: kHeadsA/kHeads | P5: kHeadsA/Mm3 | Q5: Annual aviability | R5: Years | S5: KtCH4/kHeadsA | T5: ktCH4/kHeadsA | U5: ktCH4/kHeadsA | V5: ktN2O/kHeadsA | W5: kHeads | X5: MEUR/kheads
B6: =IF(SUM(W6:W6)=0,"\I:","DMD") -> \I: | C6: AFOLIVGRSASSWTRE0 | D6: Afolu Livestock Grass Asses Existing 0 | E6: kHeadsA | F6: kHeads | G6: Annual | H6: NO | J6: =IF(SUM(W6:W6)=0,"\I:",C6) -> \I: | K6: Afolu Livestock Grass Asses Existing 0 | L6: WTRAFO | M6: AFOLIVASSDEM | O6: 1 | P6: {=IFERROR(1/INDEX('Calc - water'!G:G, MATCH(1, (Z6='Calc - water'!B:B)*(AA6='Calc - water'!C:C), 0)),0)} -> 60.882801 | Q6: 1 | R6: 10 | T6: =IFERROR(IF(VLOOKUP($Z6,'Calculations - livestock '!$A$5:$M$17,4,FALSE)= 0, "",1000*VLOOKUP($Z6,'Calculations - livestock '!$A$5:$M$17,4,FALSE)), " ") | U6: =IF($S7=0,IFERROR(IF(VLOOKUP($Z6,'Calculations - livestock '!$A$5:$M$17,6,FALSE)= 0, "",1000*VLOOKUP($Z6,'Calculations - livestock '!$A$5:$M$17,6,FALSE)), " "),"") | V6: =IF($S7=0,IFERROR(IF(VLOOKUP($Z6,'Calculations - livestock '!$A$5:$M$17,9,FALSE)= 0, "",1000*VLOOKUP($Z6,'Calculations - livestock '!$A$5:$M$17,9,FALSE)), " "),"") | W6: =IFERROR(IF(VLOOKUP($Z6,'Calculations - livestock '!$A:$B,2,FALSE)/1000*$AB6=0,"",VLOOKUP($Z6,'Calculations - livestock '!$A:$B,2,FALSE)/1000*$AB6)," ") | X6: =IF(AA6<>"",SUMIFS(DefaultAFOLU!$G:$G,DefaultAFOLU!$D:$D,Livestock!AA6,DefaultAFOLU!$B:$B,Livestock!X$4,DefaultAFOLU!$C:$C,Livestock!Z6),"") -> 1e-05 | Z6: Asses | AA6: Grass | AB6: =INDEX('InputCritical-yearless'!$C$12:$N$13, MATCH(AA6, 'InputCritical-yearless'!$B$12:$B$13, 0), MATCH(LEFT(Z6, 3), 'InputCritical-yearless'!$C$11:$N$11, 0)) -> 0.5
B7: =IF(SUM(W7:W7)=0,"\I:","DMD") -> \I: | C7: AFOLIVGRSBUFWTRE0 | D7: Afolu Livestock Grass Buffalo Existing 0 | E7: kHeadsA | F7: kHeads | G7: Annual | H7: NO | J7: =IF(SUM(W7:W7)=0,"\I:",C7) -> \I: | K7: Afolu Livestock Grass Buffalo Existing 0 | L7: WTRAFO | M7: AFOLIVBUFDEM | O7: 1 | P7: {=IFERROR(1/INDEX('Calc - water'!G:G, MATCH(1, (Z7='Calc - water'!B:B)*(AA7='Calc - water'!C:C), 0)),0)} -> 39.138943 | Q7: 1 | R7: 10 | T7: =IFERROR(IF(VLOOKUP($Z7,'Calculations - livestock '!$A$5:$M$17,4,FALSE)= 0, "",1000*VLOOKUP($Z7,'Calculations - livestock '!$A$5:$M$17,4,FALSE)), " ") | U7: =IF($S8=0,IFERROR(IF(VLOOKUP($Z7,'Calculations - livestock '!$A$5:$M$17,6,FALSE)= 0, "",1000*VLOOKUP($Z7,'Calculations - livestock '!$A$5:$M$17,6,FALSE)), " "),"") | V7: =IF($S8=0,IFERROR(IF(VLOOKUP($Z7,'Calculations - livestock '!$A$5:$M$17,9,FALSE)= 0, "",1000*VLOOKUP($Z7,'Calculations - livestock '!$A$5:$M$17,9,FALSE)), " "),"") | W7: =IFERROR(IF(VLOOKUP($Z7,'Calculations - livestock '!$A:$B,2,FALSE)/1000*$AB7=0,"",VLOOKUP($Z7,'Calculations - livestock '!$A:$B,2,FALSE)/1000*$AB7)," ") | X7: =IF(AA7<>"",SUMIFS(DefaultAFOLU!$G:$G,DefaultAFOLU!$D:$D,Livestock!AA7,DefaultAFOLU!$B:$B,Livestock!X$4,DefaultAFOLU!$C:$C,Livestock!Z7),"") -> 1e-05 | Z7: Buffalo | AA7: Grass | AB7: =INDEX('InputCritical-yearless'!$C$12:$N$13, MATCH(AA7, 'InputCritical-yearless'!$B$12:$B$13, 0), MATCH(LEFT(Z7, 3), 'InputCritical-yearless'!$C$11:$N$11, 0)) -> 0.5
B8: =IF(SUM(W8:W8)=0,"\I:","DMD") -> \I: | C8: AFOLIVGRSCAMWTRE0 | D8: Afolu Livestock Grass Camels Existing 0 | E8: kHeadsA | F8: kHeads | G8: Annual | H8: NO | J8: =IF(SUM(W8:W8)=0,"\I:",C8) -> \I: | K8: Afolu Livestock Grass Camels Existing 0 | L8: WTRAFO | M8: AFOLIVCAMDEM | O8: 1 | P8: {=IFERROR(1/INDEX('Calc - water'!G:G, MATCH(1, (Z8='Calc - water'!B:B)*(AA8='Calc - water'!C:C), 0)),0)} -> 117.41223 | Q8: 1 | R8: 10 | T8: =IFERROR(IF(VLOOKUP($Z8,'Calculations - livestock '!$A$5:$M$17,4,FALSE)= 0, "",1000*VLOOKUP($Z8,'Calculations - livestock '!$A$5:$M$17,4,FALSE)), " ") | U8: =IF($S9=0,IFERROR(IF(VLOOKUP($Z8,'Calculations - livestock '!$A$5:$M$17,6,FALSE)= 0, "",1000*VLOOKUP($Z8,'Calculations - livestock '!$A$5:$M$17,6,FALSE)), " "),"") | V8: =IF($S9=0,IFERROR(IF(VLOOKUP($Z8,'Calculations - livestock '!$A$5:$M$17,9,FALSE)= 0, "",1000*VLOOKUP($Z8,'Calculations - livestock '!$A$5:$M$17,9,FALSE)), " "),"") | W8: =IFERROR(IF(VLOOKUP($Z8,'Calculations - livestock '!$A:$B,2,FALSE)/1000*$AB8=0,"",VLOOKUP($Z8,'Calculations - livestock '!$A:$B,2,FALSE)/1000*$AB8)," ") | X8: =IF(AA8<>"",SUMIFS(DefaultAFOLU!$G:$G,DefaultAFOLU!$D:$D,Livestock!AA8,DefaultAFOLU!$B:$B,Livestock!X$4,DefaultAFOLU!$C:$C,Livestock!Z8),"") -> 1e-05 | Z8: Camels | AA8: Grass | AB8: =INDEX('InputCritical-yearless'!$C$12:$N$13, MATCH(AA8, 'InputCritical-yearless'!$B$12:$B$13, 0), MATCH(LEFT(Z8, 3), 'InputCritical-yearless'!$C$11:$N$11, 0)) -> 0.5
B9: =IF(SUM(W9:W9)=0,"\I:","DMD") -> DMD | C9: AFOLIVGRSCADWTRE0 | D9: Afolu Livestock Grass Cattle, dairy Existing 0 | E9: kHeadsA | F9: kHeads | G9: Annual | H9: NO | J9: =IF(SUM(W9:W9)=0,"\I:",C9) -> AFOLIVGRSCADWTRE0 | K9: Afolu Livestock Grass Cattle, dairy Existing 0 | L9: WTRAFO | M9: AFOLIVCADDEM | O9: 1 | P9: {=IFERROR(1/INDEX('Calc - water'!G:G, MATCH(1, (Z9='Calc - water'!B:B)*(AA9='Calc - water'!C:C), 0)),0)} -> 58.725869 | Q9: 1 | R9: 10 | T9: =IFERROR(IF(VLOOKUP($Z9,'Calculations - livestock '!$A$5:$M$17,4,FALSE)= 0, "",1000*VLOOKUP($Z9,'Calculations - livestock '!$A$5:$M$17,4,FALSE)), " ") -> 0.11700003 | U9: =IF($S10=0,IFERROR(IF(VLOOKUP($Z9,'Calculations - livestock '!$A$5:$M$17,6,FALSE)= 0, "",1000*VLOOKUP($Z9,'Calculations - livestock '!$A$5:$M$17,6,FALSE)), " "),"") -> 0.021000101 | V9: =IF($S10=0,IFERROR(IF(VLOOKUP($Z9,'Calculations - livestock '!$A$5:$M$17,9,FALSE)= 0, "",1000*VLOOKUP($Z9,'Calculations - livestock '!$A$5:$M$17,9,FALSE)), " "),"") -> 0.0010293278 | W9: =IFERROR(IF(VLOOKUP($Z9,'Calculations - livestock '!$A:$B,2,FALSE)/1000*$AB9=0,"",VLOOKUP($Z9,'Calculations - livestock '!$A:$B,2,FALSE)/1000*$AB9)," ") -> 148.835 | X9: =IF(AA9<>"",SUMIFS(DefaultAFOLU!$G:$G,DefaultAFOLU!$D:$D,Livestock!AA9,DefaultAFOLU!$B:$B,Livestock!X$4,DefaultAFOLU!$C:$C,Livestock!Z9),"") -> 1e-05 | Z9: Cattle, dairy | AA9: Grass | AB9: =INDEX('InputCritical-yearless'!$C$12:$N$13, MATCH(AA9, 'InputCritical-yearless'!$B$12:$B$13, 0), MATCH(LEFT(Z9, 3), 'InputCritical-yearless'!$C$11:$N$11, 0)) -> 0.5
B10: =IF(SUM(W10:W10)=0,"\I:","DMD") -> DMD | C10: AFOLIVGRSCANWTRE0 | D10: Afolu Livestock Grass Cattle, non-dairy Existing 0 | E10: kHeadsA | F10: kHeads | G10: Annual | H10: NO | J10: =IF(SUM(W10:W10)=0,"\I:",C10) -> AFOLIVGRSCANWTRE0 | K10: Afolu Livestock Grass Cattle, non-dairy Existing 0 | L10: WTRAFO | M10: AFOLIVCANDEM | O10: 1 | P10: {=IFERROR(1/INDEX('Calc - water'!G:G, MATCH(1, (Z10='Calc - water'!B:B)*(AA10='Calc - water'!C:C), 0)),0)} -> 93.96139 | Q10: 1 | R10: 10 | T10: =IFERROR(IF(VLOOKUP($Z10,'Calculations - livestock '!$A$5:$M$17,4,FALSE)= 0, "",1000*VLOOKUP($Z10,'Calculations - livestock '!$A$5:$M$17,4,FALSE)), " ") -> 0.057000037 | U10: =IF($S11=0,IFERROR(IF(VLOOKUP($Z10,'Calculations - livestock '!$A$5:$M$17,6,FALSE)= 0, "",1000*VLOOKUP($Z10,'Calculations - livestock '!$A$5:$M$17,6,FALSE)), " "),"") -> 0.0060000183 | V10: =IF($S11=0,IFERROR(IF(VLOOKUP($Z10,'Calculations - livestock '!$A$5:$M$17,9,FALSE)= 0, "",1000*VLOOKUP($Z10,'Calculations - livestock '!$A$5:$M$17,9,FALSE)), " "),"") -> 0.00040269746 | W10: =IFERROR(IF(VLOOKUP($Z10,'Calculations - livestock '!$A:$B,2,FALSE)/1000*$AB10=0,"",VLOOKUP($Z10,'Calculations - livestock '!$A:$B,2,FALSE)/1000*$AB10)," ") -> 546.44 | X10: =IF(AA10<>"",SUMIFS(DefaultAFOLU!$G:$G,DefaultAFOLU!$D:$D,Livestock!AA10,DefaultAFOLU!$B:$B,Livestock!X$4,DefaultAFOLU!$C:$C,Livestock!Z10),"") -> 1e-05 | Z10: Cattle, non-dairy | AA10: Grass | AB10: =INDEX('InputCritical-yearless'!$C$12:$N$13, MATCH(AA10, 'InputCritical-yearless'!$B$12:$B$13, 0), MATCH(LEFT(Z10, 3), 'InputCritical-yearless'!$C$11:$N$11, 0)) -> 0.5
B11: =IF(SUM(W11:W11)=0,"\I:","DMD") -> DMD | C11: AFOLIVGRSGOAWTRE0 | D11: Afolu Livestock Grass Goats Existing 0 | E11: kHeadsA | F11: kHeads | G11: Annual | H11: NO | J11: =IF(SUM(W11:W11)=0,"\I:",C11) -> AFOLIVGRSGOAWTRE0 | K11: Afolu Livestock Grass Goats Existing 0 | L11: WTRAFO | M11: AFOLIVGOADEM | O11: 1 | P11: {=IFERROR(1/INDEX('Calc - water'!G:G, MATCH(1, (Z11='Calc - water'!B:B)*(AA11='Calc - water'!C:C), 0)),0)} -> 469.80695 | Q11: 1 | R11: 10 | T11: =IFERROR(IF(VLOOKUP($Z11,'Calculations - livestock '!$A$5:$M$17,4,FALSE)= 0, "",1000*VLOOKUP($Z11,'Calculations - livestock '!$A$5:$M$17,4,FALSE)), " ") -> 0.005 | U11: =IF($S12=0,IFERROR(IF(VLOOKUP($Z11,'Calculations - livestock '!$A$5:$M$17,6,FALSE)= 0, "",1000*VLOOKUP($Z11,'Calculations - livestock '!$A$5:$M$17,6,FALSE)), " "),"") -> 0.00013333333 | V11: =IF($S12=0,IFERROR(IF(VLOOKUP($Z11,'Calculations - livestock '!$A$5:$M$17,9,FALSE)= 0, "",1000*VLOOKUP($Z11,'Calculations - livestock '!$A$5:$M$17,9,FALSE)), " "),"") -> 8.3333333e-06 | W11: =IFERROR(IF(VLOOKUP($Z11,'Calculations - livestock '!$A:$B,2,FALSE)/1000*$AB11=0,"",VLOOKUP($Z11,'Calculations - livestock '!$A:$B,2,FALSE)/1000*$AB11)," ") -> 6 | X11: =IF(AA11<>"",SUMIFS(DefaultAFOLU!$G:$G,DefaultAFOLU!$D:$D,Livestock!AA11,DefaultAFOLU!$B:$B,Livestock!X$4,DefaultAFOLU!$C:$C,Livestock!Z11),"") -> 1e-05 | Z11: Goats | AA11: Grass | AB11: =INDEX('InputCritical-yearless'!$C$12:$N$13, MATCH(AA11, 'InputCritical-yearless'!$B$12:$B$13, 0), MATCH(LEFT(Z11, 3), 'InputCritical-yearless'!$C$11:$N$11, 0)) -> 0.5
B12: =IF(SUM(W12:W12)=0,"\I:","DMD") -> DMD | C12: AFOLIVGRSHORWTRE0 | D12: Afolu Livestock Grass Horses Existing 0 | E12: kHeadsA | F12: kHeads | G12: Annual | H12: NO | J12: =IF(SUM(W12:W12)=0,"\I:",C12) -> AFOLIVGRSHORWTRE0 | K12: Afolu Livestock Grass Horses Existing 0 | L12: WTRAFO | M12: AFOLIVHORDEM | O12: 1 | P12: {=IFERROR(1/INDEX('Calc - water'!G:G, MATCH(1, (Z12='Calc - water'!B:B)*(AA12='Calc - water'!C:C), 0)),0)} -> 104.40154 | Q12: 1 | R12: 10 | T12: =IFERROR(IF(VLOOKUP($Z12,'Calculations - livestock '!$A$5:$M$17,4,FALSE)= 0, "",1000*VLOOKUP($Z12,'Calculations - livestock '!$A$5:$M$17,4,FALSE)), " ") -> 0.017999925 | U12: =IF($S13=0,IFERROR(IF(VLOOKUP($Z12,'Calculations - livestock '!$A$5:$M$17,6,FALSE)= 0, "",1000*VLOOKUP($Z12,'Calculations - livestock '!$A$5:$M$17,6,FALSE)), " "),"") -> 0.001560156 | V12: =IF($S13=0,IFERROR(IF(VLOOKUP($Z12,'Calculations - livestock '!$A$5:$M$17,9,FALSE)= 0, "",1000*VLOOKUP($Z12,'Calculations - livestock '!$A$5:$M$17,9,FALSE)), " "),"") -> 1.1251125e-05 | W12: =IFERROR(IF(VLOOKUP($Z12,'Calculations - livestock '!$A:$B,2,FALSE)/1000*$AB12=0,"",VLOOKUP($Z12,'Calculations - livestock '!$A:$B,2,FALSE)/1000*$AB12)," ") -> 53.328 | X12: =IF(AA12<>"",SUMIFS(DefaultAFOLU!$G:$G,DefaultAFOLU!$D:$D,Livestock!AA12,DefaultAFOLU!$B:$B,Livestock!X$4,DefaultAFOLU!$C:$C,Livestock!Z12),"") -> 1e-05 | Z12: Horses | AA12: Grass | AB12: =INDEX('InputCritical-yearless'!$C$12:$N$13, MATCH(AA12, 'InputCritical-yearless'!$B$12:$B$13, 0), MATCH(LEFT(Z12, 3), 'InputCritical-yearless'!$C$11:$N$11, 0)) -> 0.5
B13: =IF(SUM(W13:W13)=0,"\I:","DMD") -> \I: | C13: AFOLIVGRSLLAWTRE0 | D13: Afolu Livestock Grass Llamas Existing 0 | E13: kHeadsA | F13: kHeads | G13: Annual | H13: NO | J13: =IF(SUM(W13:W13)=0,"\I:",C13) -> \I: | K13: Afolu Livestock Grass Llamas Existing 0 | L13: WTRAFO | M13: AFOLIVLLADEM | O13: 1 | P13: {=IFERROR(1/INDEX('Calc - water'!G:G, MATCH(1, (Z13='Calc - water'!B:B)*(AA13='Calc - water'!C:C), 0)),0)} -> 684.93151 | Q13: 1 | R13: 10 | T13: =IFERROR(IF(VLOOKUP($Z13,'Calculations - livestock '!$A$5:$M$17,4,FALSE)= 0, "",1000*VLOOKUP($Z13,'Calculations - livestock '!$A$5:$M$17,4,FALSE)), " ") | U13: =IF($S14=0,IFERROR(IF(VLOOKUP($Z13,'Calculations - livestock '!$A$5:$M$17,6,FALSE)= 0, "",1000*VLOOKUP($Z13,'Calculations - livestock '!$A$5:$M$17,6,FALSE)), " "),"") | V13: =IF($S14=0,IFERROR(IF(VLOOKUP($Z13,'Calculations - livestock '!$A$5:$M$17,9,FALSE)= 0, "",1000*VLOOKUP($Z13,'Calculations - livestock '!$A$5:$M$17,9,FALSE)), " "),"") | W13: =IFERROR(IF(VLOOKUP($Z13,'Calculations - livestock '!$A:$B,2,FALSE)/1000*$AB13=0,"",VLOOKUP($Z13,'Calculations - livestock '!$A:$B,2,FALSE)/1000*$AB13)," ") | X13: =IF(AA13<>"",SUMIFS(DefaultAFOLU!$G:$G,DefaultAFOLU!$D:$D,Livestock!AA13,DefaultAFOLU!$B:$B,Livestock!X$4,DefaultAFOLU!$C:$C,Livestock!Z13),"") -> 1e-05 | Z13: Llamas | AA13: Grass | AB13: =INDEX('InputCritical-yearless'!$C$12:$N$13, MATCH(AA13, 'InputCritical-yearless'!$B$12:$B$13, 0), MATCH(LEFT(Z13, 3), 'InputCritical-yearless'!$C$11:$N$11, 0)) -> 0.5
B14: =IF(SUM(W14:W14)=0,"\I:","DMD") -> \I: | C14: AFOLIVGRSMULWTRE0 | D14: Afolu Livestock Grass Mules and hinnies Existing 0 | E14: kHeadsA | F14: kHeads | G14: Annual | H14: NO | J14: =IF(SUM(W14:W14)=0,"\I:",C14) -> \I: | K14: Afolu Livestock Grass Mules and hinnies Existing 0 | L14: WTRAFO | M14: AFOLIVMULDEM | O14: 1 | P14: {=IFERROR(1/INDEX('Calc - water'!G:G, MATCH(1, (Z14='Calc - water'!B:B)*(AA14='Calc - water'!C:C), 0)),0)} -> 60.882801 | Q14: 1 | R14: 10 | T14: =IFERROR(IF(VLOOKUP($Z14,'Calculations - livestock '!$A$5:$M$17,4,FALSE)= 0, "",1000*VLOOKUP($Z14,'Calculations - livestock '!$A$5:$M$17,4,FALSE)), " ") | U14: =IF($S15=0,IFERROR(IF(VLOOKUP($Z14,'Calculations - livestock '!$A$5:$M$17,6,FALSE)= 0, "",1000*VLOOKUP($Z14,'Calculations - livestock '!$A$5:$M$17,6,FALSE)), " "),"") | V14: =IF($S15=0,IFERROR(IF(VLOOKUP($Z14,'Calculations - livestock '!$A$5:$M$17,9,FALSE)= 0, "",1000*VLOOKUP($Z14,'Calculations - livestock '!$A$5:$M$17,9,FALSE)), " "),"") | W14: =IFERROR(IF(VLOOKUP($Z14,'Calculations - livestock '!$A:$B,2,FALSE)/1000*$AB14=0,"",VLOOKUP($Z14,'Calculations - livestock '!$A:$B,2,FALSE)/1000*$AB14)," ") | X14: =IF(AA14<>"",SUMIFS(DefaultAFOLU!$G:$G,DefaultAFOLU!$D:$D,Livestock!AA14,DefaultAFOLU!$B:$B,Livestock!X$4,DefaultAFOLU!$C:$C,Livestock!Z14),"") -> 1e-05 | Z14: Mules and hinnies | AA14: Grass | AB14: =INDEX('InputCritical-yearless'!$C$12:$N$13, MATCH(AA14, 'InputCritical-yearless'!$B$12:$B$13, 0), MATCH(LEFT(Z14, 3), 'InputCritical-yearless'!$C$11:$N$11, 0)) -> 0.5
B15: =IF(SUM(W15:W15)=0,"\I:","DMD") -> DMD | C15: AFOLIVGRSSHPWTRE0 | D15: Afolu Livestock Grass Sheep Existing 0 | E15: kHeadsA | F15: kHeads | G15: Annual | H15: NO | J15: =IF(SUM(W15:W15)=0,"\I:",C15) -> AFOLIVGRSSHPWTRE0 | K15: Afolu Livestock Grass Sheep Existing 0 | L15: WTRAFO | M15: AFOLIVSHPDEM | O15: 1 | P15: {=IFERROR(1/INDEX('Calc - water'!G:G, MATCH(1, (Z15='Calc - water'!B:B)*(AA15='Calc - water'!C:C), 0)),0)} -> 939.6139 | Q15: 1 | R15: 10 | T15: =IFERROR(IF(VLOOKUP($Z15,'Calculations - livestock '!$A$5:$M$17,4,FALSE)= 0, "",1000*VLOOKUP($Z15,'Calculations - livestock '!$A$5:$M$17,4,FALSE)), " ") -> 0.0079999413 | U15: =IF($S16=0,IFERROR(IF(VLOOKUP($Z15,'Calculations - livestock '!$A$5:$M$17,6,FALSE)= 0, "",1000*VLOOKUP($Z15,'Calculations - livestock '!$A$5:$M$17,6,FALSE)), " "),"") -> 0.00019011853 | V15: =IF($S16=0,IFERROR(IF(VLOOKUP($Z15,'Calculations - livestock '!$A$5:$M$17,9,FALSE)= 0, "",1000*VLOOKUP($Z15,'Calculations - livestock '!$A$5:$M$17,9,FALSE)), " "),"") -> 1.9070532e-05 | W15: =IFERROR(IF(VLOOKUP($Z15,'Calculations - livestock '!$A:$B,2,FALSE)/1000*$AB15=0,"",VLOOKUP($Z15,'Calculations - livestock '!$A:$B,2,FALSE)/1000*$AB15)," ") -> 170.42 | X15: =IF(AA15<>"",SUMIFS(DefaultAFOLU!$G:$G,DefaultAFOLU!$D:$D,Livestock!AA15,DefaultAFOLU!$B:$B,Livestock!X$4,DefaultAFOLU!$C:$C,Livestock!Z15),"") -> 1e-05 | Z15: Sheep | AA15: Grass | AB15: =INDEX('InputCritical-yearless'!$C$12:$N$13, MATCH(AA15, 'InputCritical-yearless'!$B$12:$B$13, 0), MATCH(LEFT(Z15, 3), 'InputCritical-yearless'!$C$11:$N$11, 0)) -> 0.5
B16: =IF(SUM(W16:W16)=0,"\I:","DMD") -> DMD | C16: AFOLIVGRSSWBWTRE0 | D16: Afolu Livestock Grass Swine, breeding Existing 0 | E16: kHeadsA | F16: kHeads | G16: Annual | H16: NO | J16: =IF(SUM(W16:W16)=0,"\I:",C16) -> AFOLIVGRSSWBWTRE0 | K16: Afolu Livestock Grass Swine, breeding Existing 0 | L16: WTRAFO | M16: AFOLIVSWBDEM | O16: 1 | P16: {=IFERROR(1/INDEX('Calc - water'!G:G, MATCH(1, (Z16='Calc - water'!B:B)*(AA16='Calc - water'!C:C), 0)),0)} -> 195.7529 | Q16: 1 | R16: 10 | T16: =IFERROR(IF(VLOOKUP($Z16,'Calculations - livestock '!$A$5:$M$17,4,FALSE)= 0, "",1000*VLOOKUP($Z16,'Calculations - livestock '!$A$5:$M$17,4,FALSE)), " ") -> 0.001499714 | U16: =IF($S17=0,IFERROR(IF(VLOOKUP($Z16,'Calculations - livestock '!$A$5:$M$17,6,FALSE)= 0, "",1000*VLOOKUP($Z16,'Calculations - livestock '!$A$5:$M$17,6,FALSE)), " "),"") -> 0.0089996964 | V16: =IF($S17=0,IFERROR(IF(VLOOKUP($Z16,'Calculations - livestock '!$A$5:$M$17,9,FALSE)= 0, "",1000*VLOOKUP($Z16,'Calculations - livestock '!$A$5:$M$17,9,FALSE)), " "),"") -> 0.00024147938 | W16: =IFERROR(IF(VLOOKUP($Z16,'Calculations - livestock '!$A:$B,2,FALSE)/1000*$AB16=0,"",VLOOKUP($Z16,'Calculations - livestock '!$A:$B,2,FALSE)/1000*$AB16)," ") -> 70.8135 | X16: =IF(AA16<>"",SUMIFS(DefaultAFOLU!$G:$G,DefaultAFOLU!$D:$D,Livestock!AA16,DefaultAFOLU!$B:$B,Livestock!X$4,DefaultAFOLU!$C:$C,Livestock!Z16),"") -> 1e-05 | Z16: Swine, breeding | AA16: Grass | AB16: =INDEX('InputCritical-yearless'!$C$12:$N$13, MATCH(AA16, 'InputCritical-yearless'!$B$12:$B$13, 0), MATCH(LEFT(Z16, 3), 'InputCritical-yearless'!$C$11:$N$11, 0)) -> 0.5
B17: =IF(SUM(W17:W17)=0,"\I:","DMD") -> DMD | C17: AFOLIVGRSSWMWTRE0 | D17: Afolu Livestock Grass Swine, market Existing 0 | E17: kHeadsA | F17: kHeads | G17: Annual | H17: NO | J17: =IF(SUM(W17:W17)=0,"\I:",C17) -> AFOLIVGRSSWMWTRE0 | K17: Afolu Livestock Grass Swine, market Existing 0 | L17: WTRAFO | M17: AFOLIVSWMDEM | O17: 1 | P17: {=IFERROR(1/INDEX('Calc - water'!G:G, MATCH(1, (Z17='Calc - water'!B:B)*(AA17='Calc - water'!C:C), 0)),0)} -> 522.00772 | Q17: 1 | R17: 10 | T17: =IFERROR(IF(VLOOKUP($Z17,'Calculations - livestock '!$A$5:$M$17,4,FALSE)= 0, "",1000*VLOOKUP($Z17,'Calculations - livestock '!$A$5:$M$17,4,FALSE)), " ") -> 0.0015000279 | U17: =IF($S18=0,IFERROR(IF(VLOOKUP($Z17,'Calculations - livestock '!$A$5:$M$17,6,FALSE)= 0, "",1000*VLOOKUP($Z17,'Calculations - livestock '!$A$5:$M$17,6,FALSE)), " "),"") -> 0.006000033 | V17: =IF($S18=0,IFERROR(IF(VLOOKUP($Z17,'Calculations - livestock '!$A$5:$M$17,9,FALSE)= 0, "",1000*VLOOKUP($Z17,'Calculations - livestock '!$A$5:$M$17,9,FALSE)), " "),"") -> 7.4138406e-05 | W17: =IFERROR(IF(VLOOKUP($Z17,'Calculations - livestock '!$A:$B,2,FALSE)/1000*$AB17=0,"",VLOOKUP($Z17,'Calculations - livestock '!$A:$B,2,FALSE)/1000*$AB17)," ") -> 637.3215 | X17: =IF(AA17<>"",SUMIFS(DefaultAFOLU!$G:$G,DefaultAFOLU!$D:$D,Livestock!AA17,DefaultAFOLU!$B:$B,Livestock!X$4,DefaultAFOLU!$C:$C,Livestock!Z17),"") -> 1e-05 | Z17: Swine, market | AA17: Grass | AB17: =INDEX('InputCritical-yearless'!$C$12:$N$13, MATCH(AA17, 'InputCritical-yearless'!$B$12:$B$13, 0), MATCH(LEFT(Z17, 3), 'InputCritical-yearless'!$C$11:$N$11, 0)) -> 0.5
... B22: =IF(SUM(W22:W22)=0,"\I:","DMD") -> DMD | C22: AFOLIVFRMCADWTRE0 | D22: Afolu Livestock Farm Cattle, dairy Existing 0 | E22: kHeadsA | F22: kHeads | G22: Annual | H22: NO | J22: =IF(SUM(W22:W22)=0,"\I:",C22) -> AFOLIVFRMCADWTRE0 | K22: Afolu Livestock Farm Cattle, dairy Existing 0 | L22: WTRAFO | M22: AFOLIVCADDEM | O22: 1 | P22: {=IFERROR(1/INDEX('Calc - water'!G:G, MATCH(1, (Z22='Calc - water'!B:B)*(AA22='Calc - water'!C:C), 0)),0)} -> 39.150579 | Q22: 1 | R22: 10 | T22: =IFERROR(IF(VLOOKUP($Z22,'Calculations - livestock '!$A$5:$M$17,4,FALSE)= 0, "",1000*VLOOKUP($Z22,'Calculations - livestock '!$A$5:$M$17,4,FALSE)), " ") -> 0.11700003 | U22: =IF($S23=0,IFERROR(IF(VLOOKUP($Z22,'Calculations - livestock '!$A$5:$M$17,6,FALSE)= 0, "",1000*VLOOKUP($Z22,'Calculations - livestock '!$A$5:$M$17,6,FALSE)), " "),"") | V22: =IF($S23=0,IFERROR(IF(VLOOKUP($Z22,'Calculations - livestock '!$A$5:$M$17,9,FALSE)= 0, "",1000*VLOOKUP($Z22,'Calculations - livestock '!$A$5:$M$17,9,FALSE)), " "),"") | W22: =IFERROR(IF(VLOOKUP($Z22,'Calculations - livestock '!$A:$B,2,FALSE)/1000*$AB22=0,"",VLOOKUP($Z22,'Calculations - livestock '!$A:$B,2,FALSE)/1000*$AB22)," ") -> 148.835 | X22: =IF(AA22<>"",SUMIFS(DefaultAFOLU!$G:$G,DefaultAFOLU!$D:$D,Livestock!AA22,DefaultAFOLU!$B:$B,Livestock!X$4,DefaultAFOLU!$C:$C,Livestock!Z22),"") -> 1e-05 | Z22: Cattle, dairy | AA22: Farm | AB22: =INDEX('InputCritical-yearless'!$C$12:$N$13, MATCH(AA22, 'InputCritical-yearless'!$B$12:$B$13, 0), MATCH(LEFT(Z22, 3), 'InputCritical-yearless'!$C$11:$N$11, 0)) -> 0.5
B23: =IF(SUM(W23:W23)=0,"\I:","DMD") -> \I: | N23: CADMNR | S23: =VLOOKUP(Z22,'Calculations - livestock '!$A$25:$E$37,3,FALSE) -> 0.189125 | T23: =IFERROR(IF(VLOOKUP($Z23,'Calculations - livestock '!$A$5:$M$17,4,FALSE)= 0, "",1000*VLOOKUP($Z23,'Calculations - livestock '!$A$5:$M$17,4,FALSE)), " ") | U23: =IF($S24=0,IFERROR(IF(VLOOKUP($Z23,'Calculations - livestock '!$A$5:$M$17,6,FALSE)= 0, "",1000*VLOOKUP($Z23,'Calculations - livestock '!$A$5:$M$17,6,FALSE)), " "),"") | V23: =IF($S24=0,IFERROR(IF(VLOOKUP($Z23,'Calculations - livestock '!$A$5:$M$17,9,FALSE)= 0, "",1000*VLOOKUP($Z23,'Calculations - livestock '!$A$5:$M$17,9,FALSE)), " "),"") | X23: =IF(AA23<>"",SUMIFS(DefaultAFOLU!$G:$G,DefaultAFOLU!$D:$D,Livestock!AA23,DefaultAFOLU!$B:$B,Livestock!X$4,DefaultAFOLU!$C:$C,Livestock!Z23),"") | AC23: =S23*W22 -> 28.148419
B24: =IF(SUM(W24:W24)=0,"\I:","DMD") -> DMD | C24: AFOLIVFRMCANWTRE0 | D24: Afolu Livestock Farm Cattle, non-dairy Existing 0 | E24: kHeadsA | F24: kHeads | G24: Annual | H24: NO | J24: =IF(SUM(W24:W24)=0,"\I:",C24) -> AFOLIVFRMCANWTRE0 | K24: Afolu Livestock Farm Cattle, non-dairy Existing 0 | L24: WTRAFO | M24: AFOLIVCANDEM | O24: 1 | P24: {=IFERROR(1/INDEX('Calc - water'!G:G, MATCH(1, (Z24='Calc - water'!B:B)*(AA24='Calc - water'!C:C), 0)),0)} -> 62.640927 | Q24: 1 | R24: 10 | T24: =IFERROR(IF(VLOOKUP($Z24,'Calculations - livestock '!$A$5:$M$17,4,FALSE)= 0, "",1000*VLOOKUP($Z24,'Calculations - livestock '!$A$5:$M$17,4,FALSE)), " ") -> 0.057000037 | U24: =IF($S25=0,IFERROR(IF(VLOOKUP($Z24,'Calculations - livestock '!$A$5:$M$17,6,FALSE)= 0, "",1000*VLOOKUP($Z24,'Calculations - livestock '!$A$5:$M$17,6,FALSE)), " "),"") | V24: =IF($S25=0,IFERROR(IF(VLOOKUP($Z24,'Calculations - livestock '!$A$5:$M$17,9,FALSE)= 0, "",1000*VLOOKUP($Z24,'Calculations - livestock '!$A$5:$M$17,9,FALSE)), " "),"") | W24: =IFERROR(IF(VLOOKUP($Z24,'Calculations - livestock '!$A:$B,2,FALSE)/1000*$AB24=0,"",VLOOKUP($Z24,'Calculations - livestock '!$A:$B,2,FALSE)/1000*$AB24)," ") -> 546.44 | X24: =IF(AA24<>"",SUMIFS(DefaultAFOLU!$G:$G,DefaultAFOLU!$D:$D,Livestock!AA24,DefaultAFOLU!$B:$B,Livestock!X$4,DefaultAFOLU!$C:$C,Livestock!Z24),"") -> 1e-05 | Z24: Cattle, non-dairy | AA24: Farm | AB24: =INDEX('InputCritical-yearless'!$C$12:$N$13, MATCH(AA24, 'InputCritical-yearless'!$B$12:$B$13, 0), MATCH(LEFT(Z24, 3), 'InputCritical-yearless'!$C$11:$N$11, 0)) -> 0.5
B25: =IF(SUM(W25:W25)=0,"\I:","DMD") -> \I: | N25: CANMNR | S25: =VLOOKUP(Z24,'Calculations - livestock '!$A$25:$E$37,3,FALSE) -> 0.0775625 | T25: =IFERROR(IF(VLOOKUP($Z25,'Calculations - livestock '!$A$5:$M$17,4,FALSE)= 0, "",1000*VLOOKUP($Z25,'Calculations - livestock '!$A$5:$M$17,4,FALSE)), " ") | U25: =IF($S26=0,IFERROR(IF(VLOOKUP($Z25,'Calculations - livestock '!$A$5:$M$17,6,FALSE)= 0, "",1000*VLOOKUP($Z25,'Calculations - livestock '!$A$5:$M$17,6,FALSE)), " "),"") | V25: =IF($S26=0,IFERROR(IF(VLOOKUP($Z25,'Calculations - livestock '!$A$5:$M$17,9,FALSE)= 0, "",1000*VLOOKUP($Z25,'Calculations - livestock '!$A$5:$M$17,9,FALSE)), " "),"") | X25: =IF(AA25<>"",SUMIFS(DefaultAFOLU!$G:$G,DefaultAFOLU!$D:$D,Livestock!AA25,DefaultAFOLU!$B:$B,Livestock!X$4,DefaultAFOLU!$C:$C,Livestock!Z25),"") | AC25: =S25*W24 -> 42.383253
B26: =IF(SUM(W26:W26)=0,"\I:","DMD") -> DMD | C26: AFOLIVFRMGOAWTRE0 | D26: Afolu Livestock Farm Goats Existing 0 | E26: kHeadsA | F26: kHeads | G26: Annual | H26: NO | J26: =IF(SUM(W26:W26)=0,"\I:",C26) -> AFOLIVFRMGOAWTRE0 | K26: Afolu Livestock Farm Goats Existing 0 | L26: WTRAFO | M26: AFOLIVGOADEM | O26: 1 | P26: {=IFERROR(1/INDEX('Calc - water'!G:G, MATCH(1, (Z26='Calc - water'!B:B)*(AA26='Calc - water'!C:C), 0)),0)} -> 313.20463 | Q26: 1 | R26: 10 | T26: =IFERROR(IF(VLOOKUP($Z26,'Calculations - livestock '!$A$5:$M$17,4,FALSE)= 0, "",1000*VLOOKUP($Z26,'Calculations - livestock '!$A$5:$M$17,4,FALSE)), " ") -> 0.005 | U26: =IF($S27=0,IFERROR(IF(VLOOKUP($Z26,'Calculations - livestock '!$A$5:$M$17,6,FALSE)= 0, "",1000*VLOOKUP($Z26,'Calculations - livestock '!$A$5:$M$17,6,FALSE)), " "),"") -> 0.00013333333 | V26: =IF($S27=0,IFERROR(IF(VLOOKUP($Z26,'Calculations - livestock '!$A$5:$M$17,9,FALSE)= 0, "",1000*VLOOKUP($Z26,'Calculations - livestock '!$A$5:$M$17,9,FALSE)), " "),"") -> 8.3333333e-06 | W26: =IFERROR(IF(VLOOKUP($Z26,'Calculations - livestock '!$A:$B,2,FALSE)/1000*$AB26=0,"",VLOOKUP($Z26,'Calculations - livestock '!$A:$B,2,FALSE)/1000*$AB26)," ") -> 6 | X26: =IF(AA26<>"",SUMIFS(DefaultAFOLU!$G:$G,DefaultAFOLU!$D:$D,Livestock!AA26,DefaultAFOLU!$B:$B,Livestock!X$4,DefaultAFOLU!$C:$C,Livestock!Z26),"") -> 1e-05 | Z26: Goats | AA26: Farm | AB26: =INDEX('InputCritical-yearless'!$C$12:$N$13, MATCH(AA26, 'InputCritical-yearless'!$B$12:$B$13, 0), MATCH(LEFT(Z26, 3), 'InputCritical-yearless'!$C$11:$N$11, 0)) -> 0.5
B27: =IF(SUM(W27:W27)=0,"\I:","DMD") -> DMD | C27: AFOLIVFRMHORWTRE0 | D27: Afolu Livestock Farm Horses Existing 0 | E27: kHeadsA | F27: kHeads | G27: Annual | H27: NO | J27: =IF(SUM(W27:W27)=0,"\I:",C27) -> AFOLIVFRMHORWTRE0 | K27: Afolu Livestock Farm Horses Existing 0 | L27: WTRAFO | M27: AFOLIVHORDEM | O27: 1 | P27: {=IFERROR(1/INDEX('Calc - water'!G:G, MATCH(1, (Z27='Calc - water'!B:B)*(AA27='Calc - water'!C:C), 0)),0)} -> 69.60103 | Q27: 1 | R27: 10 | T27: =IFERROR(IF(VLOOKUP($Z27,'Calculations - livestock '!$A$5:$M$17,4,FALSE)= 0, "",1000*VLOOKUP($Z27,'Calculations - livestock '!$A$5:$M$17,4,FALSE)), " ") -> 0.017999925 | U27: =IF($S28=0,IFERROR(IF(VLOOKUP($Z27,'Calculations - livestock '!$A$5:$M$17,6,FALSE)= 0, "",1000*VLOOKUP($Z27,'Calculations - livestock '!$A$5:$M$17,6,FALSE)), " "),"") -> 0.001560156 | V27: =IF($S28=0,IFERROR(IF(VLOOKUP($Z27,'Calculations - livestock '!$A$5:$M$17,9,FALSE)= 0, "",1000*VLOOKUP($Z27,'Calculations - livestock '!$A$5:$M$17,9,FALSE)), " "),"") -> 1.1251125e-05 | W27: =IFERROR(IF(VLOOKUP($Z27,'Calculations - livestock '!$A:$B,2,FALSE)/1000*$AB27=0,"",VLOOKUP($Z27,'Calculations - livestock '!$A:$B,2,FALSE)/1000*$AB27)," ") -> 53.328 | X27: =IF(AA27<>"",SUMIFS(DefaultAFOLU!$G:$G,DefaultAFOLU!$D:$D,Livestock!AA27,DefaultAFOLU!$B:$B,Livestock!X$4,DefaultAFOLU!$C:$C,Livestock!Z27),"") -> 1e-05 | Z27: Horses | AA27: Farm | AB27: =INDEX('InputCritical-yearless'!$C$12:$N$13, MATCH(AA27, 'InputCritical-yearless'!$B$12:$B$13, 0), MATCH(LEFT(Z27, 3), 'InputCritical-yearless'!$C$11:$N$11, 0)) -> 0.5
B28: =IF(SUM(W28:W28)=0,"\I:","DMD") -> \I: | C28: AFOLIVFRMLLAWTRE0 | D28: Afolu Livestock Farm Llamas Existing 0 | E28: kHeadsA | F28: kHeads | G28: Annual | H28: NO | J28: =IF(SUM(W28:W28)=0,"\I:",C28) -> \I: | K28: Afolu Livestock Farm Llamas Existing 0 | L28: WTRAFO | M28: AFOLIVLLADEM | O28: 1 | P28: {=IFERROR(1/INDEX('Calc - water'!G:G, MATCH(1, (Z28='Calc - water'!B:B)*(AA28='Calc - water'!C:C), 0)),0)} -> 456.621 | Q28: 1 | R28: 10 | T28: =IFERROR(IF(VLOOKUP($Z28,'Calculations - livestock '!$A$5:$M$17,4,FALSE)= 0, "",1000*VLOOKUP($Z28,'Calculations - livestock '!$A$5:$M$17,4,FALSE)), " ") | U28: =IF($S29=0,IFERROR(IF(VLOOKUP($Z28,'Calculations - livestock '!$A$5:$M$17,6,FALSE)= 0, "",1000*VLOOKUP($Z28,'Calculations - livestock '!$A$5:$M$17,6,FALSE)), " "),"") | V28: =IF($S29=0,IFERROR(IF(VLOOKUP($Z28,'Calculations - livestock '!$A$5:$M$17,9,FALSE)= 0, "",1000*VLOOKUP($Z28,'Calculations - livestock '!$A$5:$M$17,9,FALSE)), " "),"") | W28: =IFERROR(IF(VLOOKUP($Z28,'Calculations - livestock '!$A:$B,2,FALSE)/1000*$AB28=0,"",VLOOKUP($Z28,'Calculations - livestock '!$A:$B,2,FALSE)/1000*$AB28)," ") | X28: =IF(AA28<>"",SUMIFS(DefaultAFOLU!$G:$G,DefaultAFOLU!$D:$D,Livestock!AA28,DefaultAFOLU!$B:$B,Livestock!X$4,DefaultAFOLU!$C:$C,Livestock!Z28),"") -> 1e-05 | Z28: Llamas | AA28: Farm | AB28: =INDEX('InputCritical-yearless'!$C$12:$N$13, MATCH(AA28, 'InputCritical-yearless'!$B$12:$B$13, 0), MATCH(LEFT(Z28, 3), 'InputCritical-yearless'!$C$11:$N$11, 0)) -> 0.5
B29: =IF(SUM(W29:W29)=0,"\I:","DMD") -> \I: | C29: AFOLIVFRMMULWTRE0 | D29: Afolu Livestock Farm Mules and hinnies Existing 0 | E29: kHeadsA | F29: kHeads | G29: Annual | H29: NO | J29: =IF(SUM(W29:W29)=0,"\I:",C29) -> \I: | K29: Afolu Livestock Farm Mules and hinnies Existing 0 | L29: WTRAFO | M29: AFOLIVMULDEM | O29: 1 | P29: {=IFERROR(1/INDEX('Calc - water'!G:G, MATCH(1, (Z29='Calc - water'!B:B)*(AA29='Calc - water'!C:C), 0)),0)} -> 40.588534 | Q29: 1 | R29: 10 | T29: =IFERROR(IF(VLOOKUP($Z29,'Calculations - livestock '!$A$5:$M$17,4,FALSE)= 0, "",1000*VLOOKUP($Z29,'Calculations - livestock '!$A$5:$M$17,4,FALSE)), " ") | U29: =IF($S30=0,IFERROR(IF(VLOOKUP($Z29,'Calculations - livestock '!$A$5:$M$17,6,FALSE)= 0, "",1000*VLOOKUP($Z29,'Calculations - livestock '!$A$5:$M$17,6,FALSE)), " "),"") | V29: =IF($S30=0,IFERROR(IF(VLOOKUP($Z29,'Calculations - livestock '!$A$5:$M$17,9,FALSE)= 0, "",1000*VLOOKUP($Z29,'Calculations - livestock '!$A$5:$M$17,9,FALSE)), " "),"") | W29: =IFERROR(IF(VLOOKUP($Z29,'Calculations - livestock '!$A:$B,2,FALSE)/1000*$AB29=0,"",VLOOKUP($Z29,'Calculations - livestock '!$A:$B,2,FALSE)/1000*$AB29)," ") | X29: =IF(AA29<>"",SUMIFS(DefaultAFOLU!$G:$G,DefaultAFOLU!$D:$D,Livestock!AA29,DefaultAFOLU!$B:$B,Livestock!X$4,DefaultAFOLU!$C:$C,Livestock!Z29),"") -> 1e-05 | Z29: Mules and hinnies | AA29: Farm | AB29: =INDEX('InputCritical-yearless'!$C$12:$N$13, MATCH(AA29, 'InputCritical-yearless'!$B$12:$B$13, 0), MATCH(LEFT(Z29, 3), 'InputCritical-yearless'!$C$11:$N$11, 0)) -> 0.5
B30: =IF(SUM(W30:W30)=0,"\I:","DMD") -> DMD | C30: AFOLIVFRMSHPWTRE0 | D30: Afolu Livestock Farm Sheep Existing 0 | E30: kHeadsA | F30: kHeads | G30: Annual | H30: NO | J30: =IF(SUM(W30:W30)=0,"\I:",C30) -> AFOLIVFRMSHPWTRE0 | K30: Afolu Livestock Farm Sheep Existing 0 | L30: WTRAFO | M30: AFOLIVSHPDEM | O30: 1 | P30: {=IFERROR(1/INDEX('Calc - water'!G:G, MATCH(1, (Z30='Calc - water'!B:B)*(AA30='Calc - water'!C:C), 0)),0)} -> 626.40927 | Q30: 1 | R30: 10 | T30: =IFERROR(IF(VLOOKUP($Z30,'Calculations - livestock '!$A$5:$M$17,4,FALSE)= 0, "",1000*VLOOKUP($Z30,'Calculations - livestock '!$A$5:$M$17,4,FALSE)), " ") -> 0.0079999413 | U30: =IF($S31=0,IFERROR(IF(VLOOKUP($Z30,'Calculations - livestock '!$A$5:$M$17,6,FALSE)= 0, "",1000*VLOOKUP($Z30,'Calculations - livestock '!$A$5:$M$17,6,FALSE)), " "),"") -> 0.00019011853 | V30: =IF($S31=0,IFERROR(IF(VLOOKUP($Z30,'Calculations - livestock '!$A$5:$M$17,9,FALSE)= 0, "",1000*VLOOKUP($Z30,'Calculations - livestock '!$A$5:$M$17,9,FALSE)), " "),"") -> 1.9070532e-05 | W30: =IFERROR(IF(VLOOKUP($Z30,'Calculations - livestock '!$A:$B,2,FALSE)/1000*$AB30=0,"",VLOOKUP($Z30,'Calculations - livestock '!$A:$B,2,FALSE)/1000*$AB30)," ") -> 170.42 | X30: =IF(AA30<>"",SUMIFS(DefaultAFOLU!$G:$G,DefaultAFOLU!$D:$D,Livestock!AA30,DefaultAFOLU!$B:$B,Livestock!X$4,DefaultAFOLU!$C:$C,Livestock!Z30),"") -> 1e-05 | Z30: Sheep | AA30: Farm | AB30: =INDEX('InputCritical-yearless'!$C$12:$N$13, MATCH(AA30, 'InputCritical-yearless'!$B$12:$B$13, 0), MATCH(LEFT(Z30, 3), 'InputCritical-yearless'!$C$11:$N$11, 0)) -> 0.5
B31: =IF(SUM(W31:W31)=0,"\I:","DMD") -> DMD | C31: AFOLIVFRMSWBWTRE0 | D31: Afolu Livestock Farm Swine, breeding Existing 0 | E31: kHeadsA | F31: kHeads | G31: Annual | H31: NO | J31: =IF(SUM(W31:W31)=0,"\I:",C31) -> AFOLIVFRMSWBWTRE0 | K31: Afolu Livestock Farm Swine, breeding Existing 0 | L31: WTRAFO | M31: AFOLIVSWBDEM | O31: 1 | P31: {=IFERROR(1/INDEX('Calc - water'!G:G, MATCH(1, (Z31='Calc - water'!B:B)*(AA31='Calc - water'!C:C), 0)),0)} -> 130.50193 | Q31: 1 | R31: 10 | T31: =IFERROR(IF(VLOOKUP($Z31,'Calculations - livestock '!$A$5:$M$17,4,FALSE)= 0, "",1000*VLOOKUP($Z31,'Calculations - livestock '!$A$5:$M$17,4,FALSE)), " ") -> 0.001499714 | U31: =IF($S32=0,IFERROR(IF(VLOOKUP($Z31,'Calculations - livestock '!$A$5:$M$17,6,FALSE)= 0, "",1000*VLOOKUP($Z31,'Calculations - livestock '!$A$5:$M$17,6,FALSE)), " "),"") | V31: =IF($S32=0,IFERROR(IF(VLOOKUP($Z31,'Calculations - livestock '!$A$5:$M$17,9,FALSE)= 0, "",1000*VLOOKUP($Z31,'Calculations - livestock '!$A$5:$M$17,9,FALSE)), " "),"") | W31: =IFERROR(IF(VLOOKUP($Z31,'Calculations - livestock '!$A:$B,2,FALSE)/1000*$AB31=0,"",VLOOKUP($Z31,'Calculations - livestock '!$A:$B,2,FALSE)/1000*$AB31)," ") -> 70.8135 | X31: =IF(AA31<>"",SUMIFS(DefaultAFOLU!$G:$G,DefaultAFOLU!$D:$D,Livestock!AA31,DefaultAFOLU!$B:$B,Livestock!X$4,DefaultAFOLU!$C:$C,Livestock!Z31),"") -> 1e-05 | Z31: Swine, breeding | AA31: Farm | AB31: =INDEX('InputCritical-yearless'!$C$12:$N$13, MATCH(AA31, 'InputCritical-yearless'!$B$12:$B$13, 0), MATCH(LEFT(Z31, 3), 'InputCritical-yearless'!$C$11:$N$11, 0)) -> 0.5
B32: =IF(SUM(W32:W32)=0,"\I:","DMD") -> \I: | N32: SWBMNR | S32: =VLOOKUP(Z31,'Calculations - livestock '!$A$25:$E$37,3,FALSE) -> 0.036125 | T32: =IFERROR(IF(VLOOKUP($Z32,'Calculations - livestock '!$A$5:$M$17,4,FALSE)= 0, "",1000*VLOOKUP($Z32,'Calculations - livestock '!$A$5:$M$17,4,FALSE)), " ") | U32: =IF($S33=0,IFERROR(IF(VLOOKUP($Z32,'Calculations - livestock '!$A$5:$M$17,6,FALSE)= 0, "",1000*VLOOKUP($Z32,'Calculations - livestock '!$A$5:$M$17,6,FALSE)), " "),"") | V32: =IF($S33=0,IFERROR(IF(VLOOKUP($Z32,'Calculations - livestock '!$A$5:$M$17,9,FALSE)= 0, "",1000*VLOOKUP($Z32,'Calculations - livestock '!$A$5:$M$17,9,FALSE)), " "),"") | X32: =IF(AA32<>"",SUMIFS(DefaultAFOLU!$G:$G,DefaultAFOLU!$D:$D,Livestock!AA32,DefaultAFOLU!$B:$B,Livestock!X$4,DefaultAFOLU!$C:$C,Livestock!Z32),"") | AC32: =S32*W31 -> 2.5581377
B33: =IF(SUM(W33:W33)=0,"\I:","DMD") -> DMD | C33: AFOLIVFRMSWMWTRE0 | D33: Afolu Livestock Farm Swine, market Existing 0 | E33: kHeadsA | F33: kHeads | G33: Annual | H33: NO | J33: =IF(SUM(W33:W33)=0,"\I:",C33) -> AFOLIVFRMSWMWTRE0 | K33: Afolu Livestock Farm Swine, market Existing 0 | L33: WTRAFO | M33: AFOLIVSWMDEM | O33: 1 | P33: {=IFERROR(1/INDEX('Calc - water'!G:G, MATCH(1, (Z33='Calc - water'!B:B)*(AA33='Calc - water'!C:C), 0)),0)} -> 348.00515 | Q33: 1 | R33: 10 | T33: =IFERROR(IF(VLOOKUP($Z33,'Calculations - livestock '!$A$5:$M$17,4,FALSE)= 0, "",1000*VLOOKUP($Z33,'Calculations - livestock '!$A$5:$M$17,4,FALSE)), " ") -> 0.0015000279 | U33: =IF($S34=0,IFERROR(IF(VLOOKUP($Z33,'Calculations - livestock '!$A$5:$M$17,6,FALSE)= 0, "",1000*VLOOKUP($Z33,'Calculations - livestock '!$A$5:$M$17,6,FALSE)), " "),"") | V33: =IF($S34=0,IFERROR(IF(VLOOKUP($Z33,'Calculations - livestock '!$A$5:$M$17,9,FALSE)= 0, "",1000*VLOOKUP($Z33,'Calculations - livestock '!$A$5:$M$17,9,FALSE)), " "),"") | W33: =IFERROR(IF(VLOOKUP($Z33,'Calculations - livestock '!$A:$B,2,FALSE)/1000*$AB33=0,"",VLOOKUP($Z33,'Calculations - livestock '!$A:$B,2,FALSE)/1000*$AB33)," ") -> 637.3215 | X33: =IF(AA33<>"",SUMIFS(DefaultAFOLU!$G:$G,DefaultAFOLU!$D:$D,Livestock!AA33,DefaultAFOLU!$B:$B,Livestock!X$4,DefaultAFOLU!$C:$C,Livestock!Z33),"") -> 1e-05 | Z33: Swine, market | AA33: Farm | AB33: =INDEX('InputCritical-yearless'!$C$12:$N$13, MATCH(AA33, 'InputCritical-yearless'!$B$12:$B$13, 0), MATCH(LEFT(Z33, 3), 'InputCritical-yearless'!$C$11:$N$11, 0)) -> 0.5
B34: =IF(SUM(W34:W34)=0,"\I:","DMD") -> \I: | N34: SWMMNR | S34: =VLOOKUP(Z33,'Calculations - livestock '!$A$25:$E$37,3,FALSE) -> 0.0148125 | T34: =IFERROR(IF(VLOOKUP($Z34,'Calculations - livestock '!$A$5:$M$17,4,FALSE)= 0, "",1000*VLOOKUP($Z34,'Calculations - livestock '!$A$5:$M$17,4,FALSE)), " ") | U34: =IF($S35=0,IFERROR(IF(VLOOKUP($Z34,'Calculations - livestock '!$A$5:$M$17,6,FALSE)= 0, "",1000*VLOOKUP($Z34,'Calculations - livestock '!$A$5:$M$17,6,FALSE)), " "),"") | V34: =IF($S35=0,IFERROR(IF(VLOOKUP($Z34,'Calculations - livestock '!$A$5:$M$17,9,FALSE)= 0, "",1000*VLOOKUP($Z34,'Calculations - livestock '!$A$5:$M$17,9,FALSE)), " "),"") | X34: =IF(AA34<>"",SUMIFS(DefaultAFOLU!$G:$G,DefaultAFOLU!$D:$D,Livestock!AA34,DefaultAFOLU!$B:$B,Livestock!X$4,DefaultAFOLU!$C:$C,Livestock!Z34),"") | AC34: =S34*W33 -> 9.4403247
B35: =IF(SUM(W35:W35)=0,"\I:","DMD") -> DMD | C35: AFOLIVFRMPOUWTRE0 | D35: Afolu Livestock Farm Poultry Existing 0 | E35: kHeadsA | F35: kHeads | G35: Annual | H35: NO | J35: =IF(SUM(W35:W35)=0,"\I:",C35) -> AFOLIVFRMPOUWTRE0 | K35: Afolu Livestock Farm Poultry Existing 0 | L35: WTRAFO | M35: AFOLIVPOUDEM | O35: 1 | P35: {=IFERROR(1/INDEX('Calc - water'!G:G, MATCH(1, (Z35='Calc - water'!B:B)*(AA35='Calc - water'!C:C), 0)),0)} -> 13729.518 | Q35: 1 | R35: 10 | T35: =IFERROR(IF(VLOOKUP($Z35,'Calculations - livestock '!$A$5:$M$17,4,FALSE)= 0, "",1000*VLOOKUP($Z35,'Calculations - livestock '!$A$5:$M$17,4,FALSE)), " ") | U35: =IF($S36=0,IFERROR(IF(VLOOKUP($Z35,'Calculations - livestock '!$A$5:$M$17,6,FALSE)= 0, "",1000*VLOOKUP($Z35,'Calculations - livestock '!$A$5:$M$17,6,FALSE)), " "),"") -> 1.9999673e-05 | V35: =IF($S36=0,IFERROR(IF(VLOOKUP($Z35,'Calculations - livestock '!$A$5:$M$17,9,FALSE)= 0, "",1000*VLOOKUP($Z35,'Calculations - livestock '!$A$5:$M$17,9,FALSE)), " "),"") -> 2.8361289e-06 | W35: =IFERROR(IF(VLOOKUP($Z35,'Calculations - livestock '!$A:$B,2,FALSE)/1000*$AB35=0,"",VLOOKUP($Z35,'Calculations - livestock '!$A:$B,2,FALSE)/1000*$AB35)," ") -> 11582.69 | X35: =IF(AA35<>"",SUMIFS(DefaultAFOLU!$G:$G,DefaultAFOLU!$D:$D,Livestock!AA35,DefaultAFOLU!$B:$B,Livestock!X$4,DefaultAFOLU!$C:$C,Livestock!Z35),"") -> 1e-05 | Z35: Poultry | AA35: Farm | AB35: =INDEX('InputCritical-yearless'!$C$12:$N$13, MATCH(AA35, 'InputCritical-yearless'!$B$12:$B$13, 0), MATCH(LEFT(Z35, 3), 'InputCritical-yearless'!$C$11:$N$11, 0)) -> 0.5
T36: =IFERROR(IF(VLOOKUP($Z36,'Calculations - livestock '!$A$5:$M$17,4,FALSE)= 0, "",1000*VLOOKUP($Z36,'Calculations - livestock '!$A$5:$M$17,4,FALSE)), " ") | U36: =IF($S37=0,IFERROR(IF(VLOOKUP($Z36,'Calculations - livestock '!$A$5:$M$17,6,FALSE)= 0, "",1000*VLOOKUP($Z36,'Calculations - livestock '!$A$5:$M$17,6,FALSE)), " "),"") | V36: =IF($S37=0,IFERROR(IF(VLOOKUP($Z36,'Calculations - livestock '!$A$5:$M$17,9,FALSE)= 0, "",1000*VLOOKUP($Z36,'Calculations - livestock '!$A$5:$M$17,9,FALSE)), " "),"")
T37: =IFERROR(IF(VLOOKUP($Z37,'Calculations - livestock '!$A$5:$M$17,4,FALSE)= 0, "",1000*VLOOKUP($Z37,'Calculations - livestock '!$A$5:$M$17,4,FALSE)), " ") | U37: =IF($S38=0,IFERROR(IF(VLOOKUP($Z37,'Calculations - livestock '!$A$5:$M$17,6,FALSE)= 0, "",1000*VLOOKUP($Z37,'Calculations - livestock '!$A$5:$M$17,6,FALSE)), " "),"") | V37: =IF($S38=0,IFERROR(IF(VLOOKUP($Z37,'Calculations - livestock '!$A$5:$M$17,9,FALSE)= 0, "",1000*VLOOKUP($Z37,'Calculations - livestock '!$A$5:$M$17,9,FALSE)), " "),"")

Sheet Livestock Demand
A1: This sheet contains the Afolu sectors LivestockDemands
B3: ~FI_Comm | I3: ~FI_T
B4: CSet | C4: CommName | D4: CommDesc | E4: Unit | F4: LimType | G4: CTSLvl | I4: CommName | J4: DEMAND
B5: \I: | C5: Name | D5: Description | E5: Activity | F5: Capacity | G5: Timeslice levels | I5: \I: Unit | J5: kHeadsA
B6: =IF(SUM(J6:J6)=0,"\I:","DEM") -> \I: | C6: AFOLIVASSDEM | D6: Asses | E6: kHeadsA | F6: FX | G6: Annual | I6: =IF(SUM(J6:J6)=0,"\I:",C6) -> \I: | J6: =VLOOKUP($D6,'Calculations - livestock '!$A$5:$B$17,2,FALSE)/1000 -> 0
B7: =IF(SUM(J7:J7)=0,"\I:","DEM") -> \I: | C7: AFOLIVBUFDEM | D7: Buffalo | E7: kHeadsA | F7: FX | G7: Annual | I7: =IF(SUM(J7:J7)=0,"\I:",C7) -> \I: | J7: =VLOOKUP($D7,'Calculations - livestock '!$A$5:$B$17,2,FALSE)/1000 -> 0
B8: =IF(SUM(J8:J8)=0,"\I:","DEM") -> \I: | C8: AFOLIVCAMDEM | D8: Camels | E8: kHeadsA | F8: FX | G8: Annual | I8: =IF(SUM(J8:J8)=0,"\I:",C8) -> \I: | J8: =VLOOKUP($D8,'Calculations - livestock '!$A$5:$B$17,2,FALSE)/1000 -> 0
B9: =IF(SUM(J9:J9)=0,"\I:","DEM") -> DEM | C9: AFOLIVCADDEM | D9: Cattle, dairy | E9: kHeadsA | F9: FX | G9: Annual | I9: =IF(SUM(J9:J9)=0,"\I:",C9) -> AFOLIVCADDEM | J9: =VLOOKUP($D9,'Calculations - livestock '!$A$5:$B$17,2,FALSE)/1000 -> 297.67
B10: =IF(SUM(J10:J10)=0,"\I:","DEM") -> DEM | C10: AFOLIVCANDEM | D10: Cattle, non-dairy | E10: kHeadsA | F10: FX | G10: Annual | I10: =IF(SUM(J10:J10)=0,"\I:",C10) -> AFOLIVCANDEM | J10: =VLOOKUP($D10,'Calculations - livestock '!$A$5:$B$17,2,FALSE)/1000 -> 1092.88
B11: =IF(SUM(J11:J11)=0,"\I:","DEM") -> DEM | C11: AFOLIVGOADEM | D11: Goats | E11: kHeadsA | F11: FX | G11: Annual | I11: =IF(SUM(J11:J11)=0,"\I:",C11) -> AFOLIVGOADEM | J11: =VLOOKUP($D11,'Calculations - livestock '!$A$5:$B$17,2,FALSE)/1000 -> 12
B12: =IF(SUM(J12:J12)=0,"\I:","DEM") -> DEM | C12: AFOLIVHORDEM | D12: Horses | E12: kHeadsA | F12: FX | G12: Annual | I12: =IF(SUM(J12:J12)=0,"\I:",C12) -> AFOLIVHORDEM | J12: =VLOOKUP($D12,'Calculations - livestock '!$A$5:$B$17,2,FALSE)/1000 -> 106.656
B13: =IF(SUM(J13:J13)=0,"\I:","DEM") -> \I: | C13: AFOLIVLLADEM | D13: Llamas | E13: kHeadsA | F13: FX | G13: Annual | I13: =IF(SUM(J13:J13)=0,"\I:",C13) -> \I: | J13: =VLOOKUP($D13,'Calculations - livestock '!$A$5:$B$17,2,FALSE)/1000 -> 0
B14: =IF(SUM(J14:J14)=0,"\I:","DEM") -> \I: | C14: AFOLIVMULDEM | D14: Mules and hinnies | E14: kHeadsA | F14: FX | G14: Annual | I14: =IF(SUM(J14:J14)=0,"\I:",C14) -> \I: | J14: =VLOOKUP($D14,'Calculations - livestock '!$A$5:$B$17,2,FALSE)/1000 -> 0
B15: =IF(SUM(J15:J15)=0,"\I:","DEM") -> DEM | C15: AFOLIVSHPDEM | D15: Sheep | E15: kHeadsA | F15: FX | G15: Annual | I15: =IF(SUM(J15:J15)=0,"\I:",C15) -> AFOLIVSHPDEM | J15: =VLOOKUP($D15,'Calculations - livestock '!$A$5:$B$17,2,FALSE)/1000 -> 340.84
B16: =IF(SUM(J16:J16)=0,"\I:","DEM") -> DEM | C16: AFOLIVSWBDEM | D16: Swine, breeding | E16: kHeadsA | F16: FX | G16: Annual | I16: =IF(SUM(J16:J16)=0,"\I:",C16) -> AFOLIVSWBDEM | J16: =VLOOKUP($D16,'Calculations - livestock '!$A$5:$B$17,2,FALSE)/1000 -> 141.627
B17: =IF(SUM(J17:J17)=0,"\I:","DEM") -> DEM | C17: AFOLIVSWMDEM | D17: Swine, market | E17: kHeadsA | F17: FX | G17: Annual | I17: =IF(SUM(J17:J17)=0,"\I:",C17) -> AFOLIVSWMDEM | J17: =VLOOKUP($D17,'Calculations - livestock '!$A$5:$B$17,2,FALSE)/1000 -> 1274.643
B18: =IF(SUM(J18:J18)=0,"\I:","DEM") -> DEM | C18: AFOLIVPOUDEM | D18: Poultry | E18: kHeadsA | F18: FX | G18: Annual | I18: =IF(SUM(J18:J18)=0,"\I:",C18) -> AFOLIVPOUDEM | J18: =VLOOKUP($D18,'Calculations - livestock '!$A$5:$B$17,2,FALSE)/1000 -> 23165.379

Sheet Forest
A1: This sheet contains the Afolu sectors Forests
B4: ~FI_Process | K4: ~FI_T
B5: Sets | C5: TechName | D5: TechDesc | E5: Tact | F5: Tcap | G5: Tslvl | H5: Vintage | J5: TechName | K5: *TechDesc | L5: Comm-IN | M5: Comm-OUT | N5: CAP2ACT | O5: EFF | P5: Share-O~UP | Q5: Share-O~UP~0 | R5: AFA | S5: LIFE | T5: EMISSIONS~AFOFRSCO2 | U5: NCAP_PASTI | V5: NCAP_COST
B6: \I: | C6: Name | D6: Description | E6: Activity | F6: Capacity | G6: Timeslice levels | H6: Tracking of investment year | J6: \I: Unit | M6: Kha | N6: KhaA/kha | O6: TJ/kha | R6: Annual aviability | S6: Years | T6: ktCO2/kha | U6: kha | V6: MEUR/kha
B7: MIN | C7: AFOFRSMIN | D7: Afolu Mining Forest Generic forest Existing 0 | E7: KhaA | F7: kha | G7: Annual | H7: NO | J7: =C7 -> AFOFRSMIN | K7: =D7 -> Afolu Mining Forest Generic forest Existing 0 | M7: FRSNATGEF | N7: 1 | R7: 1 | S7: 100
B8: PRE | C8: AFOFRSNRGFE0 | D8: Afolu Forest Generic forest Existing 1 | E8: KhaA | F8: kha | G8: Annual | H8: NO | J8: =C8 -> AFOFRSNRGFE0 | K8: =D8 -> Afolu Forest Generic forest Existing 1 | L8: FRSNATGEF | M8: FRSWOC | N8: 1 | O8: 1 | P8: =ROUND('Calc - forest biomass'!$N$5/SUM('Calc - forest biomass'!$N$5:$N$6),4) -> 0.4999 | Q8: 5 | R8: 1 | S8: 100 | T8: =('Calc - land emissions'!E13+'Calc - land emissions'!E14)/U8 -> -0.75533333 | U8: =VLOOKUP("Forest land",'Calc - land area'!$B:$C,2,FALSE) -> 27980 | V8: ='Input data - Other'!F19 -> 1.0166
B9: \I: | M9: FRSWOP
B10: \I: | M10: FRSFIW
B11: PRE | C11: AFOFRSWOCTRA | D11: Afolu Forest transferring WOC to energy content | E11: TJ | F11: TJ | G11: Annual | H11: NO | J11: =C11 -> AFOFRSWOCTRA | K11: =D11 -> Afolu Forest transferring WOC to energy content | L11: FRSWOC | M11: WOC | N11: 1 | O11: ='Calc - forest biomass'!$P$5 -> 8.7419957 | R11: 1 | S11: 100 | Z11: =IF(AND(ISNUMBER(V11), V11<>0), 5, "") | AA11: =IF(AND(ISNUMBER(W11), W11<>0), 5, "") | AB11: =IF(AND(ISNUMBER(X11), X11<>0), 5, "") | AC11: =IF(AND(ISNUMBER(Y11), Y11<>0), 5, "")
B12: PRE | C12: AFOFRSWOPTRA | D12: Afolu Forest transferring WOP to energy content | E12: TJ | F12: TJ | G12: Annual | H12: NO | J12: AFOFRSWOPTRA | K12: Afolu Forest transferring WOP to energy content | L12: FRSWOP | M12: WOP | N12: 1 | O12: ='Calc - forest biomass'!$P$5 -> 8.7419957 | R12: 1 | S12: 100
B13: PRE | C13: AFOFRSFIWTRA | D13: Afolu Forest transferring FIW to energy content | E13: TJ | F13: TJ | G13: Annual | H13: NO | J13: AFOFRSFIWTRA | K13: Afolu Forest transferring FIW to energy content | L13: FRSFIW | M13: FIW | N13: 1 | O13: ='Calc - forest biomass'!$P$5 -> 8.7419957 | R13: 1 | S13: 100
Z19: =IF(AND(ISNUMBER(V19), V19<>0), 5, "") | AA19: =IF(AND(ISNUMBER(W19), W19<>0), 5, "")
Z20: =IF(AND(ISNUMBER(V20), V20<>0), 5, "") | AA20: =IF(AND(ISNUMBER(W20), W20<>0), 5, "")
Z21: =IF(AND(ISNUMBER(V21), V21<>0), 5, "") | AA21: =IF(AND(ISNUMBER(W21), W21<>0), 5, "")
Z22: =IF(AND(ISNUMBER(V22), V22<>0), 5, "") | AA22: =IF(AND(ISNUMBER(W22), W22<>0), 5, "")
Z23: =IF(AND(ISNUMBER(V23), V23<>0), 5, "") | AA23: =IF(AND(ISNUMBER(W23), W23<>0), 5, "")
Z24: =IF(AND(ISNUMBER(V24), V24<>0), 5, "") | AA24: =IF(AND(ISNUMBER(W24), W24<>0), 5, "")
Z25: =IF(AND(ISNUMBER(V25), V25<>0), 5, "") | AA25: =IF(AND(ISNUMBER(W25), W25<>0), 5, "")
Z26: =IF(AND(ISNUMBER(V26), V26<>0), 5, "") | AA26: =IF(AND(ISNUMBER(W26), W26<>0), 5, "")
Z27: =IF(AND(ISNUMBER(V27), V27<>0), 5, "") | AA27: =IF(AND(ISNUMBER(W27), W27<>0), 5, "")
Z28: =IF(AND(ISNUMBER(V28), V28<>0), 5, "") | AA28: =IF(AND(ISNUMBER(W28), W28<>0), 5, "")
Z29: =IF(AND(ISNUMBER(V29), V29<>0), 5, "") | AA29: =IF(AND(ISNUMBER(W29), W29<>0), 5, "")
Z30: =IF(AND(ISNUMBER(V30), V30<>0), 5, "") | AA30: =IF(AND(ISNUMBER(W30), W30<>0), 5, "")
... Z45: =IF(AND(ISNUMBER(V45), V45<>0), 5, "") | AA45: =IF(AND(ISNUMBER(W45), W45<>0), 5, "")

Sheet Pasture
A1: This sheet contains the Afolu sectors Pasture
B4: ~FI_Process | L4: ~FI_T
B5: Sets | C5: TechName | D5: TechDesc | E5: *Technological Option | F5: Tact | G5: Tcap | H5: Tslvl | I5: Vintage | K5: TechName | L5: *TechDesc | M5: Comm-IN | N5: Comm-OUT | O5: CAP2ACT | P5: EFF | Q5: AFA | R5: LIFE | S5: ="EMISSIONS~"&$C$4&$D$4&"AFOPASN2O" -> EMISSIONS~AFOPASN2O | T5: NCAP_PASTI | U5: FIXOM
B6: \I: | C6: Name | D6: Description | F6: Activity | G6: Capacity | H6: Timeslice levels | I6: Tracking of investment year | K6: \I: Unit | S6: Kt/Kha | T6: Interpolation | U6: MEUR/kha
B7: DMD | C7: AFOPASNATGEPWTRE0 | D7: Afolu Pasture Generic pasture | E7: Pasture | F7: KhaA | G7: kha | H7: Annual | I7: NO | K7: =C7 -> AFOPASNATGEPWTRE0 | L7: =D7 -> Afolu Pasture Generic pasture | M7: WTRAFO | N7: AFOPASGEPDEM | O7: 1 | P7: =1000/'Calc - water'!G48 -> 35.61254 | Q7: 1 | R7: 100 | S7: ='Calc - land emissions'!C10/'Calc - land area'!G8 -> 0.00073450099 | T7: ='Calc - land area'!$G$8 -> 1513 | U7: =IF(E7<>"",SUMIFS('Input data - Other'!$F:$F,'Input data - Other'!$B:$B,U5,'Input data - Other'!$D:$D,E7),"") -> 0.156
Y8: =IF(AND(ISNUMBER(U8), U8<>0), 5, "") | Z8: =IF(AND(ISNUMBER(V8), V8<>0), 5, "") | AA8: =IF(AND(ISNUMBER(W8), W8<>0), 5, "")
Y9: =IF(AND(ISNUMBER(U9), U9<>0), 5, "") | Z9: =IF(AND(ISNUMBER(V9), V9<>0), 5, "") | AA9: =IF(AND(ISNUMBER(W9), W9<>0), 5, "")
Y10: =IF(AND(ISNUMBER(U10), U10<>0), 5, "") | Z10: =IF(AND(ISNUMBER(V10), V10<>0), 5, "") | AA10: =IF(AND(ISNUMBER(W10), W10<>0), 5, "")
Y11: =IF(AND(ISNUMBER(U11), U11<>0), 5, "") | Z11: =IF(AND(ISNUMBER(V11), V11<>0), 5, "") | AA11: =IF(AND(ISNUMBER(W11), W11<>0), 5, "")
Y12: =IF(AND(ISNUMBER(U12), U12<>0), 5, "") | Z12: =IF(AND(ISNUMBER(V12), V12<>0), 5, "") | AA12: =IF(AND(ISNUMBER(W12), W12<>0), 5, "")
Y13: =IF(AND(ISNUMBER(U13), U13<>0), 5, "") | Z13: =IF(AND(ISNUMBER(V13), V13<>0), 5, "") | AA13: =IF(AND(ISNUMBER(W13), W13<>0), 5, "")
Y14: =IF(AND(ISNUMBER(U14), U14<>0), 5, "") | Z14: =IF(AND(ISNUMBER(V14), V14<>0), 5, "") | AA14: =IF(AND(ISNUMBER(W14), W14<>0), 5, "")
Y15: =IF(AND(ISNUMBER(U15), U15<>0), 5, "") | Z15: =IF(AND(ISNUMBER(V15), V15<>0), 5, "") | AA15: =IF(AND(ISNUMBER(W15), W15<>0), 5, "")
Y16: =IF(AND(ISNUMBER(U16), U16<>0), 5, "") | Z16: =IF(AND(ISNUMBER(V16), V16<>0), 5, "") | AA16: =IF(AND(ISNUMBER(W16), W16<>0), 5, "")
Y17: =IF(AND(ISNUMBER(U17), U17<>0), 5, "") | Z17: =IF(AND(ISNUMBER(V17), V17<>0), 5, "") | AA17: =IF(AND(ISNUMBER(W17), W17<>0), 5, "")
Y18: =IF(AND(ISNUMBER(U18), U18<>0), 5, "") | Z18: =IF(AND(ISNUMBER(V18), V18<>0), 5, "") | AA18: =IF(AND(ISNUMBER(W18), W18<>0), 5, "")
Y19: =IF(AND(ISNUMBER(U19), U19<>0), 5, "") | Z19: =IF(AND(ISNUMBER(V19), V19<>0), 5, "") | AA19: =IF(AND(ISNUMBER(W19), W19<>0), 5, "")
... Y59: =IF(AND(ISNUMBER(U59), U59<>0), 5, "") | Z59: =IF(AND(ISNUMBER(V59), V59<>0), 5, "") | AA59: =IF(AND(ISNUMBER(W59), W59<>0), 5, "")

Sheet PastureDemands
A1: This sheet contains the Afolu sectors PastureDemands
B3: =IF(SUM(J6:J22)<>0,"~FI_Comm","") -> ~FI_Comm | I3: =IF(SUM(J6:J22)<>0,"~FI_T","") -> ~FI_T
B4: CSet | C4: CommName | D4: CommDesc | E4: Unit | F4: LimType | H4: CommName | I4: *Description | J4: DEMAND
B5: \I: | C5: Name | D5: Description | E5: Activity | F5: Capacity | H5: \I: Unit | J5: Kha
B6: DEM | C6: AFOPASGEPDEM | D6: Pasture Demand Commodity | E6: KhaA | F6: FX | H6: AFOPASGEPDEM | I6: =D6 -> Pasture Demand Commodity | J6: =Pasture!T7 -> 1513

Sheet MNR
A1: This sheet contains the Afolu sector MNR
B3: ~FI_Process | I3: ~FI_T
B4: Sets | C4: TechName | D4: TechDesc | E4: Tslvl | F4: Tact | G4: Tcap | I4: TechName | J4: *TechOption | K4: Comm-IN | L4: Comm-OUT | M4: Other_Indexes | N4: CAP2ACT | O4: EFF | P4: AFA | Q4: LIFE | R4: FLO_EMIS~AFOMNRCH4 | S4: FLO_EMIS~AFOMNRN2O | T4: START | U4: NCAP_COST | V4: ACT_COST | W4: NCAP_PASTI | Y4: * For internal calculation purpose only | Z4: * For internal calculation purpose only | AA4: * For internal calculation purpose only | AB4: *CH4 Reduction | AC4: *N2O Reduction
B5: \I: | C5: Name | D5: Description | E5: TimeSlice | I5: \I: | J5: \I: | K5: Name | L5: Name | N5: Kt_CH4/Kt_CH4 | O5: Kt_CH4/Kt_CH4 | R5: Kt_CH4/Kt_CH4 | S5: Kt_N2O/Kt_CH4 | V5: MEUR/KtCH4 | W5: KtCH4 | Y5: Species | Z5: Reduction Factor CH4 | AA5: Reduction Factor N2O
B6: NRG | C6: =I6 -> AFOMNRNNNCADE0 | D6: No Treatment | E6: ANNUAL | F6: KtCH4 | G6: KtCH4 | I6: ="AFOMNR"&J6&LEFT(K6,3)&"E0" -> AFOMNRNNNCADE0 | J6: NNN | K6: CADMNR | L6: =K6&J6 -> CADMNRNNN | M6: =K6 -> CADMNR | N6: 1 | O6: 1 | P6: 1 | Q6: =SUMIFS(DefaultAFOLU!$G:$G,DefaultAFOLU!$B:$B,MNR!Q$4,DefaultAFOLU!$D:$D,MNR!$Y6,DefaultAFOLU!$C:$C,MNR!$J6) -> 100 | R6: =1000*VLOOKUP(Y6,'Calculations - livestock '!$A$5:$M$17,6,FALSE)/VLOOKUP(K6,Livestock!$N$23:$S$34,6,FALSE)*(1-Z6) -> 0.11103821 | S6: =1000*VLOOKUP(Y6,'Calculations - livestock '!$A$5:$M$17,9,FALSE)/VLOOKUP(K6,Livestock!$N$23:$S$34,6,FALSE)*(1-AA6) -> 0.0054425791 | U6: =SUMIFS(DefaultAFOLU!$G:$G,DefaultAFOLU!$B:$B,MNR!U$4,DefaultAFOLU!$D:$D,MNR!$Y6,DefaultAFOLU!$C:$C,MNR!$J6) -> 0.0001 | V6: =SUMIFS(DefaultAFOLU!$G:$G,DefaultAFOLU!$B:$B,MNR!V$4,DefaultAFOLU!$D:$D,MNR!$Y6,DefaultAFOLU!$C:$C,MNR!$J6) -> 0 | W6: =ROUNDUP(SUMIFS(Livestock!$AC$19:$AC$35,Livestock!$N$19:$N$35,MNR!K6),2)*VLOOKUP(MNR!J6,'InputCritical-yearless'!$B$17:$F$24,MATCH(LEFT(MNR!K6,3),'InputCritical-yearless'!$B$16:$F$16,0),FALSE) -> 28.15 | Y6: Cattle, dairy | Z6: 0 | AA6: 0 | AB6: =1000*VLOOKUP(Y6,'Calculations - livestock '!$A$5:$M$17,6,FALSE)/VLOOKUP(M6,Livestock!$N$23:$S$34,6,FALSE)*Z6 -> 0 | AC6: =1000*VLOOKUP(Y6,'Calculations - livestock '!$A$5:$M$17,9,FALSE)/VLOOKUP(M6,Livestock!$N$23:$S$34,6,FALSE)*AA6 -> 0
B7: NRG | C7: =I7 -> AFOMNRNNNCANE0 | D7: No Treatment | E7: ANNUAL | F7: KtCH4 | G7: KtCH4 | I7: ="AFOMNR"&J7&LEFT(K7,3)&"E0" -> AFOMNRNNNCANE0 | J7: NNN | K7: CANMNR | L7: =K7&J7 -> CANMNRNNN | M7: =K7 -> CANMNR | N7: 1 | O7: 1 | P7: 1 | Q7: =SUMIFS(DefaultAFOLU!$G:$G,DefaultAFOLU!$B:$B,MNR!Q$4,DefaultAFOLU!$D:$D,MNR!$Y7,DefaultAFOLU!$C:$C,MNR!$J7) -> 100 | R7: =1000*VLOOKUP(Y7,'Calculations - livestock '!$A$5:$M$17,6,FALSE)/VLOOKUP(K7,Livestock!$N$23:$S$34,6,FALSE)*(1-Z7) -> 0.077357206 | S7: =1000*VLOOKUP(Y7,'Calculations - livestock '!$A$5:$M$17,9,FALSE)/VLOOKUP(K7,Livestock!$N$23:$S$34,6,FALSE)*(1-AA7) -> 0.0051919092 | U7: =SUMIFS(DefaultAFOLU!$G:$G,DefaultAFOLU!$B:$B,MNR!U$4,DefaultAFOLU!$D:$D,MNR!$Y7,DefaultAFOLU!$C:$C,MNR!$J7) -> 0.0001 | V7: =SUMIFS(DefaultAFOLU!$G:$G,DefaultAFOLU!B:B,MNR!V$4,DefaultAFOLU!$D:$D,MNR!$Y7,DefaultAFOLU!$C:$C,MNR!$J7) -> 0 | W7: =ROUNDUP(SUMIFS(Livestock!$AC$19:$AC$35,Livestock!$N$19:$N$35,MNR!K7),2)*VLOOKUP(MNR!J7,'InputCritical-yearless'!$B$17:$F$24,MATCH(LEFT(MNR!K7,3),'InputCritical-yearless'!$B$16:$F$16,0),FALSE) -> 42.39 | Y7: Cattle, non-dairy | Z7: 0 | AA7: 0 | AB7: =1000*VLOOKUP(Y7,'Calculations - livestock '!$A$5:$M$17,6,FALSE)/VLOOKUP(M7,Livestock!$N$23:$S$34,6,FALSE)*Z7 -> 0 | AC7: =1000*VLOOKUP(Y7,'Calculations - livestock '!$A$5:$M$17,9,FALSE)/VLOOKUP(M7,Livestock!$N$23:$S$34,6,FALSE)*AA7 -> 0
B8: NRG | C8: =I8 -> AFOMNRNNNSWBE0 | D8: No Treatment | E8: ANNUAL | F8: KtCH4 | G8: KtCH4 | I8: ="AFOMNR"&J8&LEFT(K8,3)&"E0" -> AFOMNRNNNSWBE0 | J8: NNN | K8: SWBMNR | L8: =K8&J8 -> SWBMNRNNN | M8: =K8 -> SWBMNR | N8: 1 | O8: 1 | P8: 1 | Q8: =SUMIFS(DefaultAFOLU!$G:$G,DefaultAFOLU!$B:$B,MNR!Q$4,DefaultAFOLU!$D:$D,MNR!$Y8,DefaultAFOLU!$C:$C,MNR!$J8) -> 100 | R8: =1000*VLOOKUP(Y8,'Calculations - livestock '!$A$5:$M$17,6,FALSE)/VLOOKUP(K8,Livestock!$N$23:$S$34,6,FALSE)*(1-Z8) -> 0.24912654 | S8: =1000*VLOOKUP(Y8,'Calculations - livestock '!$A$5:$M$17,9,FALSE)/VLOOKUP(K8,Livestock!$N$23:$S$34,6,FALSE)*(1-AA8) -> 0.0066845503 | U8: =SUMIFS(DefaultAFOLU!$G:$G,DefaultAFOLU!$B:$B,MNR!U$4,DefaultAFOLU!$D:$D,MNR!$Y8,DefaultAFOLU!$C:$C,MNR!$J8) -> 0.0001 | V8: =SUMIFS(DefaultAFOLU!$G:$G,DefaultAFOLU!B:B,MNR!V$4,DefaultAFOLU!$D:$D,MNR!$Y8,DefaultAFOLU!$C:$C,MNR!$J8) -> 0 | W8: =ROUNDUP(SUMIFS(Livestock!$AC$19:$AC$35,Livestock!$N$19:$N$35,MNR!K8),2)*VLOOKUP(MNR!J8,'InputCritical-yearless'!$B$17:$F$24,MATCH(LEFT(MNR!K8,3),'InputCritical-yearless'!$B$16:$F$16,0),FALSE) -> 2.56 | Y8: Swine, breeding | Z8: 0 | AA8: 0 | AB8: =1000*VLOOKUP(Y8,'Calculations - livestock '!$A$5:$M$17,6,FALSE)/VLOOKUP(M8,Livestock!$N$23:$S$34,6,FALSE)*Z8 -> 0 | AC8: =1000*VLOOKUP(Y8,'Calculations - livestock '!$A$5:$M$17,9,FALSE)/VLOOKUP(M8,Livestock!$N$23:$S$34,6,FALSE)*AA8 -> 0
B9: NRG | C9: =I9 -> AFOMNRNNNSWME0 | D9: No Treatment | E9: ANNUAL | F9: KtCH4 | G9: KtCH4 | I9: ="AFOMNR"&J9&LEFT(K9,3)&"E0" -> AFOMNRNNNSWME0 | J9: NNN | K9: SWMMNR | L9: =K9&J9 -> SWMMNRNNN | M9: =K9 -> SWMMNR | N9: 1 | O9: 1 | P9: 1 | Q9: =SUMIFS(DefaultAFOLU!$G:$G,DefaultAFOLU!$B:$B,MNR!Q$4,DefaultAFOLU!$D:$D,MNR!$Y9,DefaultAFOLU!$C:$C,MNR!$J9) -> 100 | R9: =1000*VLOOKUP(Y9,'Calculations - livestock '!$A$5:$M$17,6,FALSE)/VLOOKUP(K9,Livestock!$N$23:$S$34,6,FALSE)*(1-Z9) -> 0.40506552 | S9: =1000*VLOOKUP(Y9,'Calculations - livestock '!$A$5:$M$17,9,FALSE)/VLOOKUP(K9,Livestock!$N$23:$S$34,6,FALSE)*(1-AA9) -> 0.0050051244 | U9: =SUMIFS(DefaultAFOLU!$G:$G,DefaultAFOLU!$B:$B,MNR!U$4,DefaultAFOLU!$D:$D,MNR!$Y9,DefaultAFOLU!$C:$C,MNR!$J9) -> 0.0001 | V9: =SUMIFS(DefaultAFOLU!$G:$G,DefaultAFOLU!B:B,MNR!V$4,DefaultAFOLU!$D:$D,MNR!$Y9,DefaultAFOLU!$C:$C,MNR!$J9) -> 0 | W9: =ROUNDUP(SUMIFS(Livestock!$AC$19:$AC$35,Livestock!$N$19:$N$35,MNR!K9),2)*VLOOKUP(MNR!J9,'InputCritical-yearless'!$B$17:$F$24,MATCH(LEFT(MNR!K9,3),'InputCritical-yearless'!$B$16:$F$16,0),FALSE) -> 9.45 | Y9: Swine, market | Z9: 0 | AA9: 0 | AB9: =1000*VLOOKUP(Y9,'Calculations - livestock '!$A$5:$M$17,6,FALSE)/VLOOKUP(M9,Livestock!$N$23:$S$34,6,FALSE)*Z9 -> 0 | AC9: =1000*VLOOKUP(Y9,'Calculations - livestock '!$A$5:$M$17,9,FALSE)/VLOOKUP(M9,Livestock!$N$23:$S$34,6,FALSE)*AA9 -> 0
B10: NRG | C10: =I10 -> AFOMNRANNCADE0 | D10: Acidification | E10: ANNUAL | F10: KtCH4 | G10: KtCH4 | I10: ="AFOMNR"&J10&LEFT(K10,3)&"E0" -> AFOMNRANNCADE0 | J10: ANN | K10: CADMNR | L10: =K10&J10 -> CADMNRANN | M10: =K10 -> CADMNR | N10: 1 | O10: 1 | P10: 1 | Q10: =SUMIFS(DefaultAFOLU!$G:$G,DefaultAFOLU!$B:$B,MNR!Q$4,DefaultAFOLU!$D:$D,MNR!$Y10,DefaultAFOLU!$C:$C,MNR!$J10) -> 15 | R10: =1000*VLOOKUP(Y10,'Calculations - livestock '!$A$5:$M$17,6,FALSE)/VLOOKUP(K10,Livestock!$N$23:$S$34,6,FALSE)*(1-Z10) -> 0.049967193 | S10: =1000*VLOOKUP(Y10,'Calculations - livestock '!$A$5:$M$17,9,FALSE)/VLOOKUP(K10,Livestock!$N$23:$S$34,6,FALSE)*(1-AA10) -> 0.0032111217 | U10: =SUMIFS(DefaultAFOLU!$G:$G,DefaultAFOLU!$B:$B,MNR!U$4,DefaultAFOLU!$D:$D,MNR!$Y10,DefaultAFOLU!$C:$C,MNR!$J10) -> 0.22534016 | V10: =SUMIFS(DefaultAFOLU!$G:$G,DefaultAFOLU!B:B,MNR!V$4,DefaultAFOLU!$D:$D,MNR!$Y10,DefaultAFOLU!$C:$C,MNR!$J10) -> 0.52109692 | W10: =ROUNDUP(SUMIFS(Livestock!$AC$19:$AC$35,Livestock!$N$19:$N$35,MNR!K10),2)*VLOOKUP(MNR!J10,'InputCritical-yearless'!$B$17:$F$24,MATCH(LEFT(MNR!K10,3),'InputCritical-yearless'!$B$16:$F$16,0),FALSE) -> 0 | Y10: Cattle, dairy | Z10: =VLOOKUP(J10,DefaultAFOLU!$D$269:$H$276,4,FALSE) -> 0.55 | AA10: =VLOOKUP(J10,DefaultAFOLU!$D$269:$H$276,5,FALSE) -> 0.41 | AB10: =1000*VLOOKUP(Y10,'Calculations - livestock '!$A$5:$M$17,6,FALSE)/VLOOKUP(M10,Livestock!$N$23:$S$34,6,FALSE)*Z10 -> 0.061071014 | AC10: =1000*VLOOKUP(Y10,'Calculations - livestock '!$A$5:$M$17,9,FALSE)/VLOOKUP(M10,Livestock!$N$23:$S$34,6,FALSE)*AA10 -> 0.0022314574
B11: NRG | C11: =I11 -> AFOMNRANNCANE0 | D11: Acidification | E11: ANNUAL | F11: KtCH4 | G11: KtCH4 | I11: ="AFOMNR"&J11&LEFT(K11,3)&"E0" -> AFOMNRANNCANE0 | J11: ANN | K11: CANMNR | L11: =K11&J11 -> CANMNRANN | M11: =K11 -> CANMNR | N11: 1 | O11: 1 | P11: 1 | Q11: =SUMIFS(DefaultAFOLU!$G:$G,DefaultAFOLU!$B:$B,MNR!Q$4,DefaultAFOLU!$D:$D,MNR!$Y11,DefaultAFOLU!$C:$C,MNR!$J11) -> 15 | R11: =1000*VLOOKUP(Y11,'Calculations - livestock '!$A$5:$M$17,6,FALSE)/VLOOKUP(K11,Livestock!$N$23:$S$34,6,FALSE)*(1-Z11) -> 0.034810743 | S11: =1000*VLOOKUP(Y11,'Calculations - livestock '!$A$5:$M$17,9,FALSE)/VLOOKUP(K11,Livestock!$N$23:$S$34,6,FALSE)*(1-AA11) -> 0.0030632264 | U11: =SUMIFS(DefaultAFOLU!$G:$G,DefaultAFOLU!$B:$B,MNR!U$4,DefaultAFOLU!$D:$D,MNR!$Y11,DefaultAFOLU!$C:$C,MNR!$J11) -> 0.10624847 | V11: =SUMIFS(DefaultAFOLU!$G:$G,DefaultAFOLU!B:B,MNR!V$4,DefaultAFOLU!$D:$D,MNR!$Y11,DefaultAFOLU!$C:$C,MNR!$J11) -> 0.59910057 | W11: =ROUNDUP(SUMIFS(Livestock!$AC$19:$AC$35,Livestock!$N$19:$N$35,MNR!K11),2)*VLOOKUP(MNR!J11,'InputCritical-yearless'!$B$17:$F$24,MATCH(LEFT(MNR!K11,3),'InputCritical-yearless'!$B$16:$F$16,0),FALSE) -> 0 | Y11: Cattle, non-dairy | Z11: =VLOOKUP(J11,DefaultAFOLU!$D$269:$H$276,4,FALSE) -> 0.55 | AA11: =VLOOKUP(J11,DefaultAFOLU!$D$269:$H$276,5,FALSE) -> 0.41 | AB11: =1000*VLOOKUP(Y11,'Calculations - livestock '!$A$5:$M$17,6,FALSE)/VLOOKUP(M11,Livestock!$N$23:$S$34,6,FALSE)*Z11 -> 0.042546463 | AC11: =1000*VLOOKUP(Y11,'Calculations - livestock '!$A$5:$M$17,9,FALSE)/VLOOKUP(M11,Livestock!$N$23:$S$34,6,FALSE)*AA11 -> 0.0021286828
B12: NRG | C12: =I12 -> AFOMNRANNSWBE0 | D12: Acidification | E12: ANNUAL | F12: KtCH4 | G12: KtCH4 | I12: ="AFOMNR"&J12&LEFT(K12,3)&"E0" -> AFOMNRANNSWBE0 | J12: ANN | K12: SWBMNR | L12: =K12&J12 -> SWBMNRANN | M12: =K12 -> SWBMNR | N12: 1 | O12: 1 | P12: 1 | Q12: =SUMIFS(DefaultAFOLU!$G:$G,DefaultAFOLU!$B:$B,MNR!Q$4,DefaultAFOLU!$D:$D,MNR!$Y12,DefaultAFOLU!$C:$C,MNR!$J12) -> 15 | R12: =1000*VLOOKUP(Y12,'Calculations - livestock '!$A$5:$M$17,6,FALSE)/VLOOKUP(K12,Livestock!$N$23:$S$34,6,FALSE)*(1-Z12) -> 0.11210694 | S12: =1000*VLOOKUP(Y12,'Calculations - livestock '!$A$5:$M$17,9,FALSE)/VLOOKUP(K12,Livestock!$N$23:$S$34,6,FALSE)*(1-AA12) -> 0.0039438847 | U12: =SUMIFS(DefaultAFOLU!$G:$G,DefaultAFOLU!$B:$B,MNR!U$4,DefaultAFOLU!$D:$D,MNR!$Y12,DefaultAFOLU!$C:$C,MNR!$J12) -> 0.058030159 | V12: =SUMIFS(DefaultAFOLU!$G:$G,DefaultAFOLU!B:B,MNR!V$4,DefaultAFOLU!$D:$D,MNR!$Y12,DefaultAFOLU!$C:$C,MNR!$J12) -> 0.70254598 | W12: =ROUNDUP(SUMIFS(Livestock!$AC$19:$AC$35,Livestock!$N$19:$N$35,MNR!K12),2)*VLOOKUP(MNR!J12,'InputCritical-yearless'!$B$17:$F$24,MATCH(LEFT(MNR!K12,3),'InputCritical-yearless'!$B$16:$F$16,0),FALSE) -> 0 | Y12: Swine, breeding | Z12: =VLOOKUP(J12,DefaultAFOLU!$D$269:$H$276,4,FALSE) -> 0.55 | AA12: =VLOOKUP(J12,DefaultAFOLU!$D$269:$H$276,5,FALSE) -> 0.41 | AB12: =1000*VLOOKUP(Y12,'Calculations - livestock '!$A$5:$M$17,6,FALSE)/VLOOKUP(M12,Livestock!$N$23:$S$34,6,FALSE)*Z12 -> 0.1370196 | AC12: =1000*VLOOKUP(Y12,'Calculations - livestock '!$A$5:$M$17,9,FALSE)/VLOOKUP(M12,Livestock!$N$23:$S$34,6,FALSE)*AA12 -> 0.0027406656
B13: NRG | C13: =I13 -> AFOMNRANNSWME0 | D13: Acidification | E13: ANNUAL | F13: KtCH4 | G13: KtCH4 | I13: ="AFOMNR"&J13&LEFT(K13,3)&"E0" -> AFOMNRANNSWME0 | J13: ANN | K13: SWMMNR | L13: =K13&J13 -> SWMMNRANN | M13: =K13 -> SWMMNR | N13: 1 | O13: 1 | P13: 1 | Q13: =SUMIFS(DefaultAFOLU!$G:$G,DefaultAFOLU!$B:$B,MNR!Q$4,DefaultAFOLU!$D:$D,MNR!$Y13,DefaultAFOLU!$C:$C,MNR!$J13) -> 15 | R13: =1000*VLOOKUP(Y13,'Calculations - livestock '!$A$5:$M$17,6,FALSE)/VLOOKUP(K13,Livestock!$N$23:$S$34,6,FALSE)*(1-Z13) -> 0.18227948 | S13: =1000*VLOOKUP(Y13,'Calculations - livestock '!$A$5:$M$17,9,FALSE)/VLOOKUP(K13,Livestock!$N$23:$S$34,6,FALSE)*(1-AA13) -> 0.0029530234 | U13: =SUMIFS(DefaultAFOLU!$G:$G,DefaultAFOLU!$B:$B,MNR!U$4,DefaultAFOLU!$D:$D,MNR!$Y13,DefaultAFOLU!$C:$C,MNR!$J13) -> 0.023212064 | V13: =SUMIFS(DefaultAFOLU!$G:$G,DefaultAFOLU!B:B,MNR!V$4,DefaultAFOLU!$D:$D,MNR!$Y13,DefaultAFOLU!$C:$C,MNR!$J13) -> 0.68535287 | W13: =ROUNDUP(SUMIFS(Livestock!$AC$19:$AC$35,Livestock!$N$19:$N$35,MNR!K13),2)*VLOOKUP(MNR!J13,'InputCritical-yearless'!$B$17:$F$24,MATCH(LEFT(MNR!K13,3),'InputCritical-yearless'!$B$16:$F$16,0),FALSE) -> 0 | Y13: Swine, market | Z13: =VLOOKUP(J13,DefaultAFOLU!$D$269:$H$276,4,FALSE) -> 0.55 | AA13: =VLOOKUP(J13,DefaultAFOLU!$D$269:$H$276,5,FALSE) -> 0.41 | AB13: =1000*VLOOKUP(Y13,'Calculations - livestock '!$A$5:$M$17,6,FALSE)/VLOOKUP(M13,Livestock!$N$23:$S$34,6,FALSE)*Z13 -> 0.22278603 | AC13: =1000*VLOOKUP(Y13,'Calculations - livestock '!$A$5:$M$17,9,FALSE)/VLOOKUP(M13,Livestock!$N$23:$S$34,6,FALSE)*AA13 -> 0.002052101
B14: NRG | C14: =I14 -> AFOMNRNDNCADE0 | D14: Daily_Weekly_Manure_Removal | E14: ANNUAL | F14: KtCH4 | G14: KtCH4 | I14: ="AFOMNR"&J14&LEFT(K14,3)&"E0" -> AFOMNRNDNCADE0 | J14: NDN | K14: CADMNR | L14: =K14&J14 -> CADMNRNDN | M14: =K14 -> CADMNR | N14: 1 | O14: 1 | P14: 1 | Q14: =SUMIFS(DefaultAFOLU!$G:$G,DefaultAFOLU!$B:$B,MNR!Q$4,DefaultAFOLU!$D:$D,MNR!$Y14,DefaultAFOLU!$C:$C,MNR!$J14) -> 5 | R14: =1000*VLOOKUP(Y14,'Calculations - livestock '!$A$5:$M$17,6,FALSE)/VLOOKUP(K14,Livestock!$N$23:$S$34,6,FALSE)*(1-Z14) -> 0.028869934 | S14: =1000*VLOOKUP(Y14,'Calculations - livestock '!$A$5:$M$17,9,FALSE)/VLOOKUP(K14,Livestock!$N$23:$S$34,6,FALSE)*(1-AA14) -> 0.0045173407 | U14: =SUMIFS(DefaultAFOLU!$G:$G,DefaultAFOLU!$B:$B,MNR!U$4,DefaultAFOLU!$D:$D,MNR!$Y14,DefaultAFOLU!$C:$C,MNR!$J14) -> 0.0001 | V14: =SUMIFS(DefaultAFOLU!$G:$G,DefaultAFOLU!B:B,MNR!V$4,DefaultAFOLU!$D:$D,MNR!$Y14,DefaultAFOLU!$C:$C,MNR!$J14) -> 0.001 | W14: =ROUNDUP(SUMIFS(Livestock!$AC$19:$AC$35,Livestock!$N$19:$N$35,MNR!K14),2)*VLOOKUP(MNR!J14,'InputCritical-yearless'!$B$17:$F$24,MATCH(LEFT(MNR!K14,3),'InputCritical-yearless'!$B$16:$F$16,0),FALSE) -> 0 | Y14: Cattle, dairy | Z14: =VLOOKUP(J14,DefaultAFOLU!$D$269:$H$276,4,FALSE) -> 0.74 | AA14: =VLOOKUP(J14,DefaultAFOLU!$D$269:$H$276,5,FALSE) -> 0.17 | AB14: =1000*VLOOKUP(Y14,'Calculations - livestock '!$A$5:$M$17,6,FALSE)/VLOOKUP(M14,Livestock!$N$23:$S$34,6,FALSE)*Z14 -> 0.082168273 | AC14: =1000*VLOOKUP(Y14,'Calculations - livestock '!$A$5:$M$17,9,FALSE)/VLOOKUP(M14,Livestock!$N$23:$S$34,6,FALSE)*AA14 -> 0.00092523845
B15: NRG | C15: =I15 -> AFOMNRNDNCANE0 | D15: Daily_Weekly_Manure_Removal | E15: ANNUAL | F15: KtCH4 | G15: KtCH4 | I15: ="AFOMNR"&J15&LEFT(K15,3)&"E0" -> AFOMNRNDNCANE0 | J15: NDN | K15: CANMNR | L15: =K15&J15 -> CANMNRNDN | M15: =K15 -> CANMNR | N15: 1 | O15: 1 | P15: 1 | Q15: =SUMIFS(DefaultAFOLU!$G:$G,DefaultAFOLU!$B:$B,MNR!Q$4,DefaultAFOLU!$D:$D,MNR!$Y15,DefaultAFOLU!$C:$C,MNR!$J15) -> 5 | R15: =1000*VLOOKUP(Y15,'Calculations - livestock '!$A$5:$M$17,6,FALSE)/VLOOKUP(K15,Livestock!$N$23:$S$34,6,FALSE)*(1-Z15) -> 0.020112874 | S15: =1000*VLOOKUP(Y15,'Calculations - livestock '!$A$5:$M$17,9,FALSE)/VLOOKUP(K15,Livestock!$N$23:$S$34,6,FALSE)*(1-AA15) -> 0.0043092847 | U15: =SUMIFS(DefaultAFOLU!$G:$G,DefaultAFOLU!$B:$B,MNR!U$4,DefaultAFOLU!$D:$D,MNR!$Y15,DefaultAFOLU!$C:$C,MNR!$J15) -> 0.0001 | V15: =SUMIFS(DefaultAFOLU!$G:$G,DefaultAFOLU!B:B,MNR!V$4,DefaultAFOLU!$D:$D,MNR!$Y15,DefaultAFOLU!$C:$C,MNR!$J15) -> 0.001 | W15: =ROUNDUP(SUMIFS(Livestock!$AC$19:$AC$35,Livestock!$N$19:$N$35,MNR!K15),2)*VLOOKUP(MNR!J15,'InputCritical-yearless'!$B$17:$F$24,MATCH(LEFT(MNR!K15,3),'InputCritical-yearless'!$B$16:$F$16,0),FALSE) -> 0 | Y15: Cattle, non-dairy | Z15: =VLOOKUP(J15,DefaultAFOLU!$D$269:$H$276,4,FALSE) -> 0.74 | AA15: =VLOOKUP(J15,DefaultAFOLU!$D$269:$H$276,5,FALSE) -> 0.17 | AB15: =1000*VLOOKUP(Y15,'Calculations - livestock '!$A$5:$M$17,6,FALSE)/VLOOKUP(M15,Livestock!$N$23:$S$34,6,FALSE)*Z15 -> 0.057244333 | AC15: =1000*VLOOKUP(Y15,'Calculations - livestock '!$A$5:$M$17,9,FALSE)/VLOOKUP(M15,Livestock!$N$23:$S$34,6,FALSE)*AA15 -> 0.00088262457
B16: NRG | C16: =I16 -> AFOMNRNDNSWBE0 | D16: Daily_Weekly_Manure_Removal | E16: ANNUAL | F16: KtCH4 | G16: KtCH4 | I16: ="AFOMNR"&J16&LEFT(K16,3)&"E0" -> AFOMNRNDNSWBE0 | J16: NDN | K16: SWBMNR | L16: =K16&J16 -> SWBMNRNDN | M16: =K16 -> SWBMNR | N16: 1 | O16: 1 | P16: 1 | Q16: =SUMIFS(DefaultAFOLU!$G:$G,DefaultAFOLU!$B:$B,MNR!Q$4,DefaultAFOLU!$D:$D,MNR!$Y16,DefaultAFOLU!$C:$C,MNR!$J16) -> 5 | R16: =1000*VLOOKUP(Y16,'Calculations - livestock '!$A$5:$M$17,6,FALSE)/VLOOKUP(K16,Livestock!$N$23:$S$34,6,FALSE)*(1-Z16) -> 0.064772901 | S16: =1000*VLOOKUP(Y16,'Calculations - livestock '!$A$5:$M$17,9,FALSE)/VLOOKUP(K16,Livestock!$N$23:$S$34,6,FALSE)*(1-AA16) -> 0.0055481767 | U16: =SUMIFS(DefaultAFOLU!$G:$G,DefaultAFOLU!$B:$B,MNR!U$4,DefaultAFOLU!$D:$D,MNR!$Y16,DefaultAFOLU!$C:$C,MNR!$J16) -> 0.0001 | V16: =SUMIFS(DefaultAFOLU!$G:$G,DefaultAFOLU!B:B,MNR!V$4,DefaultAFOLU!$D:$D,MNR!$Y16,DefaultAFOLU!$C:$C,MNR!$J16) -> 0.001 | W16: =ROUNDUP(SUMIFS(Livestock!$AC$19:$AC$35,Livestock!$N$19:$N$35,MNR!K16),2)*VLOOKUP(MNR!J16,'InputCritical-yearless'!$B$17:$F$24,MATCH(LEFT(MNR!K16,3),'InputCritical-yearless'!$B$16:$F$16,0),FALSE) -> 0 | Y16: Swine, breeding | Z16: =VLOOKUP(J16,DefaultAFOLU!$D$269:$H$276,4,FALSE) -> 0.74 | AA16: =VLOOKUP(J16,DefaultAFOLU!$D$269:$H$276,5,FALSE) -> 0.17 | AB16: =1000*VLOOKUP(Y16,'Calculations - livestock '!$A$5:$M$17,6,FALSE)/VLOOKUP(M16,Livestock!$N$23:$S$34,6,FALSE)*Z16 -> 0.18435364 | AC16: =1000*VLOOKUP(Y16,'Calculations - livestock '!$A$5:$M$17,9,FALSE)/VLOOKUP(M16,Livestock!$N$23:$S$34,6,FALSE)*AA16 -> 0.0011363735
B17: NRG | C17: =I17 -> AFOMNRNDNSWME0 | D17: Daily_Weekly_Manure_Removal | E17: ANNUAL | F17: KtCH4 | G17: KtCH4 | I17: ="AFOMNR"&J17&LEFT(K17,3)&"E0" -> AFOMNRNDNSWME0 | J17: NDN | K17: SWMMNR | L17: =K17&J17 -> SWMMNRNDN | M17: =K17 -> SWMMNR | N17: 1 | O17: 1 | P17: 1 | Q17: =SUMIFS(DefaultAFOLU!$G:$G,DefaultAFOLU!$B:$B,MNR!Q$4,DefaultAFOLU!$D:$D,MNR!$Y17,DefaultAFOLU!$C:$C,MNR!$J17) -> 5 | R17: =1000*VLOOKUP(Y17,'Calculations - livestock '!$A$5:$M$17,6,FALSE)/VLOOKUP(K17,Livestock!$N$23:$S$34,6,FALSE)*(1-Z17) -> 0.10531703 | S17: =1000*VLOOKUP(Y17,'Calculations - livestock '!$A$5:$M$17,9,FALSE)/VLOOKUP(K17,Livestock!$N$23:$S$34,6,FALSE)*(1-AA17) -> 0.0041542533 | U17: =SUMIFS(DefaultAFOLU!$G:$G,DefaultAFOLU!$B:$B,MNR!U$4,DefaultAFOLU!$D:$D,MNR!$Y17,DefaultAFOLU!$C:$C,MNR!$J17) -> 0.0001 | V17: =SUMIFS(DefaultAFOLU!$G:$G,DefaultAFOLU!B:B,MNR!V$4,DefaultAFOLU!$D:$D,MNR!$Y17,DefaultAFOLU!$C:$C,MNR!$J17) -> 0.001 | W17: =ROUNDUP(SUMIFS(Livestock!$AC$19:$AC$35,Livestock!$N$19:$N$35,MNR!K17),2)*VLOOKUP(MNR!J17,'InputCritical-yearless'!$B$17:$F$24,MATCH(LEFT(MNR!K17,3),'InputCritical-yearless'!$B$16:$F$16,0),FALSE) -> 0 | Y17: Swine, market | Z17: =VLOOKUP(J17,DefaultAFOLU!$D$269:$H$276,4,FALSE) -> 0.74 | AA17: =VLOOKUP(J17,DefaultAFOLU!$D$269:$H$276,5,FALSE) -> 0.17 | AB17: =1000*VLOOKUP(Y17,'Calculations - livestock '!$A$5:$M$17,6,FALSE)/VLOOKUP(M17,Livestock!$N$23:$S$34,6,FALSE)*Z17 -> 0.29974848 | AC17: =1000*VLOOKUP(Y17,'Calculations - livestock '!$A$5:$M$17,9,FALSE)/VLOOKUP(M17,Livestock!$N$23:$S$34,6,FALSE)*AA17 -> 0.00085087116
B18: NRG | C18: =I18 -> AFOMNRNNMCADE0 | D18: Manure_Storage_Covers | E18: ANNUAL | F18: KtCH4 | G18: KtCH4 | I18: ="AFOMNR"&J18&LEFT(K18,3)&"E0" -> AFOMNRNNMCADE0 | J18: NNM | K18: CADMNR | L18: =K18&J18 -> CADMNRNNM | M18: =K18 -> CADMNR | N18: 1 | O18: 1 | P18: 1 | Q18: =SUMIFS(DefaultAFOLU!$G:$G,DefaultAFOLU!$B:$B,MNR!Q$4,DefaultAFOLU!$D:$D,MNR!$Y18,DefaultAFOLU!$C:$C,MNR!$J18) -> 5 | R18: =1000*VLOOKUP(Y18,'Calculations - livestock '!$A$5:$M$17,6,FALSE)/VLOOKUP(K18,Livestock!$N$23:$S$34,6,FALSE)*(1-Z18) -> 0.097713622 | S18: =1000*VLOOKUP(Y18,'Calculations - livestock '!$A$5:$M$17,9,FALSE)/VLOOKUP(K18,Livestock!$N$23:$S$34,6,FALSE)*(1-AA18) -> 0.0054425791 | U18: =SUMIFS(DefaultAFOLU!$G:$G,DefaultAFOLU!$B:$B,MNR!U$4,DefaultAFOLU!$D:$D,MNR!$Y18,DefaultAFOLU!$C:$C,MNR!$J18) -> 0.097624343 | V18: =SUMIFS(DefaultAFOLU!$G:$G,DefaultAFOLU!B:B,MNR!V$4,DefaultAFOLU!$D:$D,MNR!$Y18,DefaultAFOLU!$C:$C,MNR!$J18) -> 0 | W18: =ROUNDUP(SUMIFS(Livestock!$AC$19:$AC$35,Livestock!$N$19:$N$35,MNR!K18),2)*VLOOKUP(MNR!J18,'InputCritical-yearless'!$B$17:$F$24,MATCH(LEFT(MNR!K18,3),'InputCritical-yearless'!$B$16:$F$16,0),FALSE) -> 0 | Y18: Cattle, dairy | Z18: =VLOOKUP(J18,DefaultAFOLU!$D$269:$H$276,4,FALSE) -> 0.12 | AA18: =VLOOKUP(J18,DefaultAFOLU!$D$269:$H$276,5,FALSE) -> 0 | AB18: =1000*VLOOKUP(Y18,'Calculations - livestock '!$A$5:$M$17,6,FALSE)/VLOOKUP(M18,Livestock!$N$23:$S$34,6,FALSE)*Z18 -> 0.013324585 | AC18: =1000*VLOOKUP(Y18,'Calculations - livestock '!$A$5:$M$17,9,FALSE)/VLOOKUP(M18,Livestock!$N$23:$S$34,6,FALSE)*AA18 -> 0
B19: NRG | C19: =I19 -> AFOMNRNNMCANE0 | D19: Manure_Storage_Covers | E19: ANNUAL | F19: KtCH4 | G19: KtCH4 | I19: ="AFOMNR"&J19&LEFT(K19,3)&"E0" -> AFOMNRNNMCANE0 | J19: NNM | K19: CANMNR | L19: =K19&J19 -> CANMNRNNM | M19: =K19 -> CANMNR | N19: 1 | O19: 1 | P19: 1 | Q19: =SUMIFS(DefaultAFOLU!$G:$G,DefaultAFOLU!$B:$B,MNR!Q$4,DefaultAFOLU!$D:$D,MNR!$Y19,DefaultAFOLU!$C:$C,MNR!$J19) -> 5 | R19: =1000*VLOOKUP(Y19,'Calculations - livestock '!$A$5:$M$17,6,FALSE)/VLOOKUP(K19,Livestock!$N$23:$S$34,6,FALSE)*(1-Z19) -> 0.068074341 | S19: =1000*VLOOKUP(Y19,'Calculations - livestock '!$A$5:$M$17,9,FALSE)/VLOOKUP(K19,Livestock!$N$23:$S$34,6,FALSE)*(1-AA19) -> 0.0051919092 | U19: =SUMIFS(DefaultAFOLU!$G:$G,DefaultAFOLU!$B:$B,MNR!U$4,DefaultAFOLU!$D:$D,MNR!$Y19,DefaultAFOLU!$C:$C,MNR!$J19) -> 0.04603013 | V19: =SUMIFS(DefaultAFOLU!$G:$G,DefaultAFOLU!B:B,MNR!V$4,DefaultAFOLU!$D:$D,MNR!$Y19,DefaultAFOLU!$C:$C,MNR!$J19) -> 0 | W19: =ROUNDUP(SUMIFS(Livestock!$AC$19:$AC$35,Livestock!$N$19:$N$35,MNR!K19),2)*VLOOKUP(MNR!J19,'InputCritical-yearless'!$B$17:$F$24,MATCH(LEFT(MNR!K19,3),'InputCritical-yearless'!$B$16:$F$16,0),FALSE) -> 0 | Y19: Cattle, non-dairy | Z19: =VLOOKUP(J19,DefaultAFOLU!$D$269:$H$276,4,FALSE) -> 0.12 | AA19: =VLOOKUP(J19,DefaultAFOLU!$D$269:$H$276,5,FALSE) -> 0 | AB19: =1000*VLOOKUP(Y19,'Calculations - livestock '!$A$5:$M$17,6,FALSE)/VLOOKUP(M19,Livestock!$N$23:$S$34,6,FALSE)*Z19 -> 0.0092828647 | AC19: =1000*VLOOKUP(Y19,'Calculations - livestock '!$A$5:$M$17,9,FALSE)/VLOOKUP(M19,Livestock!$N$23:$S$34,6,FALSE)*AA19 -> 0
B20: NRG | C20: =I20 -> AFOMNRNNMSWBE0 | D20: Manure_Storage_Covers | E20: ANNUAL | F20: KtCH4 | G20: KtCH4 | I20: ="AFOMNR"&J20&LEFT(K20,3)&"E0" -> AFOMNRNNMSWBE0 | J20: NNM | K20: SWBMNR | L20: =K20&J20 -> SWBMNRNNM | M20: =K20 -> SWBMNR | N20: 1 | O20: 1 | P20: 1 | Q20: =SUMIFS(DefaultAFOLU!$G:$G,DefaultAFOLU!$B:$B,MNR!Q$4,DefaultAFOLU!$D:$D,MNR!$Y20,DefaultAFOLU!$C:$C,MNR!$J20) -> 5 | R20: =1000*VLOOKUP(Y20,'Calculations - livestock '!$A$5:$M$17,6,FALSE)/VLOOKUP(K20,Livestock!$N$23:$S$34,6,FALSE)*(1-Z20) -> 0.21923136 | S20: =1000*VLOOKUP(Y20,'Calculations - livestock '!$A$5:$M$17,9,FALSE)/VLOOKUP(K20,Livestock!$N$23:$S$34,6,FALSE)*(1-AA20) -> 0.0066845503 | U20: =SUMIFS(DefaultAFOLU!$G:$G,DefaultAFOLU!$B:$B,MNR!U$4,DefaultAFOLU!$D:$D,MNR!$Y20,DefaultAFOLU!$C:$C,MNR!$J20) -> 0.0016585723 | V20: =SUMIFS(DefaultAFOLU!$G:$G,DefaultAFOLU!B:B,MNR!V$4,DefaultAFOLU!$D:$D,MNR!$Y20,DefaultAFOLU!$C:$C,MNR!$J20) -> 0 | W20: =ROUNDUP(SUMIFS(Livestock!$AC$19:$AC$35,Livestock!$N$19:$N$35,MNR!K20),2)*VLOOKUP(MNR!J20,'InputCritical-yearless'!$B$17:$F$24,MATCH(LEFT(MNR!K20,3),'InputCritical-yearless'!$B$16:$F$16,0),FALSE) -> 0 | Y20: Swine, breeding | Z20: =VLOOKUP(J20,DefaultAFOLU!$D$269:$H$276,4,FALSE) -> 0.12 | AA20: =VLOOKUP(J20,DefaultAFOLU!$D$269:$H$276,5,FALSE) -> 0 | AB20: =1000*VLOOKUP(Y20,'Calculations - livestock '!$A$5:$M$17,6,FALSE)/VLOOKUP(M20,Livestock!$N$23:$S$34,6,FALSE)*Z20 -> 0.029895185 | AC20: =1000*VLOOKUP(Y20,'Calculations - livestock '!$A$5:$M$17,9,FALSE)/VLOOKUP(M20,Livestock!$N$23:$S$34,6,FALSE)*AA20 -> 0
B21: NRG | C21: =I21 -> AFOMNRNNMSWME0 | D21: Manure_Storage_Covers | E21: ANNUAL | F21: KtCH4 | G21: KtCH4 | I21: ="AFOMNR"&J21&LEFT(K21,3)&"E0" -> AFOMNRNNMSWME0 | J21: NNM | K21: SWMMNR | L21: =K21&J21 -> SWMMNRNNM | M21: =K21 -> SWMMNR | N21: 1 | O21: 1 | P21: 1 | Q21: =SUMIFS(DefaultAFOLU!$G:$G,DefaultAFOLU!$B:$B,MNR!Q$4,DefaultAFOLU!$D:$D,MNR!$Y21,DefaultAFOLU!$C:$C,MNR!$J21) -> 5 | R21: =1000*VLOOKUP(Y21,'Calculations - livestock '!$A$5:$M$17,6,FALSE)/VLOOKUP(K21,Livestock!$N$23:$S$34,6,FALSE)*(1-Z21) -> 0.35645765 | S21: =1000*VLOOKUP(Y21,'Calculations - livestock '!$A$5:$M$17,9,FALSE)/VLOOKUP(K21,Livestock!$N$23:$S$34,6,FALSE)*(1-AA21) -> 0.0050051244 | U21: =SUMIFS(DefaultAFOLU!$G:$G,DefaultAFOLU!$B:$B,MNR!U$4,DefaultAFOLU!$D:$D,MNR!$Y21,DefaultAFOLU!$C:$C,MNR!$J21) -> 0.0006634289 | V21: =SUMIFS(DefaultAFOLU!$G:$G,DefaultAFOLU!B:B,MNR!V$4,DefaultAFOLU!$D:$D,MNR!$Y21,DefaultAFOLU!$C:$C,MNR!$J21) -> 0 | W21: =ROUNDUP(SUMIFS(Livestock!$AC$19:$AC$35,Livestock!$N$19:$N$35,MNR!K21),2)*VLOOKUP(MNR!J21,'InputCritical-yearless'!$B$17:$F$24,MATCH(LEFT(MNR!K21,3),'InputCritical-yearless'!$B$16:$F$16,0),FALSE) -> 0 | Y21: Swine, market | Z21: =VLOOKUP(J21,DefaultAFOLU!$D$269:$H$276,4,FALSE) -> 0.12 | AA21: =VLOOKUP(J21,DefaultAFOLU!$D$269:$H$276,5,FALSE) -> 0 | AB21: =1000*VLOOKUP(Y21,'Calculations - livestock '!$A$5:$M$17,6,FALSE)/VLOOKUP(M21,Livestock!$N$23:$S$34,6,FALSE)*Z21 -> 0.048607862 | AC21: =1000*VLOOKUP(Y21,'Calculations - livestock '!$A$5:$M$17,9,FALSE)/VLOOKUP(M21,Livestock!$N$23:$S$34,6,FALSE)*AA21 -> 0
... B37: NRG | C37: =I37 -> AFOMNRADMSWME0 | D37: Acidification + Daily_Weekly_Manure_Removal + Manure_Storage_Covers | E37: ANNUAL | F37: KtCH4 | G37: KtCH4 | I37: ="AFOMNR"&J37&LEFT(K37,3)&"E0" -> AFOMNRADMSWME0 | J37: ADM | K37: SWMMNR | L37: =K37&J37 -> SWMMNRADM | M37: =K37 -> SWMMNR | N37: 1 | O37: 1 | P37: 1 | Q37: =SUMIFS(DefaultAFOLU!$G:$G,DefaultAFOLU!$B:$B,MNR!Q$4,DefaultAFOLU!$D:$D,MNR!$Y37,DefaultAFOLU!$C:$C,MNR!$J37) -> 15 | R37: =1000*VLOOKUP(Y37,'Calculations - livestock '!$A$5:$M$17,6,FALSE)/VLOOKUP(K37,Livestock!$N$23:$S$34,6,FALSE)*(1-Z37) -> 0.041705545 | S37: =1000*VLOOKUP(Y37,'Calculations - livestock '!$A$5:$M$17,9,FALSE)/VLOOKUP(K37,Livestock!$N$23:$S$34,6,FALSE)*(1-AA37) -> 0.0024510094 | U37: =SUMIFS(DefaultAFOLU!$G:$G,DefaultAFOLU!$B:$B,MNR!U$4,DefaultAFOLU!$D:$D,MNR!$Y37,DefaultAFOLU!$C:$C,MNR!$J37) -> 0.024012911 | V37: =SUMIFS(DefaultAFOLU!$G:$G,DefaultAFOLU!B:B,MNR!V$4,DefaultAFOLU!$D:$D,MNR!$Y37,DefaultAFOLU!$C:$C,MNR!$J37) -> 0.68635287 | W37: =ROUNDUP(SUMIFS(Livestock!$AC$19:$AC$35,Livestock!$N$19:$N$35,MNR!K37),2)*VLOOKUP(MNR!J37,'InputCritical-yearless'!$B$17:$F$24,MATCH(LEFT(MNR!K37,3),'InputCritical-yearless'!$B$16:$F$16,0),FALSE) -> 0 | Y37: Swine, market | Z37: =VLOOKUP(J37,DefaultAFOLU!$D$269:$H$276,4,FALSE) -> 0.89704 | AA37: =VLOOKUP(J37,DefaultAFOLU!$D$269:$H$276,5,FALSE) -> 0.5103 | AB37: =1000*VLOOKUP(Y37,'Calculations - livestock '!$A$5:$M$17,6,FALSE)/VLOOKUP(M37,Livestock!$N$23:$S$34,6,FALSE)*Z37 -> 0.36335997 | AC37: =1000*VLOOKUP(Y37,'Calculations - livestock '!$A$5:$M$17,9,FALSE)/VLOOKUP(M37,Livestock!$N$23:$S$34,6,FALSE)*AA37 -> 0.002554115
B39: ~FI_Process | I39: ~FI_T
B40: Sets | C40: TechName | D40: TechDesc | E40: Tslvl | F40: Tact | G40: Tcap | I40: TechName | J40: *TechOption | K40: Comm-IN | L40: Comm-OUT | M40: Other_Indexes | N40: CAP2ACT | O40: EFF | P40: AFA~FX | Q40: LIFE | R40: FLO_EMIS~AFOBGACH4 | S40: FLO_EMIS~AFOBGAN2O | T40: START | U40: NCAP_COST | V40: FLO_COST | W40: NCAP_PASTI | Y40: * For internal calculation purpose only | Z40: * For internal calculation purpose only | AA40: * For internal calculation purpose only
B41: \I: | C41: Name | D41: Description | E41: TimeSlice | I41: \I: | J41: \I: | K41: Name | L41: Name | N41: TJa/TJ | O41: TJ/Kt_CH4 | R41: Kt_CH4/Kt_CH4 | S41: Kt_N2O/Kt_CH4 | V41: MEUR/KtCH4 | W41: TJ | Y41: Species | Z41: Reduction Factor CH4 | AA41: Reduction Factor N2O
B42: NRG | C42: AFOMNRBGACADE0 | D42: Anaerobically Digested Biogas | E42: ANNUAL | F42: TJ | G42: TJa | I42: =C42 -> AFOMNRBGACADE0 | J42: BGA | K42: {=_xlfn._xlws.FILTER($L$6:$L$37,$M$6:$M$37=MID($I$42,10,3)&"MNR")} -> CADMNRNNN | L42: MNR | M42: =K42 -> CADMNRNNN | N42: 1 | O42: =DefaultAFOLU!$G$21/DefaultAFOLU!$G$20 -> 57.408 | P42: 1 | Q42: =IF($I42<>"",SUMIFS(DefaultAFOLU!$G:$G,DefaultAFOLU!$C:$C,MNR!$I42,DefaultAFOLU!$B:$B,MNR!Q$40),"") -> 25 | R42: =-SUMIF($L$6:$L$37,$M42,R$6:R$37)*Z42 -> -0.03220108 | S42: =-SUMIF($L$6:$L$37,$M42,S$6:S$37)*AA42 -> -0.0011429416 | U42: =IF($I42<>"",SUMIFS(DefaultAFOLU!$G:$G,DefaultAFOLU!$C:$C,MNR!$I42,DefaultAFOLU!$B:$B,MNR!U$40),"") -> 0.0001 | V42: =VLOOKUP(Y42,'Calculations - livestock '!$A$27:$B$35,2,FALSE) -> 0.13572505 | W42: =Livestock!AC23*'Input data - Other'!$F$22*O42 -> 323.18889 | Y42: Cattle, dairy | Z42: =VLOOKUP($J$42,DefaultAFOLU!$D$269:$H$276,4,FALSE) -> 0.29 | AA42: =VLOOKUP($J$42,DefaultAFOLU!$D$269:$H$276,5,FALSE) -> 0.21
B43: NRG | C43: AFOMNRBGACANE0 | D43: Anaerobically Digested Biogas | E43: ANNUAL | F43: TJ | G43: TJa | K43: CADMNRANN | M43: =K43 -> CADMNRANN | Q43: =IF($I43<>"",SUMIFS(DefaultAFOLU!$G:$G,DefaultAFOLU!$C:$C,MNR!$I43,DefaultAFOLU!$B:$B,MNR!Q$40),"") | R43: =-SUMIF($L$6:$L$37,$M43,R$6:R$37)*Z43 -> -0.014490486 | S43: =-SUMIF($L$6:$L$37,$M43,S$6:S$37)*AA43 -> -0.00067433555 | U43: =IF($I43<>"",SUMIFS(DefaultAFOLU!$G:$G,DefaultAFOLU!$C:$C,MNR!$I43,DefaultAFOLU!$B:$B,MNR!U$40),"") | V43: =VLOOKUP(Y43,'Calculations - livestock '!$A$27:$B$35,2,FALSE) -> 0.13572505 | Y43: Cattle, dairy | Z43: =VLOOKUP($J$42,DefaultAFOLU!$D$269:$H$276,4,FALSE) -> 0.29 | AA43: =VLOOKUP($J$42,DefaultAFOLU!$D$269:$H$276,5,FALSE) -> 0.21
B44: NRG | C44: AFOMNRBGASWBE0 | D44: Anaerobically Digested Biogas | E44: ANNUAL | F44: TJ | G44: TJa | K44: CADMNRNDN | M44: =K44 -> CADMNRNDN | Q44: =IF($I44<>"",SUMIFS(DefaultAFOLU!$G:$G,DefaultAFOLU!$C:$C,MNR!$I44,DefaultAFOLU!$B:$B,MNR!Q$40),"") | R44: =-SUMIF($L$6:$L$37,$M44,R$6:R$37)*Z44 -> -0.0083722808 | S44: =-SUMIF($L$6:$L$37,$M44,S$6:S$37)*AA44 -> -0.00094864154 | U44: =IF($I44<>"",SUMIFS(DefaultAFOLU!$G:$G,DefaultAFOLU!$C:$C,MNR!$I44,DefaultAFOLU!$B:$B,MNR!U$40),"") | V44: =VLOOKUP(Y44,'Calculations - livestock '!$A$27:$B$35,2,FALSE) -> 0.13572505 | Y44: Cattle, dairy | Z44: =VLOOKUP($J$42,DefaultAFOLU!$D$269:$H$276,4,FALSE) -> 0.29 | AA44: =VLOOKUP($J$42,DefaultAFOLU!$D$269:$H$276,5,FALSE) -> 0.21
B45: NRG | C45: AFOMNRBGASWME0 | D45: Anaerobically Digested Biogas | E45: ANNUAL | F45: TJ | G45: TJa | K45: CADMNRNNM | M45: =K45 -> CADMNRNNM | Q45: =IF($I45<>"",SUMIFS(DefaultAFOLU!$G:$G,DefaultAFOLU!$C:$C,MNR!$I45,DefaultAFOLU!$B:$B,MNR!Q$40),"") | R45: =-SUMIF($L$6:$L$37,$M45,R$6:R$37)*Z45 -> -0.02833695 | S45: =-SUMIF($L$6:$L$37,$M45,S$6:S$37)*AA45 -> -0.0011429416 | U45: =IF($I45<>"",SUMIFS(DefaultAFOLU!$G:$G,DefaultAFOLU!$C:$C,MNR!$I45,DefaultAFOLU!$B:$B,MNR!U$40),"") | V45: =VLOOKUP(Y45,'Calculations - livestock '!$A$27:$B$35,2,FALSE) -> 0.13572505 | Y45: Cattle, dairy | Z45: =VLOOKUP($J$42,DefaultAFOLU!$D$269:$H$276,4,FALSE) -> 0.29 | AA45: =VLOOKUP($J$42,DefaultAFOLU!$D$269:$H$276,5,FALSE) -> 0.21
K46: CADMNRADN | M46: =K46 -> CADMNRADN | Q46: =IF($I46<>"",SUMIFS(DefaultAFOLU!$G:$G,DefaultAFOLU!$C:$C,MNR!$I46,DefaultAFOLU!$B:$B,MNR!Q$40),"") | R46: =-SUMIF($L$6:$L$37,$M46,R$6:R$37)*Z46 -> -0.0037675263 | S46: =-SUMIF($L$6:$L$37,$M46,S$6:S$37)*AA46 -> -0.00055969851 | U46: =IF($I46<>"",SUMIFS(DefaultAFOLU!$G:$G,DefaultAFOLU!$C:$C,MNR!$I46,DefaultAFOLU!$B:$B,MNR!U$40),"") | V46: =VLOOKUP(Y46,'Calculations - livestock '!$A$27:$B$35,2,FALSE) -> 0.13572505 | Y46: Cattle, dairy | Z46: =VLOOKUP($J$42,DefaultAFOLU!$D$269:$H$276,4,FALSE) -> 0.29 | AA46: =VLOOKUP($J$42,DefaultAFOLU!$D$269:$H$276,5,FALSE) -> 0.21
K47: CADMNRNDM | M47: =K47 -> CADMNRNDM | Q47: =IF($I47<>"",SUMIFS(DefaultAFOLU!$G:$G,DefaultAFOLU!$C:$C,MNR!$I47,DefaultAFOLU!$B:$B,MNR!Q$40),"") | R47: =-SUMIF($L$6:$L$37,$M47,R$6:R$37)*Z47 -> -0.0073676071 | S47: =-SUMIF($L$6:$L$37,$M47,S$6:S$37)*AA47 -> -0.00094864154 | U47: =IF($I47<>"",SUMIFS(DefaultAFOLU!$G:$G,DefaultAFOLU!$C:$C,MNR!$I47,DefaultAFOLU!$B:$B,MNR!U$40),"") | V47: =VLOOKUP(Y47,'Calculations - livestock '!$A$27:$B$35,2,FALSE) -> 0.13572505 | Y47: Cattle, dairy | Z47: =VLOOKUP($J$42,DefaultAFOLU!$D$269:$H$276,4,FALSE) -> 0.29 | AA47: =VLOOKUP($J$42,DefaultAFOLU!$D$269:$H$276,5,FALSE) -> 0.21
K48: CADMNRANM | M48: =K48 -> CADMNRANM | Q48: =IF($I48<>"",SUMIFS(DefaultAFOLU!$G:$G,DefaultAFOLU!$C:$C,MNR!$I48,DefaultAFOLU!$B:$B,MNR!Q$40),"") | R48: =-SUMIF($L$6:$L$37,$M48,R$6:R$37)*Z48 -> -0.0016953869 | S48: =-SUMIF($L$6:$L$37,$M48,S$6:S$37)*AA48 -> -0.00067433555 | U48: =IF($I48<>"",SUMIFS(DefaultAFOLU!$G:$G,DefaultAFOLU!$C:$C,MNR!$I48,DefaultAFOLU!$B:$B,MNR!U$40),"") | V48: =VLOOKUP(Y48,'Calculations - livestock '!$A$27:$B$35,2,FALSE) -> 0.13572505 | Y48: Cattle, dairy | Z48: =VLOOKUP($J$42,DefaultAFOLU!$D$269:$H$276,4,FALSE) -> 0.29 | AA48: =VLOOKUP($J$42,DefaultAFOLU!$D$269:$H$276,5,FALSE) -> 0.21
K49: CADMNRADM | M49: =K49 -> CADMNRADM | Q49: =IF($I49<>"",SUMIFS(DefaultAFOLU!$G:$G,DefaultAFOLU!$C:$C,MNR!$I49,DefaultAFOLU!$B:$B,MNR!Q$40),"") | R49: =-SUMIF($L$6:$L$37,$M49,R$6:R$37)*Z49 -> -0.0033154232 | S49: =-SUMIF($L$6:$L$37,$M49,S$6:S$37)*AA49 -> -0.00055969851 | U49: =IF($I49<>"",SUMIFS(DefaultAFOLU!$G:$G,DefaultAFOLU!$C:$C,MNR!$I49,DefaultAFOLU!$B:$B,MNR!U$40),"") | V49: =VLOOKUP(Y49,'Calculations - livestock '!$A$27:$B$35,2,FALSE) -> 0.13572505 | Y49: Cattle, dairy | Z49: =VLOOKUP($J$42,DefaultAFOLU!$D$269:$H$276,4,FALSE) -> 0.29 | AA49: =VLOOKUP($J$42,DefaultAFOLU!$D$269:$H$276,5,FALSE) -> 0.21
I50: =C43 -> AFOMNRBGACANE0 | J50: BGA | K50: {=_xlfn._xlws.FILTER($L$6:$L$37,$M$6:$M$37=MID($I$50,10,3)&"MNR")} -> CANMNRNNN | L50: MNR | M50: =K50 -> CANMNRNNN | N50: 1 | O50: =DefaultAFOLU!$G$21/DefaultAFOLU!$G$20 -> 57.408 | P50: 1 | Q50: =IF($I50<>"",SUMIFS(DefaultAFOLU!$G:$G,DefaultAFOLU!$C:$C,MNR!$I50,DefaultAFOLU!$B:$B,MNR!Q$40),"") -> 25 | R50: =-SUMIF($L$6:$L$37,$M50,R$6:R$37)*Z50 -> -0.02243359 | S50: =-SUMIF($L$6:$L$37,$M50,S$6:S$37)*AA50 -> -0.0010903009 | U50: =IF($I50<>"",SUMIFS(DefaultAFOLU!$G:$G,DefaultAFOLU!$C:$C,MNR!$I50,DefaultAFOLU!$B:$B,MNR!U$40),"") -> 0.0001 | V50: =VLOOKUP(Y50,'Calculations - livestock '!$A$27:$B$35,2,FALSE) -> 0.1560419 | W50: =Livestock!AC25*'Input data - Other'!$F$22*O50 -> 486.62755 | Y50: Cattle, non-dairy | Z50: =VLOOKUP($J$42,DefaultAFOLU!$D$269:$H$276,4,FALSE) -> 0.29 | AA50: =VLOOKUP($J$42,DefaultAFOLU!$D$269:$H$276,5,FALSE) -> 0.21
K51: CANMNRANN | M51: =K51 -> CANMNRANN | Q51: =IF($I51<>"",SUMIFS(DefaultAFOLU!$G:$G,DefaultAFOLU!$C:$C,MNR!$I51,DefaultAFOLU!$B:$B,MNR!Q$40),"") | R51: =-SUMIF($L$6:$L$37,$M51,R$6:R$37)*Z51 -> -0.010095115 | S51: =-SUMIF($L$6:$L$37,$M51,S$6:S$37)*AA51 -> -0.00064327755 | U51: =IF($I51<>"",SUMIFS(DefaultAFOLU!$G:$G,DefaultAFOLU!$C:$C,MNR!$I51,DefaultAFOLU!$B:$B,MNR!U$40),"") | V51: =VLOOKUP(Y51,'Calculations - livestock '!$A$27:$B$35,2,FALSE) -> 0.1560419 | Y51: Cattle, non-dairy | Z51: =VLOOKUP($J$42,DefaultAFOLU!$D$269:$H$276,4,FALSE) -> 0.29 | AA51: =VLOOKUP($J$42,DefaultAFOLU!$D$269:$H$276,5,FALSE) -> 0.21
K52: CANMNRNDN | M52: =K52 -> CANMNRNDN | Q52: =IF($I52<>"",SUMIFS(DefaultAFOLU!$G:$G,DefaultAFOLU!$C:$C,MNR!$I52,DefaultAFOLU!$B:$B,MNR!Q$40),"") | R52: =-SUMIF($L$6:$L$37,$M52,R$6:R$37)*Z52 -> -0.0058327333 | S52: =-SUMIF($L$6:$L$37,$M52,S$6:S$37)*AA52 -> -0.00090494978 | U52: =IF($I52<>"",SUMIFS(DefaultAFOLU!$G:$G,DefaultAFOLU!$C:$C,MNR!$I52,DefaultAFOLU!$B:$B,MNR!U$40),"") | V52: =VLOOKUP(Y52,'Calculations - livestock '!$A$27:$B$35,2,FALSE) -> 0.1560419 | Y52: Cattle, non-dairy | Z52: =VLOOKUP($J$42,DefaultAFOLU!$D$269:$H$276,4,FALSE) -> 0.29 | AA52: =VLOOKUP($J$42,DefaultAFOLU!$D$269:$H$276,5,FALSE) -> 0.21
K53: CANMNRNNM | M53: =K53 -> CANMNRNNM | Q53: =IF($I53<>"",SUMIFS(DefaultAFOLU!$G:$G,DefaultAFOLU!$C:$C,MNR!$I53,DefaultAFOLU!$B:$B,MNR!Q$40),"") | R53: =-SUMIF($L$6:$L$37,$M53,R$6:R$37)*Z53 -> -0.019741559 | S53: =-SUMIF($L$6:$L$37,$M53,S$6:S$37)*AA53 -> -0.0010903009 | U53: =IF($I53<>"",SUMIFS(DefaultAFOLU!$G:$G,DefaultAFOLU!$C:$C,MNR!$I53,DefaultAFOLU!$B:$B,MNR!U$40),"") | V53: =VLOOKUP(Y53,'Calculations - livestock '!$A$27:$B$35,2,FALSE) -> 0.1560419 | Y53: Cattle, non-dairy | Z53: =VLOOKUP($J$42,DefaultAFOLU!$D$269:$H$276,4,FALSE) -> 0.29 | AA53: =VLOOKUP($J$42,DefaultAFOLU!$D$269:$H$276,5,FALSE) -> 0.21
K54: CANMNRADN | M54: =K54 -> CANMNRADN | Q54: =IF($I54<>"",SUMIFS(DefaultAFOLU!$G:$G,DefaultAFOLU!$C:$C,MNR!$I54,DefaultAFOLU!$B:$B,MNR!Q$40),"") | R54: =-SUMIF($L$6:$L$37,$M54,R$6:R$37)*Z54 -> -0.00262473 | S54: =-SUMIF($L$6:$L$37,$M54,S$6:S$37)*AA54 -> -0.00053392037 | U54: =IF($I54<>"",SUMIFS(DefaultAFOLU!$G:$G,DefaultAFOLU!$C:$C,MNR!$I54,DefaultAFOLU!$B:$B,MNR!U$40),"") | V54: =VLOOKUP(Y54,'Calculations - livestock '!$A$27:$B$35,2,FALSE) -> 0.1560419 | Y54: Cattle, non-dairy | Z54: =VLOOKUP($J$42,DefaultAFOLU!$D$269:$H$276,4,FALSE) -> 0.29 | AA54: =VLOOKUP($J$42,DefaultAFOLU!$D$269:$H$276,5,FALSE) -> 0.21
K55: CANMNRNDM | M55: =K55 -> CANMNRNDM | Q55: =IF($I55<>"",SUMIFS(DefaultAFOLU!$G:$G,DefaultAFOLU!$C:$C,MNR!$I55,DefaultAFOLU!$B:$B,MNR!Q$40),"") | R55: =-SUMIF($L$6:$L$37,$M55,R$6:R$37)*Z55 -> -0.0051328053 | S55: =-SUMIF($L$6:$L$37,$M55,S$6:S$37)*AA55 -> -0.00090494978 | U55: =IF($I55<>"",SUMIFS(DefaultAFOLU!$G:$G,DefaultAFOLU!$C:$C,MNR!$I55,DefaultAFOLU!$B:$B,MNR!U$40),"") | V55: =VLOOKUP(Y55,'Calculations - livestock '!$A$27:$B$35,2,FALSE) -> 0.1560419 | Y55: Cattle, non-dairy | Z55: =VLOOKUP($J$42,DefaultAFOLU!$D$269:$H$276,4,FALSE) -> 0.29 | AA55: =VLOOKUP($J$42,DefaultAFOLU!$D$269:$H$276,5,FALSE) -> 0.21
K56: CANMNRANM | M56: =K56 -> CANMNRANM | Q56: =IF($I56<>"",SUMIFS(DefaultAFOLU!$G:$G,DefaultAFOLU!$C:$C,MNR!$I56,DefaultAFOLU!$B:$B,MNR!Q$40),"") | R56: =-SUMIF($L$6:$L$37,$M56,R$6:R$37)*Z56 -> -0.0011811285 | S56: =-SUMIF($L$6:$L$37,$M56,S$6:S$37)*AA56 -> -0.00064327755 | U56: =IF($I56<>"",SUMIFS(DefaultAFOLU!$G:$G,DefaultAFOLU!$C:$C,MNR!$I56,DefaultAFOLU!$B:$B,MNR!U$40),"") | V56: =VLOOKUP(Y56,'Calculations - livestock '!$A$27:$B$35,2,FALSE) -> 0.1560419 | Y56: Cattle, non-dairy | Z56: =VLOOKUP($J$42,DefaultAFOLU!$D$269:$H$276,4,FALSE) -> 0.29 | AA56: =VLOOKUP($J$42,DefaultAFOLU!$D$269:$H$276,5,FALSE) -> 0.21
K57: CANMNRADM | M57: =K57 -> CANMNRADM | Q57: =IF($I57<>"",SUMIFS(DefaultAFOLU!$G:$G,DefaultAFOLU!$C:$C,MNR!$I57,DefaultAFOLU!$B:$B,MNR!Q$40),"") | R57: =-SUMIF($L$6:$L$37,$M57,R$6:R$37)*Z57 -> -0.0023097624 | S57: =-SUMIF($L$6:$L$37,$M57,S$6:S$37)*AA57 -> -0.00053392037 | U57: =IF($I57<>"",SUMIFS(DefaultAFOLU!$G:$G,DefaultAFOLU!$C:$C,MNR!$I57,DefaultAFOLU!$B:$B,MNR!U$40),"") | V57: =VLOOKUP(Y57,'Calculations - livestock '!$A$27:$B$35,2,FALSE) -> 0.1560419 | Y57: Cattle, non-dairy | Z57: =VLOOKUP($J$42,DefaultAFOLU!$D$269:$H$276,4,FALSE) -> 0.29 | AA57: =VLOOKUP($J$42,DefaultAFOLU!$D$269:$H$276,5,FALSE) -> 0.21
I58: =C44 -> AFOMNRBGASWBE0 | J58: BGA | K58: {=_xlfn._xlws.FILTER($L$6:$L$37,$M$6:$M$37=MID($I$58,10,3)&"MNR")} -> SWBMNRNNN | L58: MNR | M58: =K58 -> SWBMNRNNN | N58: 1 | O58: =DefaultAFOLU!$G$21/DefaultAFOLU!$G$20 -> 57.408 | P58: 1 | Q58: =IF($I58<>"",SUMIFS(DefaultAFOLU!$G:$G,DefaultAFOLU!$C:$C,MNR!$I58,DefaultAFOLU!$B:$B,MNR!Q$40),"") -> 25 | R58: =-SUMIF($L$6:$L$37,$M58,R$6:R$37)*Z58 -> -0.072246698 | S58: =-SUMIF($L$6:$L$37,$M58,S$6:S$37)*AA58 -> -0.0014037556 | U58: =IF($I58<>"",SUMIFS(DefaultAFOLU!$G:$G,DefaultAFOLU!$C:$C,MNR!$I58,DefaultAFOLU!$B:$B,MNR!U$40),"") -> 0.0001 | V58: =VLOOKUP(Y58,'Calculations - livestock '!$A$27:$B$35,2,FALSE) -> 0.14726644 | W58: =Livestock!AC32*'Input data - Other'!$F$22*O58 -> 29.371514 | Y58: Swine, breeding | Z58: =VLOOKUP($J$42,DefaultAFOLU!$D$269:$H$276,4,FALSE) -> 0.29 | AA58: =VLOOKUP($J$42,DefaultAFOLU!$D$269:$H$276,5,FALSE) -> 0.21
K59: SWBMNRANN | M59: =K59 -> SWBMNRANN | Q59: =IF($I59<>"",SUMIFS(DefaultAFOLU!$G:$G,DefaultAFOLU!$C:$C,MNR!$I59,DefaultAFOLU!$B:$B,MNR!Q$40),"") | R59: =-SUMIF($L$6:$L$37,$M59,R$6:R$37)*Z59 -> -0.032511014 | S59: =-SUMIF($L$6:$L$37,$M59,S$6:S$37)*AA59 -> -0.00082821578 | U59: =IF($I59<>"",SUMIFS(DefaultAFOLU!$G:$G,DefaultAFOLU!$C:$C,MNR!$I59,DefaultAFOLU!$B:$B,MNR!U$40),"") | V59: =VLOOKUP(Y59,'Calculations - livestock '!$A$27:$B$35,2,FALSE) -> 0.14726644 | Y59: Swine, breeding | Z59: =VLOOKUP($J$42,DefaultAFOLU!$D$269:$H$276,4,FALSE) -> 0.29 | AA59: =VLOOKUP($J$42,DefaultAFOLU!$D$269:$H$276,5,FALSE) -> 0.21
K60: SWBMNRNDN | M60: =K60 -> SWBMNRNDN | Q60: =IF($I60<>"",SUMIFS(DefaultAFOLU!$G:$G,DefaultAFOLU!$C:$C,MNR!$I60,DefaultAFOLU!$B:$B,MNR!Q$40),"") | R60: =-SUMIF($L$6:$L$37,$M60,R$6:R$37)*Z60 -> -0.018784141 | S60: =-SUMIF($L$6:$L$37,$M60,S$6:S$37)*AA60 -> -0.0011651171 | U60: =IF($I60<>"",SUMIFS(DefaultAFOLU!$G:$G,DefaultAFOLU!$C:$C,MNR!$I60,DefaultAFOLU!$B:$B,MNR!U$40),"") | V60: =VLOOKUP(Y60,'Calculations - livestock '!$A$27:$B$35,2,FALSE) -> 0.14726644 | Y60: Swine, breeding | Z60: =VLOOKUP($J$42,DefaultAFOLU!$D$269:$H$276,4,FALSE) -> 0.29 | AA60: =VLOOKUP($J$42,DefaultAFOLU!$D$269:$H$276,5,FALSE) -> 0.21
K61: SWBMNRNNM | M61: =K61 -> SWBMNRNNM | Q61: =IF($I61<>"",SUMIFS(DefaultAFOLU!$G:$G,DefaultAFOLU!$C:$C,MNR!$I61,DefaultAFOLU!$B:$B,MNR!Q$40),"") | R61: =-SUMIF($L$6:$L$37,$M61,R$6:R$37)*Z61 -> -0.063577094 | S61: =-SUMIF($L$6:$L$37,$M61,S$6:S$37)*AA61 -> -0.0014037556 | U61: =IF($I61<>"",SUMIFS(DefaultAFOLU!$G:$G,DefaultAFOLU!$C:$C,MNR!$I61,DefaultAFOLU!$B:$B,MNR!U$40),"") | V61: =VLOOKUP(Y61,'Calculations - livestock '!$A$27:$B$35,2,FALSE) -> 0.14726644 | Y61: Swine, breeding | Z61: =VLOOKUP($J$42,DefaultAFOLU!$D$269:$H$276,4,FALSE) -> 0.29 | AA61: =VLOOKUP($J$42,DefaultAFOLU!$D$269:$H$276,5,FALSE) -> 0.21
K62: SWBMNRADN | M62: =K62 -> SWBMNRADN | Q62: =IF($I62<>"",SUMIFS(DefaultAFOLU!$G:$G,DefaultAFOLU!$C:$C,MNR!$I62,DefaultAFOLU!$B:$B,MNR!Q$40),"") | R62: =-SUMIF($L$6:$L$37,$M62,R$6:R$37)*Z62 -> -0.0084528636 | S62: =-SUMIF($L$6:$L$37,$M62,S$6:S$37)*AA62 -> -0.0006874191 | U62: =IF($I62<>"",SUMIFS(DefaultAFOLU!$G:$G,DefaultAFOLU!$C:$C,MNR!$I62,DefaultAFOLU!$B:$B,MNR!U$40),"") | V62: =VLOOKUP(Y62,'Calculations - livestock '!$A$27:$B$35,2,FALSE) -> 0.14726644 | Y62: Swine, breeding | Z62: =VLOOKUP($J$42,DefaultAFOLU!$D$269:$H$276,4,FALSE) -> 0.29 | AA62: =VLOOKUP($J$42,DefaultAFOLU!$D$269:$H$276,5,FALSE) -> 0.21
K63: SWBMNRNDM | M63: =K63 -> SWBMNRNDM | Q63: =IF($I63<>"",SUMIFS(DefaultAFOLU!$G:$G,DefaultAFOLU!$C:$C,MNR!$I63,DefaultAFOLU!$B:$B,MNR!Q$40),"") | R63: =-SUMIF($L$6:$L$37,$M63,R$6:R$37)*Z63 -> -0.016530044 | S63: =-SUMIF($L$6:$L$37,$M63,S$6:S$37)*AA63 -> -0.0011651171 | U63: =IF($I63<>"",SUMIFS(DefaultAFOLU!$G:$G,DefaultAFOLU!$C:$C,MNR!$I63,DefaultAFOLU!$B:$B,MNR!U$40),"") | V63: =VLOOKUP(Y63,'Calculations - livestock '!$A$27:$B$35,2,FALSE) -> 0.14726644 | Y63: Swine, breeding | Z63: =VLOOKUP($J$42,DefaultAFOLU!$D$269:$H$276,4,FALSE) -> 0.29 | AA63: =VLOOKUP($J$42,DefaultAFOLU!$D$269:$H$276,5,FALSE) -> 0.21
K64: SWBMNRANM | M64: =K64 -> SWBMNRANM | Q64: =IF($I64<>"",SUMIFS(DefaultAFOLU!$G:$G,DefaultAFOLU!$C:$C,MNR!$I64,DefaultAFOLU!$B:$B,MNR!Q$40),"") | R64: =-SUMIF($L$6:$L$37,$M64,R$6:R$37)*Z64 -> -0.0038037886 | S64: =-SUMIF($L$6:$L$37,$M64,S$6:S$37)*AA64 -> -0.00082821578 | U64: =IF($I64<>"",SUMIFS(DefaultAFOLU!$G:$G,DefaultAFOLU!$C:$C,MNR!$I64,DefaultAFOLU!$B:$B,MNR!U$40),"") | V64: =VLOOKUP(Y64,'Calculations - livestock '!$A$27:$B$35,2,FALSE) -> 0.14726644 | Y64: Swine, breeding | Z64: =VLOOKUP($J$42,DefaultAFOLU!$D$269:$H$276,4,FALSE) -> 0.29 | AA64: =VLOOKUP($J$42,DefaultAFOLU!$D$269:$H$276,5,FALSE) -> 0.21
K65: SWBMNRADM | M65: =K65 -> SWBMNRADM | Q65: =IF($I65<>"",SUMIFS(DefaultAFOLU!$G:$G,DefaultAFOLU!$C:$C,MNR!$I65,DefaultAFOLU!$B:$B,MNR!Q$40),"") | R65: =-SUMIF($L$6:$L$37,$M65,R$6:R$37)*Z65 -> -0.00743852 | S65: =-SUMIF($L$6:$L$37,$M65,S$6:S$37)*AA65 -> -0.0006874191 | U65: =IF($I65<>"",SUMIFS(DefaultAFOLU!$G:$G,DefaultAFOLU!$C:$C,MNR!$I65,DefaultAFOLU!$B:$B,MNR!U$40),"") | V65: =VLOOKUP(Y65,'Calculations - livestock '!$A$27:$B$35,2,FALSE) -> 0.14726644 | Y65: Swine, breeding | Z65: =VLOOKUP($J$42,DefaultAFOLU!$D$269:$H$276,4,FALSE) -> 0.29 | AA65: =VLOOKUP($J$42,DefaultAFOLU!$D$269:$H$276,5,FALSE) -> 0.21
I66: =C45 -> AFOMNRBGASWME0 | J66: BGA | K66: {=_xlfn._xlws.FILTER($L$6:$L$37,$M$6:$M$37=MID($I$66,10,3)&"MNR")} -> SWMMNRNNN | L66: MNR | M66: =K66 -> SWMMNRNNN | N66: 1 | O66: =DefaultAFOLU!$G$21/DefaultAFOLU!$G$20 -> 57.408 | P66: 1 | Q66: =IF($I66<>"",SUMIFS(DefaultAFOLU!$G:$G,DefaultAFOLU!$C:$C,MNR!$I66,DefaultAFOLU!$B:$B,MNR!Q$40),"") -> 25 | R66: =-SUMIF($L$6:$L$37,$M66,R$6:R$37)*Z66 -> -0.117469 | S66: =-SUMIF($L$6:$L$37,$M66,S$6:S$37)*AA66 -> -0.0010510761 | U66: =IF($I66<>"",SUMIFS(DefaultAFOLU!$G:$G,DefaultAFOLU!$C:$C,MNR!$I66,DefaultAFOLU!$B:$B,MNR!U$40),"") -> 0.0001 | V66: =VLOOKUP(Y66,'Calculations - livestock '!$A$27:$B$35,2,FALSE) -> 0.14366245 | W66: =Livestock!AC34*'Input data - Other'!$F$22*O66 -> 108.39003 | Y66: Swine, market | Z66: =VLOOKUP($J$42,DefaultAFOLU!$D$269:$H$276,4,FALSE) -> 0.29 | AA66: =VLOOKUP($J$42,DefaultAFOLU!$D$269:$H$276,5,FALSE) -> 0.21
K67: SWMMNRANN | M67: =K67 -> SWMMNRANN | Q67: =IF($I67<>"",SUMIFS(DefaultAFOLU!$G:$G,DefaultAFOLU!$C:$C,MNR!$I67,DefaultAFOLU!$B:$B,MNR!Q$40),"") | R67: =-SUMIF($L$6:$L$37,$M67,R$6:R$37)*Z67 -> -0.05286105 | S67: =-SUMIF($L$6:$L$37,$M67,S$6:S$37)*AA67 -> -0.00062013492 | U67: =IF($I67<>"",SUMIFS(DefaultAFOLU!$G:$G,DefaultAFOLU!$C:$C,MNR!$I67,DefaultAFOLU!$B:$B,MNR!U$40),"") | V67: =VLOOKUP(Y67,'Calculations - livestock '!$A$27:$B$35,2,FALSE) -> 0.14366245 | Y67: Swine, market | Z67: =VLOOKUP($J$42,DefaultAFOLU!$D$269:$H$276,4,FALSE) -> 0.29 | AA67: =VLOOKUP($J$42,DefaultAFOLU!$D$269:$H$276,5,FALSE) -> 0.21
K68: SWMMNRNDN | M68: =K68 -> SWMMNRNDN | Q68: =IF($I68<>"",SUMIFS(DefaultAFOLU!$G:$G,DefaultAFOLU!$C:$C,MNR!$I68,DefaultAFOLU!$B:$B,MNR!Q$40),"") | R68: =-SUMIF($L$6:$L$37,$M68,R$6:R$37)*Z68 -> -0.03054194 | S68: =-SUMIF($L$6:$L$37,$M68,S$6:S$37)*AA68 -> -0.00087239319 | U68: =IF($I68<>"",SUMIFS(DefaultAFOLU!$G:$G,DefaultAFOLU!$C:$C,MNR!$I68,DefaultAFOLU!$B:$B,MNR!U$40),"") | V68: =VLOOKUP(Y68,'Calculations - livestock '!$A$27:$B$35,2,FALSE) -> 0.14366245 | Y68: Swine, market | Z68: =VLOOKUP($J$42,DefaultAFOLU!$D$269:$H$276,4,FALSE) -> 0.29 | AA68: =VLOOKUP($J$42,DefaultAFOLU!$D$269:$H$276,5,FALSE) -> 0.21
K69: SWMMNRNNM | M69: =K69 -> SWMMNRNNM | Q69: =IF($I69<>"",SUMIFS(DefaultAFOLU!$G:$G,DefaultAFOLU!$C:$C,MNR!$I69,DefaultAFOLU!$B:$B,MNR!Q$40),"") | R69: =-SUMIF($L$6:$L$37,$M69,R$6:R$37)*Z69 -> -0.10337272 | S69: =-SUMIF($L$6:$L$37,$M69,S$6:S$37)*AA69 -> -0.0010510761 | U69: =IF($I69<>"",SUMIFS(DefaultAFOLU!$G:$G,DefaultAFOLU!$C:$C,MNR!$I69,DefaultAFOLU!$B:$B,MNR!U$40),"") | V69: =VLOOKUP(Y69,'Calculations - livestock '!$A$27:$B$35,2,FALSE) -> 0.14366245 | Y69: Swine, market | Z69: =VLOOKUP($J$42,DefaultAFOLU!$D$269:$H$276,4,FALSE) -> 0.29 | AA69: =VLOOKUP($J$42,DefaultAFOLU!$D$269:$H$276,5,FALSE) -> 0.21
K70: SWMMNRADN | M70: =K70 -> SWMMNRADN | Q70: =IF($I70<>"",SUMIFS(DefaultAFOLU!$G:$G,DefaultAFOLU!$C:$C,MNR!$I70,DefaultAFOLU!$B:$B,MNR!Q$40),"") | R70: =-SUMIF($L$6:$L$37,$M70,R$6:R$37)*Z70 -> -0.013743873 | S70: =-SUMIF($L$6:$L$37,$M70,S$6:S$37)*AA70 -> -0.00051471198 | U70: =IF($I70<>"",SUMIFS(DefaultAFOLU!$G:$G,DefaultAFOLU!$C:$C,MNR!$I70,DefaultAFOLU!$B:$B,MNR!U$40),"") | V70: =VLOOKUP(Y70,'Calculations - livestock '!$A$27:$B$35,2,FALSE) -> 0.14366245 | Y70: Swine, market | Z70: =VLOOKUP($J$42,DefaultAFOLU!$D$269:$H$276,4,FALSE) -> 0.29 | AA70: =VLOOKUP($J$42,DefaultAFOLU!$D$269:$H$276,5,FALSE) -> 0.21
K71: SWMMNRNDM | M71: =K71 -> SWMMNRNDM | Q71: =IF($I71<>"",SUMIFS(DefaultAFOLU!$G:$G,DefaultAFOLU!$C:$C,MNR!$I71,DefaultAFOLU!$B:$B,MNR!Q$40),"") | R71: =-SUMIF($L$6:$L$37,$M71,R$6:R$37)*Z71 -> -0.026876907 | S71: =-SUMIF($L$6:$L$37,$M71,S$6:S$37)*AA71 -> -0.00087239319 | U71: =IF($I71<>"",SUMIFS(DefaultAFOLU!$G:$G,DefaultAFOLU!$C:$C,MNR!$I71,DefaultAFOLU!$B:$B,MNR!U$40),"") | V71: =VLOOKUP(Y71,'Calculations - livestock '!$A$27:$B$35,2,FALSE) -> 0.14366245 | Y71: Swine, market | Z71: =VLOOKUP($J$42,DefaultAFOLU!$D$269:$H$276,4,FALSE) -> 0.29 | AA71: =VLOOKUP($J$42,DefaultAFOLU!$D$269:$H$276,5,FALSE) -> 0.21
K72: SWMMNRANM | M72: =K72 -> SWMMNRANM | Q72: =IF($I72<>"",SUMIFS(DefaultAFOLU!$G:$G,DefaultAFOLU!$C:$C,MNR!$I72,DefaultAFOLU!$B:$B,MNR!Q$40),"") | R72: =-SUMIF($L$6:$L$37,$M72,R$6:R$37)*Z72 -> -0.0061847428 | S72: =-SUMIF($L$6:$L$37,$M72,S$6:S$37)*AA72 -> -0.00062013492 | U72: =IF($I72<>"",SUMIFS(DefaultAFOLU!$G:$G,DefaultAFOLU!$C:$C,MNR!$I72,DefaultAFOLU!$B:$B,MNR!U$40),"") | V72: =VLOOKUP(Y72,'Calculations - livestock '!$A$27:$B$35,2,FALSE) -> 0.14366245 | Y72: Swine, market | Z72: =VLOOKUP($J$42,DefaultAFOLU!$D$269:$H$276,4,FALSE) -> 0.29 | AA72: =VLOOKUP($J$42,DefaultAFOLU!$D$269:$H$276,5,FALSE) -> 0.21
K73: SWMMNRADM | M73: =K73 -> SWMMNRADM | Q73: =IF($I73<>"",SUMIFS(DefaultAFOLU!$G:$G,DefaultAFOLU!$C:$C,MNR!$I73,DefaultAFOLU!$B:$B,MNR!Q$40),"") | R73: =-SUMIF($L$6:$L$37,$M73,R$6:R$37)*Z73 -> -0.012094608 | S73: =-SUMIF($L$6:$L$37,$M73,S$6:S$37)*AA73 -> -0.00051471198 | U73: =IF($I73<>"",SUMIFS(DefaultAFOLU!$G:$G,DefaultAFOLU!$C:$C,MNR!$I73,DefaultAFOLU!$B:$B,MNR!U$40),"") | V73: =VLOOKUP(Y73,'Calculations - livestock '!$A$27:$B$35,2,FALSE) -> 0.14366245 | Y73: Swine, market | Z73: =VLOOKUP($J$42,DefaultAFOLU!$D$269:$H$276,4,FALSE) -> 0.29 | AA73: =VLOOKUP($J$42,DefaultAFOLU!$D$269:$H$276,5,FALSE) -> 0.21
B75: ~FI_Process | I75: ~FI_T
B76: Sets | C76: TechName | D76: TechDesc | E76: Tslvl | F76: Tact | G76: Tcap | I76: TechName | J76: *TechOption | K76: Comm-IN | L76: Comm-OUT | M76: CAP2ACT
B77: \I: | C77: Name | D77: Description | E77: TimeSlice | I77: \I: | J77: \I: | K77: Name | L77: Name
B78: EXP | C78: AFOMNREXP | D78: Manure Destroyer | E78: ANNUAL | F78: KtCH4 | G78: KtCH4 | I78: AFOMNREXP | J78: EXP | K78: =_xlfn.TEXTJOIN(",",TRUE,L6:L37) -> CADMNRNNN,CANMNRNNN,SWBMNRNNN,SWMMNRNNN,CADMNRANN,CANMNRANN,SWBMNRANN,SWMMNRANN,CADMNRNDN,CANMNRNDN,SWBMNRNDN,SWMMNRNDN,CADMNRNNM,CANMNRNNM,SWBMNRNNM,SWMMNRNNM,CADMNRADN,CANMNRADN,SWBMNRADN,SWMMNRADN,CADMNRNDM,CANMNRNDM,SWBMNRNDM,SWMMNRNDM,CADMNRANM,CANMNRANM,SWBMNRANM,SWMMNRANM,CADMNRADM,CANMNRADM,SWBMNRADM,SWMMNRADM | M78: 1

Sheet RemoveWhenLinked
A1: This sheet contains export processes only used when stand alone model
B3: ~FI_Process | I3: ~FI_T
B4: Sets | C4: TechName | D4: TechDesc | E4: Tslvl | F4: Tact | G4: Tcap | I4: TechName | J4: Comm-IN | K4: CAP2ACT | L4: COST
B5: \I: | C5: Name | D5: Description | E5: TimeSlice | I5: \I: | J5: Name | L5: MEUR/TJ
B6: EXP | C6: =B6&J6 -> EXPMNR | D6: Export of manure | E6: ANNUAL | F6: TJ | G6: Tja | I6: =C6 -> EXPMNR | J6: MNR | K6: 1 | L6: =0.155/1000 -> 0.000155
B7: EXP | C7: =B7&J7 -> EXPWOC | D7: Export of wood chips | E7: ANNUAL | F7: TJ | G7: Tja | I7: =C7 -> EXPWOC | J7: WOC | K7: 1 | L7: =13.754/1000 -> 0.013754
B8: EXP | C8: =B8&J8 -> EXPWOP | D8: Export of Wood pellets | E8: ANNUAL | F8: TJ | G8: Tja | I8: =C8 -> EXPWOP | J8: WOP | K8: 1 | L8: =21.229/1000 -> 0.021229
B9: EXP | C9: =B9&J9 -> EXPFIW | D9: Export of fire wood | E9: ANNUAL | F9: TJ | G9: Tja | I9: =C9 -> EXPFIW | J9: FIW | K9: 1 | L9: =L7 -> 0.013754
B10: EXP | C10: =B10&J10 -> EXPSTR | D10: Export of straw | E10: ANNUAL | F10: TJ | G10: Tja | I10: =C10 -> EXPSTR | J10: STR | K10: 1 | L10: =11.2333/1000 -> 0.0112333
B11: EXP | C11: =B11&J11 -> EXPWSA | D11: Export of agricultural waste | E11: ANNUAL | F11: TJ | G11: Tja | I11: =C11 -> EXPWSA | J11: WSA | K11: 1 | L11: =0.171/1000 -> 0.000171

Sheet InputCritical-yearless
A1: Critical data for the Agriculture sector - not available from international databases
B3: Crop area, distribution by type of production technology
C4: CER | D4: RIC | E4: LEG | F4: SEE | G4: FCR | H4: VEG | I4: WCR | J4: ROO | K4: HAG
B5: Open Field | C5: 1 | D5: 1 | E5: 1 | F5: 1 | G5: 1 | H5: 0.8 | I5: 1 | J5: 1 | K5: 1
B6: Greenhouse | C6: 0 | D6: 0 | E6: 0 | F6: 0 | G6: 0 | H6: 0 | I6: 0 | J6: 0 | K6: 0
B7: Aquaponics | C7: 0 | D7: 0 | E7: 0 | F7: 0 | G7: 0 | H7: 0 | I7: 0 | J7: 0 | K7: 0
B8: Organic | C8: 0 | D8: 0 | E8: 0 | F8: 0 | G8: 0 | H8: 0.2 | I8: 0 | J8: 0 | K8: 0
B10: Number of animals, distribution by type of production technology
C11: ASS | D11: BUF | E11: CAM | F11: CAT | G11: GOA | H11: HOR | I11: LLA | J11: MUL | K11: SHE | L11: SWI | M11: SWM | N11: POU
B12: Grass | C12: 0.5 | D12: 0.5 | E12: 0.5 | F12: 0.5 | G12: 0.5 | H12: 0.5 | I12: 0.5 | J12: 0.5 | K12: 0.5 | L12: 0.5 | M12: 0.5 | N12: 0.5
B13: Farm | C13: 0.5 | D13: 0.5 | E13: 0.5 | F13: 0.5 | G13: 0.5 | H13: 0.5 | I13: 0.5 | J13: 0.5 | K13: 0.5 | L13: 0.5 | M13: 0.5 | N13: 0.5
B15: Number of animals, distribution by type of production technology
C16: CAD | D16: CAN | E16: SWB | F16: SWM
B17: NNN | C17: 1 | D17: 1 | E17: 1 | F17: 1
B18: ANN | C18: 0 | D18: 0 | E18: 0 | F18: 0
B19: NDN | C19: 0 | D19: 0 | E19: 0 | F19: 0
B20: NNM | C20: 0 | D20: 0 | E20: 0 | F20: 0
B21: ADN | C21: 0 | D21: 0 | E21: 0 | F21: 0
B22: NDM | C22: 0 | D22: 0 | E22: 0 | F22: 0
B23: ANM | C23: 0 | D23: 0 | E23: 0 | F23: 0
B24: ADM | C24: 0 | D24: 0 | E24: 0 | F24: 0

Sheet Calc - Crops
B1: ="Crops in "&Country -> Crops in Sweden
B2: ="Area in "&Country -> Area in Sweden | C2: ="Yield factor in "&Country&" (ton/ha)" -> Yield factor in Sweden (ton/ha) | D2: Yield (ton)
A3: Item | B3: Area harvested | C3: Yield | D3: ton | E3: Category
A4: Barley | B4: =IFERROR(AVERAGEIFS('Input data - crops'!G:G,'Input data - crops'!D:D,A4,'Input data - crops'!C:C,$B$3,'Input data - crops'!B:B,Country),"") -> 274800 | C4: =IFERROR(AVERAGEIFS('Input data - crops'!$G:$G,'Input data - crops'!$D:$D,A4,'Input data - crops'!$C:$C,$C$3,'Input data - crops'!$B:$B, Country)*Settings!$Q$7,"NA") -> 0.54931 | D4: =IF(OR(B4="",B4=0),"",C4*B4) -> 150950.39 | E4: =INDEX('Lookup tables'!$B:$B,MATCH($A4,'Lookup tables'!$A:$A,0)) -> Cereals
A5: Olives | B5: =IFERROR(AVERAGEIFS('Input data - crops'!G:G,'Input data - crops'!D:D,A5,'Input data - crops'!C:C,$B$3,'Input data - crops'!B:B,Country),"") -> 0 | C5: =IFERROR(AVERAGEIFS('Input data - crops'!$G:$G,'Input data - crops'!$D:$D,A5,'Input data - crops'!$C:$C,$C$3,'Input data - crops'!$B:$B, Country)*Settings!$Q$7,"NA") -> NA | D5: =IF(OR(B5="",B5=0),"",C5*B5) | E5: =INDEX('Lookup tables'!$B:$B,MATCH($A5,'Lookup tables'!$A:$A,0)) -> Woody crops
A6: Wheat | B6: =IFERROR(AVERAGEIFS('Input data - crops'!G:G,'Input data - crops'!D:D,A6,'Input data - crops'!C:C,$B$3,'Input data - crops'!B:B,Country),"") -> 461570 | C6: =IFERROR(AVERAGEIFS('Input data - crops'!$G:$G,'Input data - crops'!$D:$D,A6,'Input data - crops'!$C:$C,$C$3,'Input data - crops'!$B:$B, Country)*Settings!$Q$7,"NA") -> 0.6995 | D6: =IF(OR(B6="",B6=0),"",C6*B6) -> 322868.22 | E6: =INDEX('Lookup tables'!$B:$B,MATCH($A6,'Lookup tables'!$A:$A,0)) -> Cereals
A7: Grapes | B7: =IFERROR(AVERAGEIFS('Input data - crops'!G:G,'Input data - crops'!D:D,A7,'Input data - crops'!C:C,$B$3,'Input data - crops'!B:B,Country),"") -> 90 | C7: =IFERROR(AVERAGEIFS('Input data - crops'!$G:$G,'Input data - crops'!$D:$D,A7,'Input data - crops'!$C:$C,$C$3,'Input data - crops'!$B:$B, Country)*Settings!$Q$7,"NA") -> 0.15556 | D7: =IF(OR(B7="",B7=0),"",C7*B7) -> 14.0004 | E7: =INDEX('Lookup tables'!$B:$B,MATCH($A7,'Lookup tables'!$A:$A,0)) -> Woody crops
A8: Almonds, in shell | B8: =IFERROR(AVERAGEIFS('Input data - crops'!G:G,'Input data - crops'!D:D,A8,'Input data - crops'!C:C,$B$3,'Input data - crops'!B:B,Country),"") -> 0 | C8: =IFERROR(AVERAGEIFS('Input data - crops'!$G:$G,'Input data - crops'!$D:$D,A8,'Input data - crops'!$C:$C,$C$3,'Input data - crops'!$B:$B, Country)*Settings!$Q$7,"NA") -> NA | D8: =IF(OR(B8="",B8=0),"",C8*B8) | E8: =INDEX('Lookup tables'!$B:$B,MATCH($A8,'Lookup tables'!$A:$A,0)) -> Woody crops
A9: Sunflower seed | B9: =IFERROR(AVERAGEIFS('Input data - crops'!G:G,'Input data - crops'!D:D,A9,'Input data - crops'!C:C,$B$3,'Input data - crops'!B:B,Country),"") | C9: =IFERROR(AVERAGEIFS('Input data - crops'!$G:$G,'Input data - crops'!$D:$D,A9,'Input data - crops'!$C:$C,$C$3,'Input data - crops'!$B:$B, Country)*Settings!$Q$7,"NA") -> NA | D9: =IF(OR(B9="",B9=0),"",C9*B9) | E9: =INDEX('Lookup tables'!$B:$B,MATCH($A9,'Lookup tables'!$A:$A,0)) -> Seeds
A10: Oats | B10: =IFERROR(AVERAGEIFS('Input data - crops'!G:G,'Input data - crops'!D:D,A10,'Input data - crops'!C:C,$B$3,'Input data - crops'!B:B,Country),"") -> 153760 | C10: =IFERROR(AVERAGEIFS('Input data - crops'!$G:$G,'Input data - crops'!$D:$D,A10,'Input data - crops'!$C:$C,$C$3,'Input data - crops'!$B:$B, Country)*Settings!$Q$7,"NA") -> 0.47789 | D10: =IF(OR(B10="",B10=0),"",C10*B10) -> 73480.366 | E10: =INDEX('Lookup tables'!$B:$B,MATCH($A10,'Lookup tables'!$A:$A,0)) -> Cereals
A11: Maize (corn) | B11: =IFERROR(AVERAGEIFS('Input data - crops'!G:G,'Input data - crops'!D:D,A11,'Input data - crops'!C:C,$B$3,'Input data - crops'!B:B,Country),"") -> 1770 | C11: =IFERROR(AVERAGEIFS('Input data - crops'!$G:$G,'Input data - crops'!$D:$D,A11,'Input data - crops'!$C:$C,$C$3,'Input data - crops'!$B:$B, Country)*Settings!$Q$7,"NA") -> 0.68927 | D11: =IF(OR(B11="",B11=0),"",C11*B11) -> 1220.0079 | E11: =INDEX('Lookup tables'!$B:$B,MATCH($A11,'Lookup tables'!$A:$A,0)) -> Cereals
A12: Other pulses n.e.c. | B12: =IFERROR(AVERAGEIFS('Input data - crops'!G:G,'Input data - crops'!D:D,A12,'Input data - crops'!C:C,$B$3,'Input data - crops'!B:B,Country),"") -> 490 | C12: =IFERROR(AVERAGEIFS('Input data - crops'!$G:$G,'Input data - crops'!$D:$D,A12,'Input data - crops'!$C:$C,$C$3,'Input data - crops'!$B:$B, Country)*Settings!$Q$7,"NA") -> 0.18776 | D12: =IF(OR(B12="",B12=0),"",C12*B12) -> 92.0024 | E12: =INDEX('Lookup tables'!$B:$B,MATCH($A12,'Lookup tables'!$A:$A,0)) -> Legumes
A13: Triticale | B13: =IFERROR(AVERAGEIFS('Input data - crops'!G:G,'Input data - crops'!D:D,A13,'Input data - crops'!C:C,$B$3,'Input data - crops'!B:B,Country),"") -> 28640 | C13: =IFERROR(AVERAGEIFS('Input data - crops'!$G:$G,'Input data - crops'!$D:$D,A13,'Input data - crops'!$C:$C,$C$3,'Input data - crops'!$B:$B, Country)*Settings!$Q$7,"NA") -> 0.56739 | D13: =IF(OR(B13="",B13=0),"",C13*B13) -> 16250.05 | E13: =INDEX('Lookup tables'!$B:$B,MATCH($A13,'Lookup tables'!$A:$A,0)) -> Cereals
A14: Oranges | B14: =IFERROR(AVERAGEIFS('Input data - crops'!G:G,'Input data - crops'!D:D,A14,'Input data - crops'!C:C,$B$3,'Input data - crops'!B:B,Country),"") -> 0 | C14: =IFERROR(AVERAGEIFS('Input data - crops'!$G:$G,'Input data - crops'!$D:$D,A14,'Input data - crops'!$C:$C,$C$3,'Input data - crops'!$B:$B, Country)*Settings!$Q$7,"NA") -> NA | D14: =IF(OR(B14="",B14=0),"",C14*B14) | E14: =INDEX('Lookup tables'!$B:$B,MATCH($A14,'Lookup tables'!$A:$A,0)) -> Woody crops
A15: Rye | B15: =IFERROR(AVERAGEIFS('Input data - crops'!G:G,'Input data - crops'!D:D,A15,'Input data - crops'!C:C,$B$3,'Input data - crops'!B:B,Country),"") -> 20760 | C15: =IFERROR(AVERAGEIFS('Input data - crops'!$G:$G,'Input data - crops'!$D:$D,A15,'Input data - crops'!$C:$C,$C$3,'Input data - crops'!$B:$B, Country)*Settings!$Q$7,"NA") -> 0.62235 | D15: =IF(OR(B15="",B15=0),"",C15*B15) -> 12919.986 | E15: =INDEX('Lookup tables'!$B:$B,MATCH($A15,'Lookup tables'!$A:$A,0)) -> Cereals
